{"name":"Italy","nameZh":"意大利","iso":"IT","confederation":"UEFA","confederationZh":"欧足联","totalStats":{"p":83,"w":46,"d":17,"l":20,"gf":128,"ga":77,"yellow":92,"red":6,"gd":51,"winRate":55.4},"topPlayers":[{"name":"Roberto Baggio","apps":16,"goals":9,"starts":13,"birthDate":"1967-02-18","age":59},{"name":"Paolo Rossi","apps":14,"goals":9,"starts":14,"birthDate":"1956-09-23","age":69},{"name":"Christian Vieri","apps":9,"goals":9,"starts":9,"birthDate":"1973-07-12","age":52},{"name":"Salvatore Schillaci","apps":7,"goals":6,"starts":5,"birthDate":"1964-12-01","age":61},{"name":"Alessandro Altobelli","apps":7,"goals":5,"starts":4,"birthDate":"1955-11-28","age":70},{"name":"Silvio Piola","apps":0,"goals":5,"starts":0,"birthDate":"1913-09-29"},{"name":"Angelo Schiavio","apps":0,"goals":4,"starts":0,"birthDate":"1905-10-15"},{"name":"Gino Colaussi","apps":0,"goals":4,"starts":0,"birthDate":"1914-03-04"},{"name":"Gigi Riva","apps":8,"goals":3,"starts":8,"birthDate":"1944-11-07","age":81},{"name":"Gianni Rivera","apps":6,"goals":3,"starts":2,"birthDate":"1943-08-18","age":82},{"name":"Raimundo Orsi","apps":0,"goals":3,"starts":0,"birthDate":"1901-12-02"},{"name":"Giuseppe Meazza","apps":0,"goals":3,"starts":0,"birthDate":"1910-08-23"},{"name":"Marco Tardelli","apps":13,"goals":2,"starts":13,"birthDate":"1954-09-24","age":71},{"name":"Dino Baggio","apps":12,"goals":2,"starts":11,"birthDate":"1971-07-24","age":54},{"name":"Alessandro Del Piero","apps":12,"goals":2,"starts":5,"birthDate":"1974-11-09","age":51}],"tournaments":[{"year":2014,"stage":"小组赛","manager":"Cesare Prandelli","cards":{"yellow":3,"red":1},"group":{"name":"Group D","standings":[{"pos":1,"team":"哥斯达黎加","p":3,"w":2,"d":1,"l":0,"gf":4,"ga":1,"pts":7},{"pos":2,"team":"乌拉圭","p":3,"w":2,"d":0,"l":1,"gf":4,"ga":4,"pts":6},{"pos":3,"team":"意大利","p":3,"w":1,"d":0,"l":2,"gf":2,"ga":3,"pts":3},{"pos":4,"team":"英格兰","p":3,"w":0,"d":1,"l":2,"gf":2,"ga":4,"pts":1}]},"matches":[{"stage":"group stage","home":"英格兰","away":"意大利","homeScore":1,"awayScore":2,"extra":false,"pens":false,"penScore":"","goals":[{"player":"Claudio Marchisio","team":"意大利","minute":"35'","penalty":false,"ownGoal":false},{"player":"Daniel Sturridge","team":"英格兰","minute":"37'","penalty":false,"ownGoal":false},{"player":"Mario Balotelli","team":"意大利","minute":"50'","penalty":false,"ownGoal":false}],"venue":{"stadium":"Arena da Amazônia","city":"Manaus","capacity":41000},"subs":[{"playerOff":"Danny Welbeck","playerOn":"Ross Barkley","minute":"61'"},{"playerOff":"Jordan Henderson","playerOn":"Jack Wilshere","minute":"73'"},{"playerOff":"Daniel Sturridge","playerOn":"Adam Lallana","minute":"80'"},{"playerOff":"Marco Verratti","playerOn":"Thiago Motta","minute":"57'"},{"playerOff":"Mario Balotelli","playerOn":"Ciro Immobile","minute":"73'"},{"playerOff":"Antonio Candreva","playerOn":"Marco Parolo","minute":"79'"}]},{"stage":"group stage","home":"意大利","away":"哥斯达黎加","homeScore":0,"awayScore":1,"extra":false,"pens":false,"penScore":"","goals":[{"player":"Bryan Ruiz","team":"哥斯达黎加","minute":"44'","penalty":false,"ownGoal":false}],"venue":{"stadium":"Arena Pernambuco","city":"Recife","capacity":43000},"subs":[{"playerOff":"Thiago Motta","playerOn":"Antonio Cassano","minute":"46'"},{"playerOff":"Antonio Candreva","playerOn":"Lorenzo Insigne","minute":"57'"},{"playerOff":"Claudio Marchisio","playerOn":"Alessio Cerci","minute":"69'"},{"playerOff":"Yeltsin Tejeda","playerOn":"José Miguel Cubero","minute":"68'"},{"playerOff":"Joel Campbell","playerOn":"Marco Ureña","minute":"74'"},{"playerOff":"Bryan Ruiz","playerOn":"Randall Brenes","minute":"81'"}]},{"stage":"group stage","home":"意大利","away":"乌拉圭","homeScore":0,"awayScore":1,"extra":false,"pens":false,"penScore":"","goals":[{"player":"Diego Godín","team":"乌拉圭","minute":"81'","penalty":false,"ownGoal":false}],"venue":{"stadium":"Arena das Dunas","city":"Natal","capacity":40000},"subs":[{"playerOff":"Mario Balotelli","playerOn":"Marco Parolo","minute":"46'"},{"playerOff":"Ciro Immobile","playerOn":"Antonio Cassano","minute":"71'"},{"playerOff":"Marco Verratti","playerOn":"Thiago Motta","minute":"75'"},{"playerOff":"Nicolás Lodeiro","playerOn":"Maxi Pereira","minute":"46'"},{"playerOff":"Álvaro Pereira","playerOn":"Cristhian Stuani","minute":"63'"},{"playerOff":"Cristian Rodríguez","playerOn":"Gastón Ramírez","minute":"78'"}]}],"squad":[{"name":"Gianluigi Buffon","pos":"GK","num":1,"birthDate":"1978-01-28","age":48},{"name":"Mattia De Sciglio","pos":"DF","num":2,"birthDate":"1992-10-20","age":33},{"name":"Giorgio Chiellini","pos":"DF","num":3,"birthDate":"1984-08-14","age":41},{"name":"Matteo Darmian","pos":"DF","num":4,"birthDate":"1989-12-02","age":36},{"name":"Thiago Motta","pos":"MF","num":5,"birthDate":"1982-08-28","age":43},{"name":"Antonio Candreva","pos":"MF","num":6,"birthDate":"1987-02-28","age":39},{"name":"Ignazio Abate","pos":"DF","num":7,"birthDate":"1986-11-12","age":39},{"name":"Claudio Marchisio","pos":"MF","num":8,"birthDate":"1986-01-19","age":40},{"name":"Mario Balotelli","pos":"FW","num":9,"birthDate":"1990-08-12","age":35},{"name":"Antonio Cassano","pos":"FW","num":10,"birthDate":"1982-07-12","age":43},{"name":"Alessio Cerci","pos":"FW","num":11,"birthDate":"1987-07-23","age":38},{"name":"Salvatore Sirigu","pos":"GK","num":12,"birthDate":"1987-01-12","age":39},{"name":"Mattia Perin","pos":"GK","num":13,"birthDate":"1992-11-10","age":33},{"name":"Alberto Aquilani","pos":"MF","num":14,"birthDate":"1984-07-07","age":41},{"name":"Andrea Barzagli","pos":"DF","num":15,"birthDate":"1981-05-08","age":45},{"name":"Daniele De Rossi","pos":"MF","num":16,"birthDate":"1983-07-24","age":42},{"name":"Ciro Immobile","pos":"FW","num":17,"birthDate":"1990-02-20","age":36},{"name":"Marco Parolo","pos":"MF","num":18,"birthDate":"1985-01-25","age":41},{"name":"Leonardo Bonucci","pos":"DF","num":19,"birthDate":"1987-05-01","age":39},{"name":"Gabriel Paletta","pos":"DF","num":20,"birthDate":"1986-02-15","age":40},{"name":"Andrea Pirlo","pos":"MF","num":21,"birthDate":"1979-05-19","age":47},{"name":"Lorenzo Insigne","pos":"FW","num":22,"birthDate":"1991-06-04","age":35},{"name":"Marco Verratti","pos":"MF","num":23,"birthDate":"1992-11-05","age":33}]},{"year":2010,"stage":"小组赛","manager":"Marcello Lippi","cards":{"yellow":5,"red":0},"group":{"name":"Group F","standings":[{"pos":1,"team":"巴拉圭","p":3,"w":1,"d":2,"l":0,"gf":3,"ga":1,"pts":5},{"pos":2,"team":"斯洛伐克","p":3,"w":1,"d":1,"l":1,"gf":4,"ga":5,"pts":4},{"pos":3,"team":"新西兰","p":3,"w":0,"d":3,"l":0,"gf":2,"ga":2,"pts":3},{"pos":4,"team":"意大利","p":3,"w":0,"d":2,"l":1,"gf":4,"ga":5,"pts":2}]},"matches":[{"stage":"group stage","home":"意大利","away":"巴拉圭","homeScore":1,"awayScore":1,"extra":false,"pens":false,"penScore":"","goals":[{"player":"Antolín Alcaraz","team":"巴拉圭","minute":"39'","penalty":false,"ownGoal":false},{"player":"Daniele De Rossi","team":"意大利","minute":"63'","penalty":false,"ownGoal":false}],"venue":{"stadium":"Cape Town Stadium","city":"Cape Town","capacity":64000},"subs":[{"playerOff":"Gianluigi Buffon","playerOn":"Federico Marchetti","minute":"46'"},{"playerOff":"Claudio Marchisio","playerOn":"Mauro Camoranesi","minute":"59'"},{"playerOff":"Alberto Gilardino","playerOn":"Antonio Di Natale","minute":"72'"},{"playerOff":"Aureliano Torres","playerOn":"Jonathan Santana","minute":"60'"},{"playerOff":"Nelson Valdez","playerOn":"Roque Santa Cruz","minute":"68'"},{"playerOff":"Lucas Barrios","playerOn":"Óscar Cardozo","minute":"76'"}]},{"stage":"group stage","home":"意大利","away":"新西兰","homeScore":1,"awayScore":1,"extra":false,"pens":false,"penScore":"","goals":[{"player":"Shane Smeltz","team":"新西兰","minute":"7'","penalty":false,"ownGoal":false},{"player":"Vincenzo Iaquinta","team":"意大利","minute":"29'","penalty":true,"ownGoal":false}],"venue":{"stadium":"Mbombela Stadium","city":"Nelspruit","capacity":41000},"subs":[{"playerOff":"Simone Pepe","playerOn":"Mauro Camoranesi","minute":"46'"},{"playerOff":"Alberto Gilardino","playerOn":"Antonio Di Natale","minute":"46'"},{"playerOff":"Claudio Marchisio","playerOn":"Giampaolo Pazzini","minute":"61'"},{"playerOff":"Rory Fallon","playerOn":"Chris Wood","minute":"63'"},{"playerOff":"Ivan Vicelich","playerOn":"Jeremy Christie","minute":"81'"},{"playerOff":"Chris Killen","playerOn":"Andy Barron","minute":"90'+3'"}]},{"stage":"group stage","home":"斯洛伐克","away":"意大利","homeScore":3,"awayScore":2,"extra":false,"pens":false,"penScore":"","goals":[{"player":"Róbert Vittek","team":"斯洛伐克","minute":"25'","penalty":false,"ownGoal":false},{"player":"Róbert Vittek","team":"斯洛伐克","minute":"73'","penalty":false,"ownGoal":false},{"player":"Antonio Di Natale","team":"意大利","minute":"81'","penalty":false,"ownGoal":false},{"player":"Kamil Kopúnek","team":"斯洛伐克","minute":"89'","penalty":false,"ownGoal":false},{"player":"Fabio Quagliarella","team":"意大利","minute":"90'+2'","penalty":false,"ownGoal":false}],"venue":{"stadium":"Ellis Park Stadium","city":"Johannesburg","capacity":56000},"subs":[{"playerOff":"Zdeno Štrba","playerOn":"Kamil Kopúnek","minute":"87'"},{"playerOff":"Róbert Vittek","playerOn":"Stanislav Šesták","minute":"90'+2'"},{"playerOff":"Erik Jendrišek","playerOn":"Martin Petráš","minute":"90'+4'"},{"playerOff":"Domenico Criscito","playerOn":"Christian Maggio","minute":"46'"},{"playerOff":"Gennaro Gattuso","playerOn":"Fabio Quagliarella","minute":"46'"},{"playerOff":"Riccardo Montolivo","playerOn":"Andrea Pirlo","minute":"56'"}]}],"squad":[{"name":"Gianluigi Buffon","pos":"GK","num":1,"birthDate":"1978-01-28","age":48},{"name":"Christian Maggio","pos":"DF","num":2,"birthDate":"1982-02-11","age":44},{"name":"Domenico Criscito","pos":"DF","num":3,"birthDate":"1986-12-30","age":39},{"name":"Giorgio Chiellini","pos":"DF","num":4,"birthDate":"1984-08-14","age":41},{"name":"Fabio Cannavaro","pos":"DF","num":5,"birthDate":"1973-09-13","age":52},{"name":"Daniele De Rossi","pos":"MF","num":6,"birthDate":"1983-07-24","age":42},{"name":"Simone Pepe","pos":"MF","num":7,"birthDate":"1983-08-30","age":42},{"name":"Gennaro Gattuso","pos":"MF","num":8,"birthDate":"1978-01-09","age":48},{"name":"Vincenzo Iaquinta","pos":"FW","num":9,"birthDate":"1979-11-21","age":46},{"name":"Antonio Di Natale","pos":"FW","num":10,"birthDate":"1977-10-13","age":48},{"name":"Alberto Gilardino","pos":"FW","num":11,"birthDate":"1982-07-05","age":43},{"name":"Federico Marchetti","pos":"GK","num":12,"birthDate":"1983-02-07","age":43},{"name":"Salvatore Bocchetti","pos":"DF","num":13,"birthDate":"1986-11-30","age":39},{"name":"Morgan De Sanctis","pos":"GK","num":14,"birthDate":"1977-03-26","age":49},{"name":"Claudio Marchisio","pos":"MF","num":15,"birthDate":"1986-01-19","age":40},{"name":"Mauro Camoranesi","pos":"MF","num":16,"birthDate":"1976-10-04","age":49},{"name":"Angelo Palombo","pos":"MF","num":17,"birthDate":"1981-09-25","age":44},{"name":"Fabio Quagliarella","pos":"FW","num":18,"birthDate":"1983-01-31","age":43},{"name":"Gianluca Zambrotta","pos":"DF","num":19,"birthDate":"1977-02-19","age":49},{"name":"Giampaolo Pazzini","pos":"FW","num":20,"birthDate":"1984-08-02","age":41},{"name":"Andrea Pirlo","pos":"MF","num":21,"birthDate":"1979-05-19","age":47},{"name":"Riccardo Montolivo","pos":"MF","num":22,"birthDate":"1985-01-18","age":41},{"name":"Leonardo Bonucci","pos":"DF","num":23,"birthDate":"1987-05-01","age":39}]},{"year":2006,"stage":"冠军","manager":"Marcello Lippi","cards":{"yellow":11,"red":2},"group":{"name":"Group E","standings":[{"pos":1,"team":"意大利","p":3,"w":2,"d":1,"l":0,"gf":5,"ga":1,"pts":7},{"pos":2,"team":"加纳","p":3,"w":2,"d":0,"l":1,"gf":4,"ga":3,"pts":6},{"pos":3,"team":"捷克","p":3,"w":1,"d":0,"l":2,"gf":3,"ga":4,"pts":3},{"pos":4,"team":"美国","p":3,"w":0,"d":1,"l":2,"gf":2,"ga":6,"pts":1}]},"matches":[{"stage":"group stage","home":"意大利","away":"加纳","homeScore":2,"awayScore":0,"extra":false,"pens":false,"penScore":"","goals":[{"player":"Andrea Pirlo","team":"意大利","minute":"40'","penalty":false,"ownGoal":false},{"player":"Vincenzo Iaquinta","team":"意大利","minute":"83'","penalty":false,"ownGoal":false}],"venue":{"stadium":"Niedersachsenstadion","city":"Hanover","capacity":60000},"subs":[{"playerOff":"Francesco Totti","playerOn":"Mauro Camoranesi","minute":"56'"},{"playerOff":"Alberto Gilardino","playerOn":"Vincenzo Iaquinta","minute":"64'"},{"playerOff":"Luca Toni","playerOn":"Alessandro Del Piero","minute":"82'"},{"playerOff":"Emmanuel Pappoe","playerOn":"Illiasu Shilla","minute":"46'"},{"playerOff":"Matthew Amoah","playerOn":"Razak Pimpong","minute":"68'"},{"playerOff":"Asamoah Gyan","playerOn":"Alex Tachie-Mensah","minute":"89'"}]},{"stage":"group stage","home":"意大利","away":"美国","homeScore":1,"awayScore":1,"extra":false,"pens":false,"penScore":"","goals":[{"player":"Alberto Gilardino","team":"意大利","minute":"22'","penalty":false,"ownGoal":false},{"player":"Cristian Zaccardo","team":"美国","minute":"27'","penalty":false,"ownGoal":true}],"venue":{"stadium":"Fritz-Walter-Stadion","city":"Kaiserslautern","capacity":46000},"subs":[{"playerOff":"Francesco Totti","playerOn":"Gennaro Gattuso","minute":"35'"},{"playerOff":"Cristian Zaccardo","playerOn":"Alessandro Del Piero","minute":"54'"},{"playerOff":"Luca Toni","playerOn":"Vincenzo Iaquinta","minute":"61'"},{"playerOff":"Bobby Convey","playerOn":"Jimmy Conrad","minute":"52'"},{"playerOff":"Clint Dempsey","playerOn":"DaMarcus Beasley","minute":"62'"}]},{"stage":"group stage","home":"捷克","away":"意大利","homeScore":0,"awayScore":2,"extra":false,"pens":false,"penScore":"","goals":[{"player":"Marco Materazzi","team":"意大利","minute":"26'","penalty":false,"ownGoal":false},{"player":"Filippo Inzaghi","team":"意大利","minute":"87'","penalty":false,"ownGoal":false}],"venue":{"stadium":"Volksparkstadion","city":"Hamburg","capacity":61000},"subs":[{"playerOff":"Karel Poborský","playerOn":"Jiří Štajner","minute":"46'"},{"playerOff":"Milan Baroš","playerOn":"David Jarolím","minute":"64'"},{"playerOff":"Radoslav Kováč","playerOn":"Marek Heinz","minute":"78'"},{"playerOff":"Alessandro Nesta","playerOn":"Marco Materazzi","minute":"17'"},{"playerOff":"Alberto Gilardino","playerOn":"Filippo Inzaghi","minute":"60'"},{"playerOff":"Mauro Camoranesi","playerOn":"Simone Barone","minute":"74'"}]},{"stage":"round of 16","home":"意大利","away":"澳大利亚","homeScore":1,"awayScore":0,"extra":false,"pens":false,"penScore":"","goals":[{"player":"Francesco Totti","team":"意大利","minute":"90'+5'","penalty":true,"ownGoal":false}],"venue":{"stadium":"Fritz-Walter-Stadion","city":"Kaiserslautern","capacity":46000},"subs":[{"playerOff":"Alberto Gilardino","playerOn":"Vincenzo Iaquinta","minute":"46'"},{"playerOff":"Luca Toni","playerOn":"Andrea Barzagli","minute":"56'"},{"playerOff":"Alessandro Del Piero","playerOn":"Francesco Totti","minute":"75'"},{"playerOff":"Mile Sterjovski","playerOn":"John Aloisi","minute":"81'"}]},{"stage":"quarter-finals","home":"意大利","away":"乌克兰","homeScore":3,"awayScore":0,"extra":false,"pens":false,"penScore":"","goals":[{"player":"Gianluca Zambrotta","team":"意大利","minute":"6'","penalty":false,"ownGoal":false},{"player":"Luca Toni","team":"意大利","minute":"59'","penalty":false,"ownGoal":false},{"player":"Luca Toni","team":"意大利","minute":"69'","penalty":false,"ownGoal":false}],"venue":{"stadium":"Volksparkstadion","city":"Hamburg","capacity":61000},"subs":[{"playerOff":"Mauro Camoranesi","playerOn":"Simone Barone","minute":"68'"},{"playerOff":"Andrea Pirlo","playerOn":"Massimo Oddo","minute":"68'"},{"playerOff":"Gennaro Gattuso","playerOn":"Cristian Zaccardo","minute":"77'"},{"playerOff":"Vyacheslav Sviderskyi","playerOn":"Andriy Vorobey","minute":"20'"},{"playerOff":"Andriy Rusol","playerOn":"Vladyslav Vashchuk","minute":"45'+2'"},{"playerOff":"Artem Milevskyi","playerOn":"Oleksiy Byelik","minute":"72'"}]},{"stage":"semi-finals","home":"德国","away":"意大利","homeScore":0,"awayScore":2,"extra":true,"pens":false,"penScore":"","goals":[{"player":"Fabio Grosso","team":"意大利","minute":"119'","penalty":false,"ownGoal":false},{"player":"Alessandro Del Piero","team":"意大利","minute":"120'+1'","penalty":false,"ownGoal":false}],"venue":{"stadium":"Westfalenstadion","city":"Dortmund","capacity":65000},"subs":[{"playerOff":"Tim Borowski","playerOn":"Bastian Schweinsteiger","minute":"73'"},{"playerOff":"Bernd Schneider","playerOn":"David Odonkor","minute":"83'"},{"playerOff":"Miroslav Klose","playerOn":"Oliver Neuville","minute":"111'"},{"playerOff":"Luca Toni","playerOn":"Alberto Gilardino","minute":"74'"},{"playerOff":"Mauro Camoranesi","playerOn":"Vincenzo Iaquinta","minute":"91'"},{"playerOff":"Simone Perrotta","playerOn":"Alessandro Del Piero","minute":"104'"}]},{"stage":"final","home":"意大利","away":"法国","homeScore":1,"awayScore":1,"extra":true,"pens":true,"penScore":"5-3","goals":[{"player":"Zinedine Zidane","team":"法国","minute":"7'","penalty":true,"ownGoal":false},{"player":"Marco Materazzi","team":"意大利","minute":"19'","penalty":false,"ownGoal":false}],"venue":{"stadium":"Olympiastadion","city":"Berlin","capacity":86000},"subs":[{"playerOff":"Simone Perrotta","playerOn":"Daniele De Rossi","minute":"61'"},{"playerOff":"Francesco Totti","playerOn":"Vincenzo Iaquinta","minute":"61'"},{"playerOff":"Mauro Camoranesi","playerOn":"Alessandro Del Piero","minute":"86'"},{"playerOff":"Patrick Vieira","playerOn":"Alou Diarra","minute":"56'"},{"playerOff":"Franck Ribéry","playerOn":"David Trezeguet","minute":"100'"},{"playerOff":"Thierry Henry","playerOn":"Sylvain Wiltord","minute":"107'"}]}],"squad":[{"name":"Gianluigi Buffon","pos":"GK","num":1,"birthDate":"1978-01-28","age":48},{"name":"Cristian Zaccardo","pos":"DF","num":2,"birthDate":"1981-12-21","age":44},{"name":"Fabio Grosso","pos":"DF","num":3,"birthDate":"1977-11-28","age":48},{"name":"Daniele De Rossi","pos":"MF","num":4,"birthDate":"1983-07-24","age":42},{"name":"Fabio Cannavaro","pos":"DF","num":5,"birthDate":"1973-09-13","age":52},{"name":"Andrea Barzagli","pos":"DF","num":6,"birthDate":"1981-05-08","age":45},{"name":"Alessandro Del Piero","pos":"FW","num":7,"birthDate":"1974-11-09","age":51},{"name":"Gennaro Gattuso","pos":"MF","num":8,"birthDate":"1978-01-09","age":48},{"name":"Luca Toni","pos":"FW","num":9,"birthDate":"1977-05-26","age":49},{"name":"Francesco Totti","pos":"FW","num":10,"birthDate":"1976-09-27","age":49},{"name":"Alberto Gilardino","pos":"FW","num":11,"birthDate":"1982-07-05","age":43},{"name":"Angelo Peruzzi","pos":"GK","num":12,"birthDate":"1970-02-16","age":56},{"name":"Alessandro Nesta","pos":"DF","num":13,"birthDate":"1976-03-19","age":50},{"name":"Marco Amelia","pos":"GK","num":14,"birthDate":"1982-04-02","age":44},{"name":"Vincenzo Iaquinta","pos":"FW","num":15,"birthDate":"1979-11-21","age":46},{"name":"Mauro Camoranesi","pos":"MF","num":16,"birthDate":"1976-10-04","age":49},{"name":"Simone Barone","pos":"MF","num":17,"birthDate":"1978-04-30","age":48},{"name":"Filippo Inzaghi","pos":"FW","num":18,"birthDate":"1973-08-09","age":52},{"name":"Gianluca Zambrotta","pos":"DF","num":19,"birthDate":"1977-02-19","age":49},{"name":"Simone Perrotta","pos":"MF","num":20,"birthDate":"1977-09-17","age":48},{"name":"Andrea Pirlo","pos":"MF","num":21,"birthDate":"1979-05-19","age":47},{"name":"Massimo Oddo","pos":"DF","num":22,"birthDate":"1976-06-14","age":49},{"name":"Marco Materazzi","pos":"DF","num":23,"birthDate":"1973-08-19","age":52}]},{"year":2002,"stage":"十六强","manager":"Giovanni Trapattoni","cards":{"yellow":11,"red":1},"group":{"name":"Group G","standings":[{"pos":1,"team":"墨西哥","p":3,"w":2,"d":1,"l":0,"gf":4,"ga":2,"pts":7},{"pos":2,"team":"意大利","p":3,"w":1,"d":1,"l":1,"gf":4,"ga":3,"pts":4},{"pos":3,"team":"克罗地亚","p":3,"w":1,"d":0,"l":2,"gf":2,"ga":3,"pts":3},{"pos":4,"team":"厄瓜多尔","p":3,"w":1,"d":0,"l":2,"gf":2,"ga":4,"pts":3}]},"matches":[{"stage":"group stage","home":"意大利","away":"厄瓜多尔","homeScore":2,"awayScore":0,"extra":false,"pens":false,"penScore":"","goals":[{"player":"Christian Vieri","team":"意大利","minute":"7'","penalty":false,"ownGoal":false},{"player":"Christian Vieri","team":"意大利","minute":"27'","penalty":false,"ownGoal":false}],"venue":{"stadium":"Sapporo Dome","city":"Sapporo","capacity":42000},"subs":[{"playerOff":"Cristiano Doni","playerOn":"Angelo Di Livio","minute":"64'"},{"playerOff":"Luigi Di Biagio","playerOn":"Gennaro Gattuso","minute":"69'"},{"playerOff":"Francesco Totti","playerOn":"Alessandro Del Piero","minute":"74'"},{"playerOff":"Álex Aguinaga","playerOn":"Carlos Tenorio","minute":"46'"},{"playerOff":"Edwin Tenorio","playerOn":"Marlon Ayoví","minute":"59'"},{"playerOff":"Cléber Chalá","playerOn":"Nicolás Asencio","minute":"85'"}]},{"stage":"group stage","home":"意大利","away":"克罗地亚","homeScore":1,"awayScore":2,"extra":false,"pens":false,"penScore":"","goals":[{"player":"Christian Vieri","team":"意大利","minute":"55'","penalty":false,"ownGoal":false},{"player":"Ivica Olić","team":"克罗地亚","minute":"73'","penalty":false,"ownGoal":false},{"player":"Milan Rapaić","team":"克罗地亚","minute":"76'","penalty":false,"ownGoal":false}],"venue":{"stadium":"Kashima Stadium","city":"Ibaraki","capacity":42000},"subs":[{"playerOff":"Alessandro Nesta","playerOn":"Marco Materazzi","minute":"24'"},{"playerOff":"Cristiano Doni","playerOn":"Filippo Inzaghi","minute":"79'"},{"playerOff":"Davor Vugrinec","playerOn":"Ivica Olić","minute":"57'"},{"playerOff":"Zvonimir Soldo","playerOn":"Jurica Vranješ","minute":"62'"},{"playerOff":"Milan Rapaić","playerOn":"Dario Šimić","minute":"79'"}]},{"stage":"group stage","home":"墨西哥","away":"意大利","homeScore":1,"awayScore":1,"extra":false,"pens":false,"penScore":"","goals":[{"player":"Jared Borgetti","team":"墨西哥","minute":"34'","penalty":false,"ownGoal":false},{"player":"Alessandro Del Piero","team":"意大利","minute":"85'","penalty":false,"ownGoal":false}],"venue":{"stadium":"Ōita Stadium","city":"Ōita","capacity":43000},"subs":[{"playerOff":"Johan Rodríguez","playerOn":"Rafael García","minute":"76'"},{"playerOff":"Ramón Morales","playerOn":"Gabriel Caballero","minute":"76'"},{"playerOff":"Jared Borgetti","playerOn":"Francisco Palencia","minute":"80'"},{"playerOff":"Filippo Inzaghi","playerOn":"Vincenzo Montella","minute":"55'"},{"playerOff":"Christian Panucci","playerOn":"Francesco Coco","minute":"63'"},{"playerOff":"Francesco Totti","playerOn":"Alessandro Del Piero","minute":"78'"}]},{"stage":"round of 16","home":"韩国","away":"意大利","homeScore":2,"awayScore":1,"extra":true,"pens":false,"penScore":"","goals":[{"player":"Christian Vieri","team":"意大利","minute":"18'","penalty":false,"ownGoal":false},{"player":"Ki-hyeon Seol","team":"韩国","minute":"88'","penalty":false,"ownGoal":false},{"player":"Jung-hwan Ahn","team":"韩国","minute":"117'","penalty":false,"ownGoal":false}],"venue":{"stadium":"Daejeon World Cup Stadium","city":"Daejeon","capacity":40000},"subs":[{"playerOff":"Tae-young Kim","playerOn":"Sun-hong Hwang","minute":"63'"},{"playerOff":"Nam-il Kim","playerOn":"Chun-soo Lee","minute":"68'"},{"playerOff":"Myung-bo Hong","playerOn":"Du-ri Cha","minute":"83'"},{"playerOff":"Alessandro Del Piero","playerOn":"Gennaro Gattuso","minute":"61'"},{"playerOff":"Gianluca Zambrotta","playerOn":"Angelo Di Livio","minute":"72'"}]}],"squad":[{"name":"Gianluigi Buffon","pos":"GK","num":1,"birthDate":"1978-01-28","age":48},{"name":"Christian Panucci","pos":"DF","num":2,"birthDate":"1973-04-12","age":53},{"name":"Paolo Maldini","pos":"DF","num":3,"birthDate":"1968-06-26","age":57},{"name":"Francesco Coco","pos":"DF","num":4,"birthDate":"1977-01-08","age":49},{"name":"Fabio Cannavaro","pos":"DF","num":5,"birthDate":"1973-09-13","age":52},{"name":"Cristiano Zanetti","pos":"MF","num":6,"birthDate":"1977-04-14","age":49},{"name":"Alessandro Del Piero","pos":"FW","num":7,"birthDate":"1974-11-09","age":51},{"name":"Gennaro Gattuso","pos":"MF","num":8,"birthDate":"1978-01-09","age":48},{"name":"Filippo Inzaghi","pos":"FW","num":9,"birthDate":"1973-08-09","age":52},{"name":"Francesco Totti","pos":"FW","num":10,"birthDate":"1976-09-27","age":49},{"name":"Cristiano Doni","pos":"MF","num":11,"birthDate":"1973-04-01","age":53},{"name":"Christian Abbiati","pos":"GK","num":12,"birthDate":"1977-07-08","age":48},{"name":"Alessandro Nesta","pos":"DF","num":13,"birthDate":"1976-03-19","age":50},{"name":"Luigi Di Biagio","pos":"MF","num":14,"birthDate":"1971-06-03","age":55},{"name":"Mark Iuliano","pos":"DF","num":15,"birthDate":"1973-08-12","age":52},{"name":"Angelo Di Livio","pos":"MF","num":16,"birthDate":"1966-07-26","age":59},{"name":"Damiano Tommasi","pos":"MF","num":17,"birthDate":"1974-05-17","age":52},{"name":"Marco Delvecchio","pos":"FW","num":18,"birthDate":"1973-04-07","age":53},{"name":"Gianluca Zambrotta","pos":"DF","num":19,"birthDate":"1977-02-19","age":49},{"name":"Vincenzo Montella","pos":"FW","num":20,"birthDate":"1974-06-18","age":51},{"name":"Christian Vieri","pos":"FW","num":21,"birthDate":"1973-07-12","age":52},{"name":"Francesco Toldo","pos":"GK","num":22,"birthDate":"1971-12-02","age":54},{"name":"Marco Materazzi","pos":"DF","num":23,"birthDate":"1973-08-19","age":52}]},{"year":1998,"stage":"八强","manager":"Cesare Maldini","cards":{"yellow":11,"red":0},"group":{"name":"Group B","standings":[{"pos":1,"team":"意大利","p":3,"w":2,"d":1,"l":0,"gf":7,"ga":3,"pts":7},{"pos":2,"team":"智利","p":3,"w":0,"d":3,"l":0,"gf":4,"ga":4,"pts":3},{"pos":3,"team":"奥地利","p":3,"w":0,"d":2,"l":1,"gf":3,"ga":4,"pts":2},{"pos":4,"team":"喀麦隆","p":3,"w":0,"d":2,"l":1,"gf":2,"ga":5,"pts":2}]},"matches":[{"stage":"group stage","home":"意大利","away":"智利","homeScore":2,"awayScore":2,"extra":false,"pens":false,"penScore":"","goals":[{"player":"Christian Vieri","team":"意大利","minute":"10'","penalty":false,"ownGoal":false},{"player":"Marcelo Salas","team":"智利","minute":"45'+3'","penalty":false,"ownGoal":false},{"player":"Marcelo Salas","team":"智利","minute":"50'","penalty":false,"ownGoal":false},{"player":"Roberto Baggio","team":"意大利","minute":"84'","penalty":true,"ownGoal":false}],"venue":{"stadium":"Stade du Parc Lescure","city":"Bordeaux","capacity":35000},"subs":[{"playerOff":"Roberto Di Matteo","playerOn":"Luigi Di Biagio","minute":"57'"},{"playerOff":"Angelo Di Livio","playerOn":"Enrico Chiesa","minute":"61'"},{"playerOff":"Christian Vieri","playerOn":"Filippo Inzaghi","minute":"71'"},{"playerOff":"Javier Margas","playerOn":"Miguel Ramírez","minute":"63'"},{"playerOff":"Fabián Estay","playerOn":"José Luis Sierra","minute":"81'"},{"playerOff":"Clarence Acuña","playerOn":"Fernando Cornejo","minute":"82'"}]},{"stage":"group stage","home":"意大利","away":"喀麦隆","homeScore":3,"awayScore":0,"extra":false,"pens":false,"penScore":"","goals":[{"player":"Luigi Di Biagio","team":"意大利","minute":"7'","penalty":false,"ownGoal":false},{"player":"Christian Vieri","team":"意大利","minute":"75'","penalty":false,"ownGoal":false},{"player":"Christian Vieri","team":"意大利","minute":"89'","penalty":false,"ownGoal":false}],"venue":{"stadium":"Stade de la Mosson","city":"Montpellier","capacity":34000},"subs":[{"playerOff":"Demetrio Albertini","playerOn":"Roberto Di Matteo","minute":"62'"},{"playerOff":"Roberto Baggio","playerOn":"Alessandro Del Piero","minute":"65'"},{"playerOff":"Francesco Moriero","playerOn":"Angelo Di Livio","minute":"83'"},{"playerOff":"Samuel Ipoua","playerOn":"Joseph-Désiré Job","minute":"45'"},{"playerOff":"François Omam-Biyik","playerOn":"Alphonse Tchami","minute":"66'"},{"playerOff":"Patrick M'Boma","playerOn":"Samuel Eto'o","minute":"66'"}]},{"stage":"group stage","home":"意大利","away":"奥地利","homeScore":2,"awayScore":1,"extra":false,"pens":false,"penScore":"","goals":[{"player":"Christian Vieri","team":"意大利","minute":"48'","penalty":false,"ownGoal":false},{"player":"Roberto Baggio","team":"意大利","minute":"90'","penalty":false,"ownGoal":false},{"player":"Andi Herzog","team":"奥地利","minute":"90'+2'","penalty":true,"ownGoal":false}],"venue":{"stadium":"Stade de France","city":"Saint-Denis","capacity":80000},"subs":[{"playerOff":"Alessandro Nesta","playerOn":"Giuseppe Bergomi","minute":"4'"},{"playerOff":"Christian Vieri","playerOn":"Filippo Inzaghi","minute":"60'"},{"playerOff":"Alessandro Del Piero","playerOn":"Roberto Baggio","minute":"72'"},{"playerOff":"Toni Polster","playerOn":"Mario Haas","minute":"62'"},{"playerOff":"Dietmar Kühbauer","playerOn":"Peter Stöger","minute":"74'"},{"playerOff":"Heimo Pfeifenberger","playerOn":"Andi Herzog","minute":"80'"}]},{"stage":"round of 16","home":"意大利","away":"挪威","homeScore":1,"awayScore":0,"extra":false,"pens":false,"penScore":"","goals":[{"player":"Christian Vieri","team":"意大利","minute":"18'","penalty":false,"ownGoal":false}],"venue":{"stadium":"Stade Vélodrome","city":"Marseille","capacity":60000},"subs":[{"playerOff":"Francesco Moriero","playerOn":"Angelo Di Livio","minute":"63'"},{"playerOff":"Demetrio Albertini","playerOn":"Gianluca Pessotto","minute":"72'"},{"playerOff":"Alessandro Del Piero","playerOn":"Enrico Chiesa","minute":"77'"},{"playerOff":"Øyvind Leonhardsen","playerOn":"Roar Strand","minute":"13'"},{"playerOff":"Roar Strand","playerOn":"Ståle Solbakken","minute":"39'"},{"playerOff":"Håvard Flo","playerOn":"Ole Gunnar Solskjær","minute":"73'"}]},{"stage":"quarter-finals","home":"意大利","away":"法国","homeScore":0,"awayScore":0,"extra":true,"pens":true,"penScore":"3-4","goals":[],"venue":{"stadium":"Stade de France","city":"Saint-Denis","capacity":80000},"subs":[{"playerOff":"Dino Baggio","playerOn":"Demetrio Albertini","minute":"52'"},{"playerOff":"Alessandro Del Piero","playerOn":"Roberto Baggio","minute":"67'"},{"playerOff":"Gianluca Pessotto","playerOn":"Angelo Di Livio","minute":"90'"},{"playerOff":"Christian Karembeu","playerOn":"Thierry Henry","minute":"65'"},{"playerOff":"Stéphane Guivarc'h","playerOn":"David Trezeguet","minute":"65'"}]}],"squad":[{"name":"Francesco Toldo","pos":"GK","num":1,"birthDate":"1971-12-02","age":54},{"name":"Giuseppe Bergomi","pos":"DF","num":2,"birthDate":"1963-12-22","age":62},{"name":"Paolo Maldini","pos":"DF","num":3,"birthDate":"1968-06-26","age":57},{"name":"Fabio Cannavaro","pos":"DF","num":4,"birthDate":"1973-09-13","age":52},{"name":"Alessandro Costacurta","pos":"DF","num":5,"birthDate":"1966-04-24","age":60},{"name":"Alessandro Nesta","pos":"DF","num":6,"birthDate":"1976-03-19","age":50},{"name":"Gianluca Pessotto","pos":"DF","num":7,"birthDate":"1970-08-11","age":55},{"name":"Moreno Torricelli","pos":"DF","num":8,"birthDate":"1970-01-23","age":56},{"name":"Demetrio Albertini","pos":"MF","num":9,"birthDate":"1971-08-23","age":54},{"name":"Alessandro Del Piero","pos":"FW","num":10,"birthDate":"1974-11-09","age":51},{"name":"Dino Baggio","pos":"MF","num":11,"birthDate":"1971-07-24","age":54},{"name":"Gianluca Pagliuca","pos":"GK","num":12,"birthDate":"1966-12-18","age":59},{"name":"Sandro Cois","pos":"MF","num":13,"birthDate":"1972-06-09","age":54},{"name":"Luigi Di Biagio","pos":"MF","num":14,"birthDate":"1971-06-03","age":55},{"name":"Angelo Di Livio","pos":"MF","num":15,"birthDate":"1966-07-26","age":59},{"name":"Roberto Di Matteo","pos":"MF","num":16,"birthDate":"1970-05-29","age":56},{"name":"Francesco Moriero","pos":"MF","num":17,"birthDate":"1969-03-31","age":57},{"name":"Roberto Baggio","pos":"FW","num":18,"birthDate":"1967-02-18","age":59},{"name":"Filippo Inzaghi","pos":"FW","num":19,"birthDate":"1973-08-09","age":52},{"name":"Enrico Chiesa","pos":"FW","num":20,"birthDate":"1970-12-29","age":55},{"name":"Christian Vieri","pos":"FW","num":21,"birthDate":"1973-07-12","age":52},{"name":"Gianluigi Buffon","pos":"GK","num":22,"birthDate":"1978-01-28","age":48}]},{"year":1994,"stage":"亚军","manager":"Arrigo Sacchi","cards":{"yellow":11,"red":2},"group":{"name":"Group E","standings":[{"pos":1,"team":"墨西哥","p":3,"w":1,"d":1,"l":1,"gf":3,"ga":3,"pts":4},{"pos":2,"team":"爱尔兰","p":3,"w":1,"d":1,"l":1,"gf":2,"ga":2,"pts":4},{"pos":3,"team":"意大利","p":3,"w":1,"d":1,"l":1,"gf":2,"ga":2,"pts":4},{"pos":4,"team":"挪威","p":3,"w":1,"d":1,"l":1,"gf":1,"ga":1,"pts":4}]},"matches":[{"stage":"group stage","home":"意大利","away":"爱尔兰","homeScore":0,"awayScore":1,"extra":false,"pens":false,"penScore":"","goals":[{"player":"Ray Houghton","team":"爱尔兰","minute":"11'","penalty":false,"ownGoal":false}],"venue":{"stadium":"Giants Stadium","city":"East Rutherford","capacity":76000},"subs":[{"playerOff":"Alberigo Evani","playerOn":"Daniele Massaro","minute":"45'"},{"playerOff":"Giuseppe Signori","playerOn":"Nicola Berti","minute":"84'"},{"playerOff":"Ray Houghton","playerOn":"Jason McAteer","minute":"68'"},{"playerOff":"Tommy Coyne","playerOn":"John Aldridge","minute":"90'"}]},{"stage":"group stage","home":"意大利","away":"挪威","homeScore":1,"awayScore":0,"extra":false,"pens":false,"penScore":"","goals":[{"player":"Dino Baggio","team":"意大利","minute":"69'","penalty":false,"ownGoal":false}],"venue":{"stadium":"Giants Stadium","city":"East Rutherford","capacity":76000},"subs":[{"playerOff":"Roberto Baggio","playerOn":"Luca Marchegiani","minute":"22'"},{"playerOff":"Franco Baresi","playerOn":"Luigi Apolloni","minute":"49'"},{"playerOff":"Pierluigi Casiraghi","playerOn":"Daniele Massaro","minute":"69'"},{"playerOff":"Sigurd Rushfeldt","playerOn":"Mini Jakobsen","minute":"45'"},{"playerOff":"Erik Mykland","playerOn":"Kjetil Rekdal","minute":"81'"}]},{"stage":"group stage","home":"意大利","away":"墨西哥","homeScore":1,"awayScore":1,"extra":false,"pens":false,"penScore":"","goals":[{"player":"Daniele Massaro","team":"意大利","minute":"48'","penalty":false,"ownGoal":false},{"player":"Marcelino Bernal","team":"墨西哥","minute":"57'","penalty":false,"ownGoal":false}],"venue":{"stadium":"RFK Stadium","city":"Washington, D.C.","capacity":53000},"subs":[{"playerOff":"Pierluigi Casiraghi","playerOn":"Daniele Massaro","minute":"45'"},{"playerOff":"Dino Baggio","playerOn":"Roberto Donadoni","minute":"65'"},{"playerOff":"Luis García Postigo","playerOn":"Juan Carlos Chávez","minute":"81'"}]},{"stage":"round of 16","home":"尼日利亚","away":"意大利","homeScore":1,"awayScore":2,"extra":true,"pens":false,"penScore":"","goals":[{"player":"Emmanuel Amunike","team":"尼日利亚","minute":"25'","penalty":false,"ownGoal":false},{"player":"Roberto Baggio","team":"意大利","minute":"88'","penalty":false,"ownGoal":false},{"player":"Roberto Baggio","team":"意大利","minute":"102'","penalty":true,"ownGoal":false}],"venue":{"stadium":"Foxboro Stadium","city":"Foxborough","capacity":54000},"subs":[{"playerOff":"Daniel Amokachi","playerOn":"Mutiu Adepoju","minute":"35'"},{"playerOff":"Emmanuel Amunike","playerOn":"Thompson Oliha","minute":"57'"},{"playerOff":"Nicola Berti","playerOn":"Dino Baggio","minute":"45'"},{"playerOff":"Giuseppe Signori","playerOn":"Gianfranco Zola","minute":"65'"}]},{"stage":"quarter-finals","home":"意大利","away":"西班牙","homeScore":2,"awayScore":1,"extra":false,"pens":false,"penScore":"","goals":[{"player":"Dino Baggio","team":"意大利","minute":"25'","penalty":false,"ownGoal":false},{"player":"José Luis Caminero","team":"西班牙","minute":"58'","penalty":false,"ownGoal":false},{"player":"Roberto Baggio","team":"意大利","minute":"88'","penalty":false,"ownGoal":false}],"venue":{"stadium":"Foxboro Stadium","city":"Foxborough","capacity":54000},"subs":[{"playerOff":"Demetrio Albertini","playerOn":"Giuseppe Signori","minute":"45'"},{"playerOff":"Antonio Conte","playerOn":"Nicola Berti","minute":"66'"},{"playerOff":"Sergi","playerOn":"Julio Salinas","minute":"60'"},{"playerOff":"José María Bakero","playerOn":"Fernando Hierro","minute":"65'"}]},{"stage":"semi-finals","home":"保加利亚","away":"意大利","homeScore":1,"awayScore":2,"extra":false,"pens":false,"penScore":"","goals":[{"player":"Roberto Baggio","team":"意大利","minute":"21'","penalty":false,"ownGoal":false},{"player":"Roberto Baggio","team":"意大利","minute":"25'","penalty":false,"ownGoal":false},{"player":"Hristo Stoichkov","team":"保加利亚","minute":"44'","penalty":true,"ownGoal":false}],"venue":{"stadium":"Giants Stadium","city":"East Rutherford","capacity":76000},"subs":[{"playerOff":"Emil Kostadinov","playerOn":"Ivaylo Yordanov","minute":"72'"},{"playerOff":"Hristo Stoichkov","playerOn":"Boncho Genchev","minute":"79'"},{"playerOff":"Dino Baggio","playerOn":"Antonio Conte","minute":"56'"},{"playerOff":"Roberto Baggio","playerOn":"Giuseppe Signori","minute":"71'"}]},{"stage":"final","home":"巴西","away":"意大利","homeScore":0,"awayScore":0,"extra":true,"pens":true,"penScore":"3-2","goals":[],"venue":{"stadium":"Rose Bowl","city":"Pasadena","capacity":94000},"subs":[{"playerOff":"Jorginho","playerOn":"Cafu","minute":"21'"},{"playerOff":"Zinho","playerOn":"Viola","minute":"106'"},{"playerOff":"Roberto Mussi","playerOn":"Luigi Apolloni","minute":"35'"},{"playerOff":"Dino Baggio","playerOn":"Alberigo Evani","minute":"95'"}]}],"squad":[{"name":"Gianluca Pagliuca","pos":"GK","num":1,"birthDate":"1966-12-18","age":59},{"name":"Luigi Apolloni","pos":"DF","num":2,"birthDate":"1967-05-02","age":59},{"name":"Antonio Benarrivo","pos":"DF","num":3,"birthDate":"1968-08-21","age":57},{"name":"Alessandro Costacurta","pos":"DF","num":4,"birthDate":"1966-04-24","age":60},{"name":"Paolo Maldini","pos":"DF","num":5,"birthDate":"1968-06-26","age":57},{"name":"Franco Baresi","pos":"DF","num":6,"birthDate":"1960-05-08","age":66},{"name":"Lorenzo Minotti","pos":"DF","num":7,"birthDate":"1967-02-08","age":59},{"name":"Roberto Mussi","pos":"DF","num":8,"birthDate":"1963-08-25","age":62},{"name":"Mauro Tassotti","pos":"DF","num":9,"birthDate":"1960-01-19","age":66},{"name":"Roberto Baggio","pos":"FW","num":10,"birthDate":"1967-02-18","age":59},{"name":"Demetrio Albertini","pos":"MF","num":11,"birthDate":"1971-08-23","age":54},{"name":"Luca Marchegiani","pos":"GK","num":12,"birthDate":"1966-02-22","age":60},{"name":"Dino Baggio","pos":"MF","num":13,"birthDate":"1971-07-24","age":54},{"name":"Nicola Berti","pos":"MF","num":14,"birthDate":"1967-04-14","age":59},{"name":"Antonio Conte","pos":"MF","num":15,"birthDate":"1969-07-31","age":56},{"name":"Roberto Donadoni","pos":"MF","num":16,"birthDate":"1963-09-09","age":62},{"name":"Alberigo Evani","pos":"MF","num":17,"birthDate":"1963-01-01","age":63},{"name":"Pierluigi Casiraghi","pos":"FW","num":18,"birthDate":"1969-03-04","age":57},{"name":"Daniele Massaro","pos":"FW","num":19,"birthDate":"1961-05-23","age":65},{"name":"Giuseppe Signori","pos":"FW","num":20,"birthDate":"1968-02-17","age":58},{"name":"Gianfranco Zola","pos":"FW","num":21,"birthDate":"1966-07-05","age":59},{"name":"Luca Bucci","pos":"GK","num":22,"birthDate":"1969-03-13","age":57}]},{"year":1990,"stage":"季军赛","manager":"Azeglio Vicini","cards":{"yellow":6,"red":0},"group":{"name":"Group A","standings":[{"pos":1,"team":"意大利","p":3,"w":3,"d":0,"l":0,"gf":4,"ga":0,"pts":6},{"pos":2,"team":"捷克斯洛伐克","p":3,"w":2,"d":0,"l":1,"gf":6,"ga":3,"pts":4},{"pos":3,"team":"奥地利","p":3,"w":1,"d":0,"l":2,"gf":2,"ga":3,"pts":2},{"pos":4,"team":"美国","p":3,"w":0,"d":0,"l":3,"gf":2,"ga":8,"pts":0}]},"matches":[{"stage":"group stage","home":"意大利","away":"奥地利","homeScore":1,"awayScore":0,"extra":false,"pens":false,"penScore":"","goals":[{"player":"Salvatore Schillaci","team":"意大利","minute":"78'","penalty":false,"ownGoal":false}],"venue":{"stadium":"Stadio Olimpico","city":"Rome","capacity":74000},"subs":[{"playerOff":"Carlo Ancelotti","playerOn":"Luigi De Agostini","minute":"46'"},{"playerOff":"Andrea Carnevale","playerOn":"Salvatore Schillaci","minute":"75'"},{"playerOff":"Peter Artner","playerOn":"Manfred Zsak","minute":"61'"},{"playerOff":"Manfred Linzmaier","playerOn":"Alfred Hörtnagl","minute":"77'"}]},{"stage":"group stage","home":"意大利","away":"美国","homeScore":1,"awayScore":0,"extra":false,"pens":false,"penScore":"","goals":[{"player":"Giuseppe Giannini","team":"意大利","minute":"11'","penalty":false,"ownGoal":false}],"venue":{"stadium":"Stadio Olimpico","city":"Rome","capacity":74000},"subs":[{"playerOff":"Andrea Carnevale","playerOn":"Salvatore Schillaci","minute":"51'"},{"playerOff":"Jimmy Banks","playerOn":"John Stollmeyer","minute":"80'"},{"playerOff":"Bruce Murray","playerOn":"Christopher Sullivan","minute":"82'"}]},{"stage":"group stage","home":"意大利","away":"捷克斯洛伐克","homeScore":2,"awayScore":0,"extra":false,"pens":false,"penScore":"","goals":[{"player":"Salvatore Schillaci","team":"意大利","minute":"9'","penalty":false,"ownGoal":false},{"player":"Roberto Baggio","team":"意大利","minute":"78'","penalty":false,"ownGoal":false}],"venue":{"stadium":"Stadio Olimpico","city":"Rome","capacity":74000},"subs":[{"playerOff":"Roberto Donadoni","playerOn":"Luigi De Agostini","minute":"51'"},{"playerOff":"Fernando De Napoli","playerOn":"Pietro Vierchowod","minute":"65'"},{"playerOff":"Václav Němeček","playerOn":"Július Bielik","minute":"46'"},{"playerOff":"Vladimír Weiss","playerOn":"Stanislav Griga","minute":"58'"}]},{"stage":"round of 16","home":"意大利","away":"乌拉圭","homeScore":2,"awayScore":0,"extra":false,"pens":false,"penScore":"","goals":[{"player":"Salvatore Schillaci","team":"意大利","minute":"65'","penalty":false,"ownGoal":false},{"player":"Aldo Serena","team":"意大利","minute":"83'","penalty":false,"ownGoal":false}],"venue":{"stadium":"Stadio Olimpico","city":"Rome","capacity":74000},"subs":[{"playerOff":"Nicola Berti","playerOn":"Aldo Serena","minute":"52'"},{"playerOff":"Roberto Baggio","playerOn":"Pietro Vierchowod","minute":"79'"},{"playerOff":"Carlos Aguilera","playerOn":"Rubén Sosa","minute":"55'"},{"playerOff":"Santiago Ostolaza","playerOn":"Antonio Alzamendi","minute":"79'"}]},{"stage":"quarter-finals","home":"爱尔兰","away":"意大利","homeScore":0,"awayScore":1,"extra":false,"pens":false,"penScore":"","goals":[{"player":"Salvatore Schillaci","team":"意大利","minute":"38'","penalty":false,"ownGoal":false}],"venue":{"stadium":"Stadio Olimpico","city":"Rome","capacity":74000},"subs":[{"playerOff":"Niall Quinn","playerOn":"Tony Cascarino","minute":"53'"},{"playerOff":"John Aldridge","playerOn":"John Sheridan","minute":"78'"},{"playerOff":"Giuseppe Giannini","playerOn":"Carlo Ancelotti","minute":"62'"},{"playerOff":"Roberto Baggio","playerOn":"Aldo Serena","minute":"70'"}]},{"stage":"semi-finals","home":"阿根廷","away":"意大利","homeScore":1,"awayScore":1,"extra":true,"pens":true,"penScore":"4-3","goals":[{"player":"Salvatore Schillaci","team":"意大利","minute":"17'","penalty":false,"ownGoal":false},{"player":"Claudio Caniggia","team":"阿根廷","minute":"67'","penalty":false,"ownGoal":false}],"venue":{"stadium":"Stadio San Paolo","city":"Naples","capacity":60000},"subs":[{"playerOff":"Gabriel Calderón","playerOn":"Pedro Troglio","minute":"46'"},{"playerOff":"José Basualdo","playerOn":"Sergio Batista","minute":"99'"},{"playerOff":"Gianluca Vialli","playerOn":"Aldo Serena","minute":"70'"},{"playerOff":"Giuseppe Giannini","playerOn":"Roberto Baggio","minute":"73'"}]},{"stage":"third-place match","home":"意大利","away":"英格兰","homeScore":2,"awayScore":1,"extra":false,"pens":false,"penScore":"","goals":[{"player":"Roberto Baggio","team":"意大利","minute":"71'","penalty":false,"ownGoal":false},{"player":"David Platt","team":"英格兰","minute":"81'","penalty":false,"ownGoal":false},{"player":"Salvatore Schillaci","team":"意大利","minute":"86'","penalty":true,"ownGoal":false}],"venue":{"stadium":"Stadio San Nicola","city":"Bari","capacity":51000},"subs":[{"playerOff":"Luigi De Agostini","playerOn":"Nicola Berti","minute":"67'"},{"playerOff":"Giuseppe Giannini","playerOn":"Riccardo Ferri","minute":"90'"},{"playerOff":"Mark Wright","playerOn":"Neil Webb","minute":"71'"},{"playerOff":"Steve McMahon","playerOn":"Chris Waddle","minute":"71'"}]}],"squad":[{"name":"Walter Zenga","pos":"GK","num":1,"birthDate":"1960-04-28","age":66},{"name":"Franco Baresi","pos":"DF","num":2,"birthDate":"1960-05-08","age":66},{"name":"Giuseppe Bergomi","pos":"DF","num":3,"birthDate":"1963-12-22","age":62},{"name":"Luigi De Agostini","pos":"DF","num":4,"birthDate":"1961-04-07","age":65},{"name":"Ciro Ferrara","pos":"DF","num":5,"birthDate":"1967-02-11","age":59},{"name":"Riccardo Ferri","pos":"DF","num":6,"birthDate":"1963-08-20","age":62},{"name":"Paolo Maldini","pos":"DF","num":7,"birthDate":"1968-06-26","age":57},{"name":"Pietro Vierchowod","pos":"DF","num":8,"birthDate":"1959-04-06","age":67},{"name":"Carlo Ancelotti","pos":"MF","num":9,"birthDate":"1959-06-10","age":67},{"name":"Nicola Berti","pos":"MF","num":10,"birthDate":"1967-04-14","age":59},{"name":"Fernando De Napoli","pos":"MF","num":11,"birthDate":"1964-03-15","age":62},{"name":"Stefano Tacconi","pos":"GK","num":12,"birthDate":"1957-05-13","age":69},{"name":"Giuseppe Giannini","pos":"MF","num":13,"birthDate":"1964-08-20","age":61},{"name":"Giancarlo Marocchi","pos":"MF","num":14,"birthDate":"1965-07-04","age":60},{"name":"Roberto Baggio","pos":"FW","num":15,"birthDate":"1967-02-18","age":59},{"name":"Andrea Carnevale","pos":"FW","num":16,"birthDate":"1961-01-12","age":65},{"name":"Roberto Donadoni","pos":"MF","num":17,"birthDate":"1963-09-09","age":62},{"name":"Roberto Mancini","pos":"FW","num":18,"birthDate":"1964-11-27","age":61},{"name":"Salvatore Schillaci","pos":"FW","num":19,"birthDate":"1964-12-01","age":61},{"name":"Aldo Serena","pos":"FW","num":20,"birthDate":"1960-06-25","age":65},{"name":"Gianluca Vialli","pos":"FW","num":21,"birthDate":"1964-07-09","age":61},{"name":"Gianluca Pagliuca","pos":"GK","num":22,"birthDate":"1966-12-18","age":59}]},{"year":1986,"stage":"十六强","manager":"Enzo Bearzot","cards":{"yellow":8,"red":0},"group":{"name":"Group A","standings":[{"pos":1,"team":"阿根廷","p":3,"w":2,"d":1,"l":0,"gf":6,"ga":2,"pts":5},{"pos":2,"team":"意大利","p":3,"w":1,"d":2,"l":0,"gf":5,"ga":4,"pts":4},{"pos":3,"team":"保加利亚","p":3,"w":0,"d":2,"l":1,"gf":2,"ga":4,"pts":2},{"pos":4,"team":"韩国","p":3,"w":0,"d":1,"l":2,"gf":4,"ga":7,"pts":1}]},"matches":[{"stage":"group stage","home":"保加利亚","away":"意大利","homeScore":1,"awayScore":1,"extra":false,"pens":false,"penScore":"","goals":[{"player":"Alessandro Altobelli","team":"意大利","minute":"44'","penalty":false,"ownGoal":false},{"player":"Nasko Sirakov","team":"保加利亚","minute":"85'","penalty":false,"ownGoal":false}],"venue":{"stadium":"Estadio Azteca","city":"Mexico City","capacity":115000},"subs":[{"playerOff":"Bozhidar Iskrenov","playerOn":"Kostadin Kostadinov","minute":"65'"},{"playerOff":"Zhivko Gospodinov","playerOn":"Andrey Zhelyazkov","minute":"74'"},{"playerOff":"Bruno Conti","playerOn":"Gianluca Vialli","minute":"65'"}]},{"stage":"group stage","home":"意大利","away":"阿根廷","homeScore":1,"awayScore":1,"extra":false,"pens":false,"penScore":"","goals":[{"player":"Alessandro Altobelli","team":"意大利","minute":"6'","penalty":true,"ownGoal":false},{"player":"Diego Maradona","team":"阿根廷","minute":"34'","penalty":false,"ownGoal":false}],"venue":{"stadium":"Estadio Cuauhtémoc","city":"Puebla","capacity":46000},"subs":[{"playerOff":"Bruno Conti","playerOn":"Gianluca Vialli","minute":"65'"},{"playerOff":"Fernando De Napoli","playerOn":"Giuseppe Baresi","minute":"87'"},{"playerOff":"Sergio Batista","playerOn":"Julio Olarticoechea","minute":"59'"},{"playerOff":"Claudio Borghi","playerOn":"Héctor Enrique","minute":"74'"}]},{"stage":"group stage","home":"韩国","away":"意大利","homeScore":2,"awayScore":3,"extra":false,"pens":false,"penScore":"","goals":[{"player":"Alessandro Altobelli","team":"意大利","minute":"17'","penalty":false,"ownGoal":false},{"player":"Soon-ho Choi","team":"韩国","minute":"62'","penalty":false,"ownGoal":false},{"player":"Alessandro Altobelli","team":"意大利","minute":"73'","penalty":false,"ownGoal":false},{"player":"Kwang-rae Cho","team":"意大利","minute":"82'","penalty":false,"ownGoal":true},{"player":"Jung-moo Huh","team":"韩国","minute":"83'","penalty":false,"ownGoal":false}],"venue":{"stadium":"Estadio Cuauhtémoc","city":"Puebla","capacity":46000},"subs":[{"playerOff":"Joo-sung Kim","playerOn":"Jong-soo Chung","minute":"46'"},{"playerOff":"Byung-joo Byun","playerOn":"Jong-boo Kim","minute":"70'"},{"playerOff":"Salvatore Bagni","playerOn":"Giuseppe Baresi","minute":"67'"},{"playerOff":"Giuseppe Galderisi","playerOn":"Gianluca Vialli","minute":"88'"}]},{"stage":"round of 16","home":"意大利","away":"法国","homeScore":0,"awayScore":2,"extra":false,"pens":false,"penScore":"","goals":[{"player":"Michel Platini","team":"法国","minute":"15'","penalty":false,"ownGoal":false},{"player":"Yannick Stopyra","team":"法国","minute":"57'","penalty":false,"ownGoal":false}],"venue":{"stadium":"Estadio Olímpico Universitario","city":"Mexico City","capacity":72000},"subs":[{"playerOff":"Giuseppe Baresi","playerOn":"Antonio Di Gennaro","minute":"46'"},{"playerOff":"Giuseppe Galderisi","playerOn":"Gianluca Vialli","minute":"58'"},{"playerOff":"Luis Fernández","playerOn":"Thierry Tusseau","minute":"73'"},{"playerOff":"Michel Platini","playerOn":"Jean-Marc Ferreri","minute":"85'"}]}],"squad":[{"name":"Giovanni Galli","pos":"GK","num":1,"birthDate":"1958-04-29","age":68},{"name":"Giuseppe Bergomi","pos":"DF","num":2,"birthDate":"1963-12-22","age":62},{"name":"Antonio Cabrini","pos":"DF","num":3,"birthDate":"1957-10-08","age":68},{"name":"Fulvio Collovati","pos":"DF","num":4,"birthDate":"1957-05-09","age":69},{"name":"Sebastiano Nela","pos":"DF","num":5,"birthDate":"1961-03-13","age":65},{"name":"Gaetano Scirea","pos":"DF","num":6,"birthDate":"1953-05-25","age":73},{"name":"Roberto Tricella","pos":"DF","num":7,"birthDate":"1959-03-18","age":67},{"name":"Pietro Vierchowod","pos":"DF","num":8,"birthDate":"1959-04-06","age":67},{"name":"Carlo Ancelotti","pos":"MF","num":9,"birthDate":"1959-06-10","age":67},{"name":"Salvatore Bagni","pos":"MF","num":10,"birthDate":"1956-09-25","age":69},{"name":"Giuseppe Baresi","pos":"MF","num":11,"birthDate":"1958-02-07","age":68},{"name":"Franco Tancredi","pos":"GK","num":12,"birthDate":"1955-01-10","age":71},{"name":"Fernando De Napoli","pos":"MF","num":13,"birthDate":"1964-03-15","age":62},{"name":"Antonio Di Gennaro","pos":"MF","num":14,"birthDate":"1958-10-05","age":67},{"name":"Marco Tardelli","pos":"MF","num":15,"birthDate":"1954-09-24","age":71},{"name":"Bruno Conti","pos":"FW","num":16,"birthDate":"1955-03-13","age":71},{"name":"Gianluca Vialli","pos":"FW","num":17,"birthDate":"1964-07-09","age":61},{"name":"Alessandro Altobelli","pos":"FW","num":18,"birthDate":"1955-11-28","age":70},{"name":"Giuseppe Galderisi","pos":"FW","num":19,"birthDate":"1963-03-22","age":63},{"name":"Paolo Rossi","pos":"FW","num":20,"birthDate":"1956-09-23","age":69},{"name":"Aldo Serena","pos":"FW","num":21,"birthDate":"1960-06-25","age":65},{"name":"Walter Zenga","pos":"GK","num":22,"birthDate":"1960-04-28","age":66}]},{"year":1982,"stage":"冠军","manager":"Enzo Bearzot","cards":{"yellow":11,"red":0},"group":{"name":"Group C","standings":[{"pos":1,"team":"意大利","p":2,"w":2,"d":0,"l":0,"gf":5,"ga":3,"pts":4},{"pos":2,"team":"巴西","p":2,"w":1,"d":0,"l":1,"gf":5,"ga":4,"pts":2},{"pos":3,"team":"阿根廷","p":2,"w":0,"d":0,"l":2,"gf":2,"ga":5,"pts":0}]},"matches":[{"stage":"group stage","home":"意大利","away":"波兰","homeScore":0,"awayScore":0,"extra":false,"pens":false,"penScore":"","goals":[],"venue":{"stadium":"Balaídos","city":"Vigo","capacity":33000},"subs":[{"playerOff":"Andrzej Iwan","playerOn":"Marek Kusto","minute":"72'"}]},{"stage":"group stage","home":"意大利","away":"秘鲁","homeScore":1,"awayScore":1,"extra":false,"pens":false,"penScore":"","goals":[{"player":"Bruno Conti","team":"意大利","minute":"18'","penalty":false,"ownGoal":false},{"player":"Rubén Toribio Díaz","team":"秘鲁","minute":"83'","penalty":false,"ownGoal":false}],"venue":{"stadium":"Balaídos","city":"Vigo","capacity":33000},"subs":[{"playerOff":"Paolo Rossi","playerOn":"Franco Causio","minute":"46'"},{"playerOff":"Gerónimo Barbadillo","playerOn":"Germán Leguía","minute":"65'"},{"playerOff":"Julio César Uribe","playerOn":"Guillermo La Rosa","minute":"65'"}]},{"stage":"group stage","home":"意大利","away":"喀麦隆","homeScore":1,"awayScore":1,"extra":false,"pens":false,"penScore":"","goals":[{"player":"Francesco Graziani","team":"意大利","minute":"60'","penalty":false,"ownGoal":false},{"player":"Grégoire M'Bida","team":"喀麦隆","minute":"61'","penalty":false,"ownGoal":false}],"venue":{"stadium":"Balaídos","city":"Vigo","capacity":33000}},{"stage":"second group stage","home":"意大利","away":"阿根廷","homeScore":2,"awayScore":1,"extra":false,"pens":false,"penScore":"","goals":[{"player":"Marco Tardelli","team":"意大利","minute":"57'","penalty":false,"ownGoal":false},{"player":"Antonio Cabrini","team":"意大利","minute":"67'","penalty":false,"ownGoal":false},{"player":"Daniel Passarella","team":"阿根廷","minute":"83'","penalty":false,"ownGoal":false}],"venue":{"stadium":"Estadi de Sarrià","city":"Barcelona","capacity":40000},"subs":[{"playerOff":"Gabriele Oriali","playerOn":"Giampiero Marini","minute":"75'"},{"playerOff":"Paolo Rossi","playerOn":"Alessandro Altobelli","minute":"80'"},{"playerOff":"Mario Kempes","playerOn":"Gabriel Calderón","minute":"58'"},{"playerOff":"Ramón Díaz","playerOn":"José Daniel Valencia","minute":"58'"}]},{"stage":"second group stage","home":"意大利","away":"巴西","homeScore":3,"awayScore":2,"extra":false,"pens":false,"penScore":"","goals":[{"player":"Paolo Rossi","team":"意大利","minute":"5'","penalty":false,"ownGoal":false},{"player":"Sócrates","team":"巴西","minute":"12'","penalty":false,"ownGoal":false},{"player":"Paolo Rossi","team":"意大利","minute":"25'","penalty":false,"ownGoal":false},{"player":"Falcão","team":"巴西","minute":"68'","penalty":false,"ownGoal":false},{"player":"Paolo Rossi","team":"意大利","minute":"74'","penalty":false,"ownGoal":false}],"venue":{"stadium":"Estadi de Sarrià","city":"Barcelona","capacity":40000},"subs":[{"playerOff":"Fulvio Collovati","playerOn":"Giuseppe Bergomi","minute":"34'"},{"playerOff":"Marco Tardelli","playerOn":"Giampiero Marini","minute":"75'"},{"playerOff":"Serginho","playerOn":"Paulo Isidoro","minute":"69'"}]},{"stage":"semi-finals","home":"波兰","away":"意大利","homeScore":0,"awayScore":2,"extra":false,"pens":false,"penScore":"","goals":[{"player":"Paolo Rossi","team":"意大利","minute":"22'","penalty":false,"ownGoal":false},{"player":"Paolo Rossi","team":"意大利","minute":"73'","penalty":false,"ownGoal":false}],"venue":{"stadium":"Camp Nou","city":"Barcelona","capacity":121000},"subs":[{"playerOff":"Włodzimierz Ciołek","playerOn":"Andrzej Pałasz","minute":"46'"},{"playerOff":"Włodzimierz Smolarek","playerOn":"Marek Kusto","minute":"77'"},{"playerOff":"Giancarlo Antognoni","playerOn":"Giampiero Marini","minute":"28'"},{"playerOff":"Francesco Graziani","playerOn":"Alessandro Altobelli","minute":"70'"}]},{"stage":"final","home":"意大利","away":"西德","homeScore":3,"awayScore":1,"extra":false,"pens":false,"penScore":"","goals":[{"player":"Paolo Rossi","team":"意大利","minute":"57'","penalty":false,"ownGoal":false},{"player":"Marco Tardelli","team":"意大利","minute":"69'","penalty":false,"ownGoal":false},{"player":"Alessandro Altobelli","team":"意大利","minute":"81'","penalty":false,"ownGoal":false},{"player":"Paul Breitner","team":"西德","minute":"83'","penalty":false,"ownGoal":false}],"venue":{"stadium":"Estadio Santiago Bernabéu","city":"Madrid","capacity":90000},"subs":[{"playerOff":"Francesco Graziani","playerOn":"Alessandro Altobelli","minute":"7'"},{"playerOff":"Alessandro Altobelli","playerOn":"Franco Causio","minute":"89'"},{"playerOff":"Wolfgang Dremmler","playerOn":"Horst Hrubesch","minute":"62'"},{"playerOff":"Karl-Heinz Rummenigge","playerOn":"Hansi Müller","minute":"70'"}]}],"squad":[{"name":"Dino Zoff","pos":"GK","num":1,"birthDate":"1942-02-28","age":84},{"name":"Franco Baresi","pos":"DF","num":2,"birthDate":"1960-05-08","age":66},{"name":"Giuseppe Bergomi","pos":"DF","num":3,"birthDate":"1963-12-22","age":62},{"name":"Antonio Cabrini","pos":"DF","num":4,"birthDate":"1957-10-08","age":68},{"name":"Fulvio Collovati","pos":"DF","num":5,"birthDate":"1957-05-09","age":69},{"name":"Claudio Gentile","pos":"DF","num":6,"birthDate":"1953-09-27","age":72},{"name":"Gaetano Scirea","pos":"DF","num":7,"birthDate":"1953-05-25","age":73},{"name":"Pietro Vierchowod","pos":"DF","num":8,"birthDate":"1959-04-06","age":67},{"name":"Giancarlo Antognoni","pos":"MF","num":9,"birthDate":"1954-04-01","age":72},{"name":"Giuseppe Dossena","pos":"MF","num":10,"birthDate":"1958-05-02","age":68},{"name":"Giampiero Marini","pos":"MF","num":11,"birthDate":"1951-02-25","age":75},{"name":"Ivano Bordon","pos":"GK","num":12,"birthDate":"1951-04-13","age":75},{"name":"Gabriele Oriali","pos":"MF","num":13,"birthDate":"1952-11-25","age":73},{"name":"Marco Tardelli","pos":"MF","num":14,"birthDate":"1954-09-24","age":71},{"name":"Franco Causio","pos":"MF","num":15,"birthDate":"1949-02-01","age":77},{"name":"Bruno Conti","pos":"MF","num":16,"birthDate":"1955-03-13","age":71},{"name":"Daniele Massaro","pos":"FW","num":17,"birthDate":"1961-05-23","age":65},{"name":"Alessandro Altobelli","pos":"FW","num":18,"birthDate":"1955-11-28","age":70},{"name":"Francesco Graziani","pos":"FW","num":19,"birthDate":"1952-12-16","age":73},{"name":"Paolo Rossi","pos":"FW","num":20,"birthDate":"1956-09-23","age":69},{"name":"Franco Selvaggi","pos":"FW","num":21,"birthDate":"1953-05-15","age":73},{"name":"Giovanni Galli","pos":"GK","num":22,"birthDate":"1958-04-29","age":68}]},{"year":1978,"stage":"季军赛","manager":"Enzo Bearzot","cards":{"yellow":6,"red":0},"group":{"name":"Group A","standings":[{"pos":1,"team":"荷兰","p":3,"w":2,"d":1,"l":0,"gf":9,"ga":4,"pts":5},{"pos":2,"team":"意大利","p":3,"w":1,"d":1,"l":1,"gf":2,"ga":2,"pts":3},{"pos":3,"team":"西德","p":3,"w":0,"d":2,"l":1,"gf":4,"ga":5,"pts":2},{"pos":4,"team":"奥地利","p":3,"w":1,"d":0,"l":2,"gf":4,"ga":8,"pts":2}]},"matches":[{"stage":"group stage","home":"意大利","away":"法国","homeScore":2,"awayScore":1,"extra":false,"pens":false,"penScore":"","goals":[{"player":"Bernard Lacombe","team":"法国","minute":"1'","penalty":false,"ownGoal":false},{"player":"Paolo Rossi","team":"意大利","minute":"29'","penalty":false,"ownGoal":false},{"player":"Renato Zaccarelli","team":"意大利","minute":"54'","penalty":false,"ownGoal":false}],"venue":{"stadium":"Estadio José María Minella","city":"Mar del Plata","capacity":44000},"subs":[{"playerOff":"Giancarlo Antognoni","playerOn":"Renato Zaccarelli","minute":"46'"},{"playerOff":"Bernard Lacombe","playerOn":"Marc Berdoll","minute":"74'"},{"playerOff":"Didier Six","playerOn":"Olivier Rouyer","minute":"76'"}]},{"stage":"group stage","home":"意大利","away":"匈牙利","homeScore":3,"awayScore":1,"extra":false,"pens":false,"penScore":"","goals":[{"player":"Paolo Rossi","team":"意大利","minute":"34'","penalty":false,"ownGoal":false},{"player":"Roberto Bettega","team":"意大利","minute":"35'","penalty":false,"ownGoal":false},{"player":"Romeo Benetti","team":"意大利","minute":"61'","penalty":false,"ownGoal":false},{"player":"András Tóth","team":"匈牙利","minute":"81'","penalty":true,"ownGoal":false}],"venue":{"stadium":"Estadio José María Minella","city":"Mar del Plata","capacity":44000},"subs":[{"playerOff":"Antonio Cabrini","playerOn":"Antonello Cuccureddu","minute":"79'"},{"playerOff":"Roberto Bettega","playerOn":"Francesco Graziani","minute":"84'"},{"playerOff":"László Nagy","playerOn":"István Halász","minute":"46'"},{"playerOff":"László Fazekas","playerOn":"András Tóth","minute":"46'"}]},{"stage":"group stage","home":"阿根廷","away":"意大利","homeScore":0,"awayScore":1,"extra":false,"pens":false,"penScore":"","goals":[{"player":"Roberto Bettega","team":"意大利","minute":"67'","penalty":false,"ownGoal":false}],"venue":{"stadium":"Estadio Monumental","city":"Buenos Aires","capacity":75000},"subs":[{"playerOff":"Oscar Ortiz","playerOn":"René Houseman","minute":"72'"},{"playerOff":"Mauro Bellugi","playerOn":"Antonello Cuccureddu","minute":"6'"},{"playerOff":"Giancarlo Antognoni","playerOn":"Renato Zaccarelli","minute":"73'"}]},{"stage":"second group stage","home":"意大利","away":"西德","homeScore":0,"awayScore":0,"extra":false,"pens":false,"penScore":"","goals":[],"venue":{"stadium":"Estadio Monumental","city":"Buenos Aires","capacity":75000},"subs":[{"playerOff":"Giancarlo Antognoni","playerOn":"Renato Zaccarelli","minute":"46'"},{"playerOff":"Herbert Zimmermann","playerOn":"Harald Konopka","minute":"53'"},{"playerOff":"Heinz Flohe","playerOn":"Erich Beer","minute":"68'"}]},{"stage":"second group stage","home":"意大利","away":"奥地利","homeScore":1,"awayScore":0,"extra":false,"pens":false,"penScore":"","goals":[{"player":"Paolo Rossi","team":"意大利","minute":"13'","penalty":false,"ownGoal":false}],"venue":{"stadium":"Estadio Monumental","city":"Buenos Aires","capacity":75000},"subs":[{"playerOff":"Mauro Bellugi","playerOn":"Antonello Cuccureddu","minute":"46'"},{"playerOff":"Roberto Bettega","playerOn":"Francesco Graziani","minute":"72'"},{"playerOff":"Walter Schachner","playerOn":"Hans Pirkner","minute":"63'"}]},{"stage":"second group stage","home":"意大利","away":"荷兰","homeScore":1,"awayScore":2,"extra":false,"pens":false,"penScore":"","goals":[{"player":"Ernie Brandts","team":"意大利","minute":"19'","penalty":false,"ownGoal":true},{"player":"Ernie Brandts","team":"荷兰","minute":"49'","penalty":false,"ownGoal":false},{"player":"Arie Haan","team":"荷兰","minute":"76'","penalty":false,"ownGoal":false}],"venue":{"stadium":"Estadio Monumental","city":"Buenos Aires","capacity":75000},"subs":[{"playerOff":"Franco Causio","playerOn":"Claudio Sala","minute":"46'"},{"playerOff":"Romeo Benetti","playerOn":"","minute":"77'"},{"playerOff":"Piet Schrijvers","playerOn":"Jan Jongbloed","minute":"21'"},{"playerOff":"Johnny Rep","playerOn":"Adrie van Kraay","minute":"65'"},{"playerOff":"","playerOn":"Francesco Graziani","minute":"72'"}]},{"stage":"third-place match","home":"巴西","away":"意大利","homeScore":2,"awayScore":1,"extra":false,"pens":false,"penScore":"","goals":[{"player":"Franco Causio","team":"意大利","minute":"38'","penalty":false,"ownGoal":false},{"player":"Nelinho","team":"巴西","minute":"64'","penalty":false,"ownGoal":false},{"player":"Dirceu","team":"巴西","minute":"71'","penalty":false,"ownGoal":false}],"venue":{"stadium":"Estadio Monumental","city":"Buenos Aires","capacity":75000},"subs":[{"playerOff":"Gil","playerOn":"Reinaldo","minute":"45'+1'"},{"playerOff":"Toninho Cerezo","playerOn":"Rivellino","minute":"64'"},{"playerOff":"Giancarlo Antognoni","playerOn":"Claudio Sala","minute":"78'"}]}],"squad":[{"name":"Dino Zoff","pos":"GK","num":1,"birthDate":"1942-02-28","age":84},{"name":"Mauro Bellugi","pos":"DF","num":2,"birthDate":"1950-02-07","age":76},{"name":"Antonio Cabrini","pos":"DF","num":3,"birthDate":"1957-10-08","age":68},{"name":"Antonello Cuccureddu","pos":"DF","num":4,"birthDate":"1949-10-04","age":76},{"name":"Claudio Gentile","pos":"DF","num":5,"birthDate":"1953-09-27","age":72},{"name":"Aldo Maldera","pos":"DF","num":6,"birthDate":"1953-10-14","age":72},{"name":"Lionello Manfredonia","pos":"DF","num":7,"birthDate":"1956-11-27","age":69},{"name":"Gaetano Scirea","pos":"DF","num":8,"birthDate":"1953-05-25","age":73},{"name":"Giancarlo Antognoni","pos":"MF","num":9,"birthDate":"1954-04-01","age":72},{"name":"Romeo Benetti","pos":"MF","num":10,"birthDate":"1945-10-20","age":80},{"name":"Eraldo Pecci","pos":"MF","num":11,"birthDate":"1955-04-12","age":71},{"name":"Paolo Conti","pos":"GK","num":12,"birthDate":"1950-04-01","age":76},{"name":"Patrizio Sala","pos":"MF","num":13,"birthDate":"1955-06-16","age":70},{"name":"Marco Tardelli","pos":"MF","num":14,"birthDate":"1954-09-24","age":71},{"name":"Renato Zaccarelli","pos":"MF","num":15,"birthDate":"1951-01-18","age":75},{"name":"Franco Causio","pos":"MF","num":16,"birthDate":"1949-02-01","age":77},{"name":"Claudio Sala","pos":"MF","num":17,"birthDate":"1947-09-08","age":78},{"name":"Roberto Bettega","pos":"FW","num":18,"birthDate":"1950-12-27","age":75},{"name":"Francesco Graziani","pos":"FW","num":19,"birthDate":"1952-12-16","age":73},{"name":"Paolo Pulici","pos":"FW","num":20,"birthDate":"1950-04-27","age":76},{"name":"Paolo Rossi","pos":"FW","num":21,"birthDate":"1956-09-23","age":69},{"name":"Ivano Bordon","pos":"GK","num":22,"birthDate":"1951-04-13","age":75}]},{"year":1974,"stage":"小组赛","manager":"Ferruccio Valcareggi","cards":{"yellow":2,"red":0},"group":{"name":"Group 4","standings":[{"pos":1,"team":"波兰","p":3,"w":3,"d":0,"l":0,"gf":12,"ga":3,"pts":6},{"pos":2,"team":"阿根廷","p":3,"w":1,"d":1,"l":1,"gf":7,"ga":5,"pts":3},{"pos":3,"team":"意大利","p":3,"w":1,"d":1,"l":1,"gf":5,"ga":4,"pts":3},{"pos":4,"team":"海地","p":3,"w":0,"d":0,"l":3,"gf":2,"ga":14,"pts":0}]},"matches":[{"stage":"group stage","home":"意大利","away":"海地","homeScore":3,"awayScore":1,"extra":false,"pens":false,"penScore":"","goals":[{"player":"Emmanuel Sanon","team":"海地","minute":"46'","penalty":false,"ownGoal":false},{"player":"Gianni Rivera","team":"意大利","minute":"52'","penalty":false,"ownGoal":false},{"player":"Romeo Benetti","team":"意大利","minute":"66'","penalty":false,"ownGoal":false},{"player":"Pietro Anastasi","team":"意大利","minute":"79'","penalty":false,"ownGoal":false}],"venue":{"stadium":"Olympiastadion","city":"Munich","capacity":78000},"subs":[{"playerOff":"Giorgio Chinaglia","playerOn":"Pietro Anastasi","minute":"76'"},{"playerOff":"Guy Saint-Vil","playerOn":"Claude Barthélemy","minute":"46'"}]},{"stage":"group stage","home":"阿根廷","away":"意大利","homeScore":1,"awayScore":1,"extra":false,"pens":false,"penScore":"","goals":[{"player":"René Houseman","team":"阿根廷","minute":"20'","penalty":false,"ownGoal":false},{"player":"Roberto Perfumo","team":"意大利","minute":"35'","penalty":false,"ownGoal":true}],"venue":{"stadium":"Neckarstadion","city":"Stuttgart","capacity":72000},"subs":[{"playerOff":"Enrique Wolff","playerOn":"Rubén Glaria","minute":"60'"},{"playerOff":"Héctor Yazalde","playerOn":"Enrique Chazarreta","minute":"78'"},{"playerOff":"Francesco Morini","playerOn":"Giuseppe Wilson","minute":"66'"},{"playerOff":"Gianni Rivera","playerOn":"Franco Causio","minute":"66'"}]},{"stage":"group stage","home":"波兰","away":"意大利","homeScore":2,"awayScore":1,"extra":false,"pens":false,"penScore":"","goals":[{"player":"Andrzej Szarmach","team":"波兰","minute":"38'","penalty":false,"ownGoal":false},{"player":"Kazimierz Deyna","team":"波兰","minute":"44'","penalty":false,"ownGoal":false},{"player":"Fabio Capello","team":"意大利","minute":"85'","penalty":false,"ownGoal":false}],"venue":{"stadium":"Neckarstadion","city":"Stuttgart","capacity":72000},"subs":[{"playerOff":"Andrzej Szarmach","playerOn":"Lesław Ćmikiewicz","minute":"78'"},{"playerOff":"Tarcisio Burgnich","playerOn":"Giuseppe Wilson","minute":"33'"},{"playerOff":"Giorgio Chinaglia","playerOn":"Roberto Boninsegna","minute":"46'"}]}],"squad":[{"name":"Dino Zoff","pos":"GK","num":1,"birthDate":"1942-02-28","age":84},{"name":"Luciano Spinosi","pos":"DF","num":2,"birthDate":"1950-05-09","age":76},{"name":"Giacinto Facchetti","pos":"DF","num":3,"birthDate":"1942-07-18","age":83},{"name":"Romeo Benetti","pos":"MF","num":4,"birthDate":"1945-10-20","age":80},{"name":"Francesco Morini","pos":"DF","num":5,"birthDate":"1944-08-12","age":81},{"name":"Tarcisio Burgnich","pos":"DF","num":6,"birthDate":"1939-04-25","age":87},{"name":"Sandro Mazzola","pos":"MF","num":7,"birthDate":"1942-11-08","age":83},{"name":"Fabio Capello","pos":"MF","num":8,"birthDate":"1946-06-18","age":79},{"name":"Giorgio Chinaglia","pos":"FW","num":9,"birthDate":"1947-01-24","age":79},{"name":"Gianni Rivera","pos":"MF","num":10,"birthDate":"1943-08-18","age":82},{"name":"Gigi Riva","pos":"FW","num":11,"birthDate":"1944-11-07","age":81},{"name":"Enrico Albertosi","pos":"GK","num":12,"birthDate":"1939-11-02","age":86},{"name":"Giuseppe Sabadini","pos":"DF","num":13,"birthDate":"1949-03-26","age":77},{"name":"Mauro Bellugi","pos":"DF","num":14,"birthDate":"1950-02-07","age":76},{"name":"Giuseppe Wilson","pos":"DF","num":15,"birthDate":"1945-10-27","age":80},{"name":"Antonio Juliano","pos":"MF","num":16,"birthDate":"1943-01-01","age":83},{"name":"Luciano Re Cecconi","pos":"MF","num":17,"birthDate":"1948-12-01","age":77},{"name":"Franco Causio","pos":"MF","num":18,"birthDate":"1949-02-01","age":77},{"name":"Pietro Anastasi","pos":"FW","num":19,"birthDate":"1948-04-07","age":78},{"name":"Roberto Boninsegna","pos":"FW","num":20,"birthDate":"1943-11-13","age":82},{"name":"Paolo Pulici","pos":"FW","num":21,"birthDate":"1950-04-27","age":76},{"name":"Luciano Castellini","pos":"GK","num":22,"birthDate":"1945-12-12","age":80}]},{"year":1970,"stage":"亚军","manager":"Ferruccio Valcareggi","cards":{"yellow":7,"red":0},"group":{"name":"Group 2","standings":[{"pos":1,"team":"意大利","p":3,"w":1,"d":2,"l":0,"gf":1,"ga":0,"pts":4},{"pos":2,"team":"乌拉圭","p":3,"w":1,"d":1,"l":1,"gf":2,"ga":1,"pts":3},{"pos":3,"team":"瑞典","p":3,"w":1,"d":1,"l":1,"gf":2,"ga":2,"pts":3},{"pos":4,"team":"以色列","p":3,"w":0,"d":2,"l":1,"gf":1,"ga":3,"pts":2}]},"matches":[{"stage":"group stage","home":"意大利","away":"瑞典","homeScore":1,"awayScore":0,"extra":false,"pens":false,"penScore":"","goals":[{"player":"Angelo Domenghini","team":"意大利","minute":"10'","penalty":false,"ownGoal":false}],"venue":{"stadium":"La Bombonera","city":"Toluca","capacity":33000},"subs":[{"playerOff":"Comunardo Niccolai","playerOn":"Roberto Rosato","minute":"37'"},{"playerOff":"Leif Eriksson","playerOn":"Inge Ejderstedt","minute":"68'"},{"playerOff":"Bo Larsson","playerOn":"Göran Nicklasson","minute":"80'"}]},{"stage":"group stage","home":"乌拉圭","away":"意大利","homeScore":0,"awayScore":0,"extra":false,"pens":false,"penScore":"","goals":[],"venue":{"stadium":"Estadio Cuauhtémoc","city":"Puebla","capacity":46000},"subs":[{"playerOff":"Rúben Bareño","playerOn":"Oscar Zubia","minute":"70'"},{"playerOff":"Angelo Domenghini","playerOn":"Giuseppe Furino","minute":"46'"}]},{"stage":"group stage","home":"意大利","away":"以色列","homeScore":0,"awayScore":0,"extra":false,"pens":false,"penScore":"","goals":[],"venue":{"stadium":"La Bombonera","city":"Toluca","capacity":33000},"subs":[{"playerOff":"Angelo Domenghini","playerOn":"Gianni Rivera","minute":"46'"},{"playerOff":"Yehoshua Feigenbaum","playerOn":"Danny Shmulevich-Rom","minute":"46'"}]},{"stage":"quarter-finals","home":"意大利","away":"墨西哥","homeScore":4,"awayScore":1,"extra":false,"pens":false,"penScore":"","goals":[{"player":"José Luis González","team":"墨西哥","minute":"13'","penalty":false,"ownGoal":false},{"player":"Javier Guzmán","team":"意大利","minute":"25'","penalty":false,"ownGoal":true},{"player":"Gigi Riva","team":"意大利","minute":"63'","penalty":false,"ownGoal":false},{"player":"Gianni Rivera","team":"意大利","minute":"70'","penalty":false,"ownGoal":false},{"player":"Gigi Riva","team":"意大利","minute":"76'","penalty":false,"ownGoal":false}],"venue":{"stadium":"La Bombonera","city":"Toluca","capacity":33000},"subs":[{"playerOff":"Sandro Mazzola","playerOn":"Gianni Rivera","minute":"46'"},{"playerOff":"Angelo Domenghini","playerOn":"Sergio Gori","minute":"84'"},{"playerOff":"Antonio Munguía","playerOn":"Isidoro Díaz","minute":"60'"},{"playerOff":"José Luis González","playerOn":"Enrique Borja","minute":"68'"}]},{"stage":"semi-finals","home":"意大利","away":"西德","homeScore":4,"awayScore":3,"extra":true,"pens":false,"penScore":"","goals":[{"player":"Roberto Boninsegna","team":"意大利","minute":"8'","penalty":false,"ownGoal":false},{"player":"Karl-Heinz Schnellinger","team":"西德","minute":"90'","penalty":false,"ownGoal":false},{"player":"Gerd Müller","team":"西德","minute":"94'","penalty":false,"ownGoal":false},{"player":"Tarcisio Burgnich","team":"意大利","minute":"98'","penalty":false,"ownGoal":false},{"player":"Gigi Riva","team":"意大利","minute":"104'","penalty":false,"ownGoal":false},{"player":"Gerd Müller","team":"西德","minute":"110'","penalty":false,"ownGoal":false},{"player":"Gianni Rivera","team":"意大利","minute":"111'","penalty":false,"ownGoal":false}],"venue":{"stadium":"Estadio Azteca","city":"Mexico City","capacity":115000},"subs":[{"playerOff":"Sandro Mazzola","playerOn":"Gianni Rivera","minute":"46'"},{"playerOff":"Roberto Rosato","playerOn":"Fabrizio Poletti","minute":"91'"},{"playerOff":"Hannes Löhr","playerOn":"Reinhard Libuda","minute":"52'"},{"playerOff":"Karl-Heinz Schnellinger","playerOn":"Sigfried Held","minute":"66'"}]},{"stage":"final","home":"巴西","away":"意大利","homeScore":4,"awayScore":1,"extra":false,"pens":false,"penScore":"","goals":[{"player":"Pelé","team":"巴西","minute":"18'","penalty":false,"ownGoal":false},{"player":"Roberto Boninsegna","team":"意大利","minute":"37'","penalty":false,"ownGoal":false},{"player":"Gérson","team":"巴西","minute":"66'","penalty":false,"ownGoal":false},{"player":"Jairzinho","team":"巴西","minute":"71'","penalty":false,"ownGoal":false},{"player":"Carlos Alberto","team":"巴西","minute":"86'","penalty":false,"ownGoal":false}],"venue":{"stadium":"Estadio Azteca","city":"Mexico City","capacity":115000},"subs":[{"playerOff":"Mario Bertini","playerOn":"Antonio Juliano","minute":"75'"},{"playerOff":"Roberto Boninsegna","playerOn":"Gianni Rivera","minute":"84'"}]}],"squad":[{"name":"Enrico Albertosi","pos":"GK","num":1,"birthDate":"1939-11-02","age":86},{"name":"Tarcisio Burgnich","pos":"DF","num":2,"birthDate":"1939-04-25","age":87},{"name":"Giacinto Facchetti","pos":"DF","num":3,"birthDate":"1942-07-18","age":83},{"name":"Fabrizio Poletti","pos":"DF","num":4,"birthDate":"1943-07-13","age":82},{"name":"Pierluigi Cera","pos":"DF","num":5,"birthDate":"1941-02-25","age":85},{"name":"Ugo Ferrante","pos":"MF","num":6,"birthDate":"1945-07-18","age":80},{"name":"Comunardo Niccolai","pos":"MF","num":7,"birthDate":"1946-12-15","age":79},{"name":"Roberto Rosato","pos":"DF","num":8,"birthDate":"1943-08-18","age":82},{"name":"Giorgio Puia","pos":"DF","num":9,"birthDate":"1938-03-08","age":88},{"name":"Mario Bertini","pos":"MF","num":10,"birthDate":"1944-01-07","age":82},{"name":"Gigi Riva","pos":"FW","num":11,"birthDate":"1944-11-07","age":81},{"name":"Dino Zoff","pos":"GK","num":12,"birthDate":"1942-02-28","age":84},{"name":"Angelo Domenghini","pos":"FW","num":13,"birthDate":"1941-08-25","age":84},{"name":"Gianni Rivera","pos":"MF","num":14,"birthDate":"1943-08-18","age":82},{"name":"Sandro Mazzola","pos":"MF","num":15,"birthDate":"1942-11-08","age":83},{"name":"Giancarlo De Sisti","pos":"MF","num":16,"birthDate":"1943-03-13","age":83},{"name":"Lido Vieri","pos":"GK","num":17,"birthDate":"1939-07-16","age":86},{"name":"Antonio Juliano","pos":"DF","num":18,"birthDate":"1943-01-01","age":83},{"name":"Sergio Gori","pos":"FW","num":19,"birthDate":"1946-02-24","age":80},{"name":"Roberto Boninsegna","pos":"FW","num":20,"birthDate":"1943-11-13","age":82},{"name":"Giuseppe Furino","pos":"DF","num":21,"birthDate":"1946-07-05","age":79},{"name":"Pierino Prati","pos":"FW","num":22,"birthDate":"1946-12-13","age":79}]},{"year":1966,"stage":"小组赛","manager":"Edmondo Fabbri","cards":{"yellow":0,"red":0},"group":{"name":"Group 4","standings":[{"pos":1,"team":"苏联","p":3,"w":3,"d":0,"l":0,"gf":6,"ga":1,"pts":6},{"pos":2,"team":"朝鲜","p":3,"w":1,"d":1,"l":1,"gf":2,"ga":4,"pts":3},{"pos":3,"team":"意大利","p":3,"w":1,"d":0,"l":2,"gf":2,"ga":2,"pts":2},{"pos":4,"team":"智利","p":3,"w":0,"d":1,"l":2,"gf":2,"ga":5,"pts":1}]},"matches":[{"stage":"group stage","home":"意大利","away":"智利","homeScore":2,"awayScore":0,"extra":false,"pens":false,"penScore":"","goals":[{"player":"Sandro Mazzola","team":"意大利","minute":"8'","penalty":false,"ownGoal":false},{"player":"Paolo Barison","team":"意大利","minute":"88'","penalty":false,"ownGoal":false}],"venue":{"stadium":"Roker Park","city":"Sunderland","capacity":40000}},{"stage":"group stage","home":"苏联","away":"意大利","homeScore":1,"awayScore":0,"extra":false,"pens":false,"penScore":"","goals":[{"player":"Igor Chislenko","team":"苏联","minute":"57'","penalty":false,"ownGoal":false}],"venue":{"stadium":"Roker Park","city":"Sunderland","capacity":40000}},{"stage":"group stage","home":"朝鲜","away":"意大利","homeScore":1,"awayScore":0,"extra":false,"pens":false,"penScore":"","goals":[{"player":"Doo-ik Pak","team":"朝鲜","minute":"42'","penalty":false,"ownGoal":false}],"venue":{"stadium":"Ayresome Park","city":"Middlesbrough","capacity":40000}}],"squad":[{"name":"Enrico Albertosi","pos":"GK","num":1,"birthDate":"1939-11-02","age":86},{"name":"Roberto Anzolin","pos":"GK","num":2,"birthDate":"1938-04-18","age":88},{"name":"Paolo Barison","pos":"MF","num":3,"birthDate":"1936-06-23","age":89},{"name":"Giacomo Bulgarelli","pos":"MF","num":4,"birthDate":"1940-10-24","age":85},{"name":"Tarcisio Burgnich","pos":"DF","num":5,"birthDate":"1939-04-25","age":87},{"name":"Giacinto Facchetti","pos":"DF","num":6,"birthDate":"1942-07-18","age":83},{"name":"Romano Fogli","pos":"MF","num":7,"birthDate":"1938-01-21","age":88},{"name":"Aristide Guarneri","pos":"DF","num":8,"birthDate":"1938-03-07","age":88},{"name":"Francesco Janich","pos":"DF","num":9,"birthDate":"1937-03-27","age":89},{"name":"Antonio Juliano","pos":"FW","num":10,"birthDate":"1943-01-01","age":83},{"name":"Spartaco Landini","pos":"DF","num":11,"birthDate":"1944-01-31","age":82},{"name":"Gianfranco Leoncini","pos":"MF","num":12,"birthDate":"1939-09-25","age":86},{"name":"Giovanni Lodetti","pos":"MF","num":13,"birthDate":"1942-08-10","age":83},{"name":"Sandro Mazzola","pos":"FW","num":14,"birthDate":"1942-11-08","age":83},{"name":"Luigi Meroni","pos":"FW","num":15,"birthDate":"1943-02-24","age":83},{"name":"Ezio Pascutti","pos":"FW","num":16,"birthDate":"1937-06-01","age":89},{"name":"Marino Perani","pos":"MF","num":17,"birthDate":"1939-10-27","age":86},{"name":"Pierluigi Pizzaballa","pos":"GK","num":18,"birthDate":"1939-09-14","age":86},{"name":"Gianni Rivera","pos":"FW","num":19,"birthDate":"1943-08-18","age":82},{"name":"Francesco Rizzo","pos":"FW","num":20,"birthDate":"1943-05-30","age":83},{"name":"Roberto Rosato","pos":"DF","num":21,"birthDate":"1943-08-18","age":82},{"name":"Sandro Salvadore","pos":"DF","num":22,"birthDate":"1939-11-29","age":86}]},{"year":1962,"stage":"小组赛","manager":"Paolo Mazza","cards":{"yellow":0,"red":0},"group":{"name":"Group 2","standings":[{"pos":1,"team":"西德","p":3,"w":2,"d":1,"l":0,"gf":4,"ga":1,"pts":5},{"pos":2,"team":"智利","p":3,"w":2,"d":0,"l":1,"gf":5,"ga":3,"pts":4},{"pos":3,"team":"意大利","p":3,"w":1,"d":1,"l":1,"gf":3,"ga":2,"pts":3},{"pos":4,"team":"瑞士","p":3,"w":0,"d":0,"l":3,"gf":2,"ga":8,"pts":0}]},"matches":[{"stage":"group stage","home":"西德","away":"意大利","homeScore":0,"awayScore":0,"extra":false,"pens":false,"penScore":"","goals":[],"venue":{"stadium":"Estadio Nacional","city":"Santiago","capacity":67000}},{"stage":"group stage","home":"智利","away":"意大利","homeScore":2,"awayScore":0,"extra":false,"pens":false,"penScore":"","goals":[{"player":"Jaime Ramírez","team":"智利","minute":"73'","penalty":false,"ownGoal":false},{"player":"Jorge Toro","team":"智利","minute":"87'","penalty":false,"ownGoal":false}],"venue":{"stadium":"Estadio Nacional","city":"Santiago","capacity":67000}},{"stage":"group stage","home":"意大利","away":"瑞士","homeScore":3,"awayScore":0,"extra":false,"pens":false,"penScore":"","goals":[{"player":"Bruno Mora","team":"意大利","minute":"2'","penalty":false,"ownGoal":false},{"player":"Giacomo Bulgarelli","team":"意大利","minute":"65'","penalty":false,"ownGoal":false},{"player":"Giacomo Bulgarelli","team":"意大利","minute":"67'","penalty":false,"ownGoal":false}],"venue":{"stadium":"Estadio Nacional","city":"Santiago","capacity":67000}}],"squad":[{"name":"Lorenzo Buffon","pos":"GK","num":1,"birthDate":"1929-12-19"},{"name":"Giacomo Losi","pos":"DF","num":2,"birthDate":"1935-11-09","age":90},{"name":"Luigi Radice","pos":"MF","num":3,"birthDate":"1935-01-15"},{"name":"Sandro Salvadore","pos":"DF","num":4,"birthDate":"1939-11-29","age":86},{"name":"Cesare Maldini","pos":"DF","num":5,"birthDate":"1932-02-05"},{"name":"Giovanni Trapattoni","pos":"MF","num":6,"birthDate":"1939-03-17","age":87},{"name":"Bruno Mora","pos":"FW","num":7,"birthDate":"1937-03-29","age":89},{"name":"Humberto Maschio","pos":"FW","num":8,"birthDate":"1933-02-20"},{"name":"José Altafini","pos":"FW","num":9,"birthDate":"1938-07-24","age":87},{"name":"Omar Sívori","pos":"FW","num":10,"birthDate":"1935-10-02","age":90},{"name":"Giampaolo Menichelli","pos":"FW","num":11,"birthDate":"1938-06-29","age":87},{"name":"Carlo Mattrel","pos":"GK","num":12,"birthDate":"1937-04-14","age":89},{"name":"Enrico Albertosi","pos":"GK","num":13,"birthDate":"1939-11-02","age":86},{"name":"Gianni Rivera","pos":"FW","num":14,"birthDate":"1943-08-18","age":82},{"name":"Angelo Sormani","pos":"FW","num":15,"birthDate":"1939-07-03","age":86},{"name":"Enzo Robotti","pos":"DF","num":16,"birthDate":"1935-06-13","age":90},{"name":"Ezio Pascutti","pos":"FW","num":17,"birthDate":"1937-06-01","age":89},{"name":"Mario David","pos":"DF","num":18,"birthDate":"1934-01-03"},{"name":"Francesco Janich","pos":"DF","num":19,"birthDate":"1937-03-27","age":89},{"name":"Paride Tumburus","pos":"MF","num":20,"birthDate":"1939-03-08","age":87},{"name":"Giorgio Ferrini","pos":"MF","num":21,"birthDate":"1939-08-18","age":86},{"name":"Giacomo Bulgarelli","pos":"FW","num":22,"birthDate":"1940-10-24","age":85}]},{"year":1954,"stage":"小组赛","manager":"Lajos Czeizler","cards":{"yellow":0,"red":0},"group":{"name":"Group 4","standings":[{"pos":1,"team":"英格兰","p":2,"w":1,"d":1,"l":0,"gf":6,"ga":4,"pts":3},{"pos":2,"team":"瑞士","p":2,"w":1,"d":0,"l":1,"gf":2,"ga":3,"pts":2},{"pos":3,"team":"意大利","p":2,"w":1,"d":0,"l":1,"gf":5,"ga":3,"pts":2},{"pos":4,"team":"比利时","p":2,"w":0,"d":1,"l":1,"gf":5,"ga":8,"pts":1}]},"matches":[{"stage":"group stage","home":"瑞士","away":"意大利","homeScore":2,"awayScore":1,"extra":false,"pens":false,"penScore":"","goals":[{"player":"Robert Ballaman","team":"瑞士","minute":"18'","penalty":false,"ownGoal":false},{"player":"Giampiero Boniperti","team":"意大利","minute":"44'","penalty":false,"ownGoal":false},{"player":"Josef Hügi","team":"瑞士","minute":"78'","penalty":false,"ownGoal":false}],"venue":{"stadium":"Stade Olympique de la Pontaise","city":"Lausanne","capacity":50000}},{"stage":"group stage","home":"意大利","away":"比利时","homeScore":4,"awayScore":1,"extra":false,"pens":false,"penScore":"","goals":[{"player":"Egisto Pandolfini","team":"意大利","minute":"41'","penalty":true,"ownGoal":false},{"player":"Carlo Galli","team":"意大利","minute":"48'","penalty":false,"ownGoal":false},{"player":"Amleto Frignani","team":"意大利","minute":"58'","penalty":false,"ownGoal":false},{"player":"Benito Lorenzi","team":"意大利","minute":"78'","penalty":false,"ownGoal":false},{"player":"Léopold Anoul","team":"比利时","minute":"81'","penalty":false,"ownGoal":false}],"venue":{"stadium":"Cornaredo Stadium","city":"Lugano","capacity":36000}},{"stage":"group stage","home":"瑞士","away":"意大利","homeScore":4,"awayScore":1,"extra":false,"pens":false,"penScore":"","goals":[{"player":"Josef Hügi","team":"瑞士","minute":"14'","penalty":false,"ownGoal":false},{"player":"Robert Ballaman","team":"瑞士","minute":"48'","penalty":false,"ownGoal":false},{"player":"Fulvio Nesti","team":"意大利","minute":"67'","penalty":false,"ownGoal":false},{"player":"Josef Hügi","team":"瑞士","minute":"85'","penalty":false,"ownGoal":false},{"player":"Jacques Fatton","team":"瑞士","minute":"90'","penalty":false,"ownGoal":false}],"venue":{"stadium":"St. Jakob Stadium","city":"Basel","capacity":55000}}],"squad":[{"name":"Giorgio Ghezzi","pos":"GK","num":1,"birthDate":"1930-07-10"},{"name":"Guido Vincenzi","pos":"DF","num":2,"birthDate":"1932-07-14"},{"name":"Giovanni Giacomazzi","pos":"DF","num":3,"birthDate":"1928-01-18"},{"name":"Maino Neri","pos":"MF","num":4,"birthDate":"1924-06-30"},{"name":"Omero Tognon","pos":"MF","num":5,"birthDate":"1924-03-03"},{"name":"Fulvio Nesti","pos":"MF","num":6,"birthDate":"1925-06-08"},{"name":"Ermes Muccinelli","pos":"FW","num":7,"birthDate":"1927-07-28"},{"name":"Egisto Pandolfini","pos":"FW","num":8,"birthDate":"1926-02-19"},{"name":"Carlo Galli","pos":"FW","num":9,"birthDate":"1931-03-06"},{"name":"Gino Cappello","pos":"FW","num":10,"birthDate":"1920-06-02"},{"name":"Benito Lorenzi","pos":"FW","num":11,"birthDate":"1925-12-20"},{"name":"Giovanni Viola","pos":"GK","num":12,"birthDate":"1926-06-26"},{"name":"Ardico Magnini","pos":"DF","num":13,"birthDate":"1928-10-21"},{"name":"Sergio Cervato","pos":"DF","num":14,"birthDate":"1929-03-22"},{"name":"Giacomo Mari","pos":"MF","num":15,"birthDate":"1924-10-17"},{"name":"Rino Ferrario","pos":"MF","num":16,"birthDate":"1926-12-07"},{"name":"Armando Segato","pos":"FW","num":17,"birthDate":"1930-05-03"},{"name":"Gino Pivatelli","pos":"FW","num":18,"birthDate":"1933-03-27"},{"name":"Giampiero Boniperti","pos":"FW","num":19,"birthDate":"1928-07-04"},{"name":"Guido Gratton","pos":"MF","num":20,"birthDate":"1932-09-23"},{"name":"Amleto Frignani","pos":"FW","num":21,"birthDate":"1932-03-05"},{"name":"Leonardo Costagliola","pos":"GK","num":22,"birthDate":"1921-10-27"}]},{"year":1950,"stage":"小组赛","manager":"Ferruccio Novo","cards":{"yellow":0,"red":0},"group":{"name":"Group 3","standings":[{"pos":1,"team":"瑞典","p":2,"w":1,"d":1,"l":0,"gf":5,"ga":4,"pts":3},{"pos":2,"team":"意大利","p":2,"w":1,"d":0,"l":1,"gf":4,"ga":3,"pts":2},{"pos":3,"team":"巴拉圭","p":2,"w":0,"d":1,"l":1,"gf":2,"ga":4,"pts":1}]},"matches":[{"stage":"group stage","home":"瑞典","away":"意大利","homeScore":3,"awayScore":2,"extra":false,"pens":false,"penScore":"","goals":[{"player":"Riccardo Carapellese","team":"意大利","minute":"7'","penalty":false,"ownGoal":false},{"player":"Hasse Jeppson","team":"瑞典","minute":"25'","penalty":false,"ownGoal":false},{"player":"Sune Andersson","team":"瑞典","minute":"33'","penalty":false,"ownGoal":false},{"player":"Hasse Jeppson","team":"瑞典","minute":"68'","penalty":false,"ownGoal":false},{"player":"Ermes Muccinelli","team":"意大利","minute":"75'","penalty":false,"ownGoal":false}],"venue":{"stadium":"Estádio do Pacaembu","city":"São Paulo","capacity":60000}},{"stage":"group stage","home":"意大利","away":"巴拉圭","homeScore":2,"awayScore":0,"extra":false,"pens":false,"penScore":"","goals":[{"player":"Riccardo Carapellese","team":"意大利","minute":"12'","penalty":false,"ownGoal":false},{"player":"Egisto Pandolfini","team":"意大利","minute":"62'","penalty":false,"ownGoal":false}],"venue":{"stadium":"Estádio do Pacaembu","city":"São Paulo","capacity":60000}}],"squad":[{"name":"Amedeo Amadei","pos":"FW","num":0,"birthDate":"1921-07-26"},{"name":"Carlo Annovazzi","pos":"DF","num":0,"birthDate":"1925-05-24"},{"name":"Ivano Blason","pos":"DF","num":0,"birthDate":"1923-05-24"},{"name":"Giampiero Boniperti","pos":"FW","num":0,"birthDate":"1928-07-04"},{"name":"Aldo Campatelli","pos":"FW","num":0,"birthDate":"1919-04-07"},{"name":"Gino Cappello","pos":"FW","num":0,"birthDate":"1920-06-02"},{"name":"Emilio Caprile","pos":"FW","num":0,"birthDate":"1928-09-30"},{"name":"Riccardo Carapellese","pos":"FW","num":0,"birthDate":"1922-07-01"},{"name":"Giuseppe Casari","pos":"GK","num":0,"birthDate":"1922-04-10"},{"name":"Osvaldo Fattori","pos":"DF","num":0,"birthDate":"1922-06-22"},{"name":"Zeffiro Furiassi","pos":"DF","num":0,"birthDate":"1923-01-19"},{"name":"Attilio Giovannini","pos":"DF","num":0,"birthDate":"1924-07-30"},{"name":"Benito Lorenzi","pos":"FW","num":0,"birthDate":"1925-12-20"},{"name":"Augusto Magli","pos":"MF","num":0,"birthDate":"1923-03-09"},{"name":"Giacomo Mari","pos":"MF","num":0,"birthDate":"1924-10-17"},{"name":"Giuseppe Moro","pos":"GK","num":0,"birthDate":"1921-01-16"},{"name":"Ermes Muccinelli","pos":"FW","num":0,"birthDate":"1927-07-28"},{"name":"Egisto Pandolfini","pos":"FW","num":0,"birthDate":"1926-02-19"},{"name":"Carlo Parola","pos":"MF","num":0,"birthDate":"1921-09-20"},{"name":"Leandro Remondini","pos":"MF","num":0,"birthDate":"1917-11-17"},{"name":"Lucidio Sentimenti","pos":"GK","num":0,"birthDate":"1920-07-01"},{"name":"Omero Tognon","pos":"MF","num":0,"birthDate":"1924-03-03"}]},{"year":1938,"stage":"冠军","manager":"Vittorio Pozzo","cards":{"yellow":0,"red":0},"matches":[{"stage":"round of 16","home":"意大利","away":"挪威","homeScore":2,"awayScore":1,"extra":true,"pens":false,"penScore":"","goals":[{"player":"Pietro Ferraris","team":"意大利","minute":"2'","penalty":false,"ownGoal":false},{"player":"Arne Brustad","team":"挪威","minute":"83'","penalty":false,"ownGoal":false},{"player":"Silvio Piola","team":"意大利","minute":"94'","penalty":false,"ownGoal":false}],"venue":{"stadium":"Stade Vélodrome","city":"Marseille","capacity":60000}},{"stage":"quarter-finals","home":"意大利","away":"法国","homeScore":3,"awayScore":1,"extra":false,"pens":false,"penScore":"","goals":[{"player":"Gino Colaussi","team":"意大利","minute":"9'","penalty":false,"ownGoal":false},{"player":"Oscar Heisserer","team":"法国","minute":"10'","penalty":false,"ownGoal":false},{"player":"Silvio Piola","team":"意大利","minute":"51'","penalty":false,"ownGoal":false},{"player":"Silvio Piola","team":"意大利","minute":"72'","penalty":false,"ownGoal":false}],"venue":{"stadium":"Stade Olympique de Colombes","city":"Paris","capacity":60000}},{"stage":"semi-finals","home":"意大利","away":"巴西","homeScore":2,"awayScore":1,"extra":false,"pens":false,"penScore":"","goals":[{"player":"Gino Colaussi","team":"意大利","minute":"51'","penalty":false,"ownGoal":false},{"player":"Giuseppe Meazza","team":"意大利","minute":"60'","penalty":true,"ownGoal":false},{"player":"Romeu","team":"巴西","minute":"87'","penalty":false,"ownGoal":false}],"venue":{"stadium":"Stade Vélodrome","city":"Marseille","capacity":60000}},{"stage":"final","home":"意大利","away":"匈牙利","homeScore":4,"awayScore":2,"extra":false,"pens":false,"penScore":"","goals":[{"player":"Gino Colaussi","team":"意大利","minute":"6'","penalty":false,"ownGoal":false},{"player":"Pál Titkos","team":"匈牙利","minute":"8'","penalty":false,"ownGoal":false},{"player":"Silvio Piola","team":"意大利","minute":"16'","penalty":false,"ownGoal":false},{"player":"Gino Colaussi","team":"意大利","minute":"35'","penalty":false,"ownGoal":false},{"player":"György Sárosi","team":"匈牙利","minute":"70'","penalty":false,"ownGoal":false},{"player":"Silvio Piola","team":"意大利","minute":"82'","penalty":false,"ownGoal":false}],"venue":{"stadium":"Stade Olympique de Colombes","city":"Paris","capacity":60000}}],"squad":[{"name":"Michele Andreolo","pos":"MF","num":0,"birthDate":"1912-09-06"},{"name":"Sergio Bertoni","pos":"FW","num":0,"birthDate":"1915-09-23"},{"name":"Amedeo Biavati","pos":"FW","num":0,"birthDate":"1915-04-04"},{"name":"Carlo Ceresoli","pos":"GK","num":0,"birthDate":"1910-05-14"},{"name":"Bruno Chizzo","pos":"MF","num":0,"birthDate":"1916-04-19"},{"name":"Gino Colaussi","pos":"FW","num":0,"birthDate":"1914-03-04"},{"name":"Aldo Donati","pos":"MF","num":0,"birthDate":"1910-09-29"},{"name":"Giovanni Ferrari","pos":"FW","num":0,"birthDate":"1907-12-06"},{"name":"Pietro Ferraris","pos":"FW","num":0,"birthDate":"1912-02-15"},{"name":"Alfredo Foni","pos":"DF","num":0,"birthDate":"1911-11-20"},{"name":"Mario Genta","pos":"MF","num":0,"birthDate":"1912-03-01"},{"name":"Ugo Locatelli","pos":"MF","num":0,"birthDate":"1916-02-05"},{"name":"Guido Masetti","pos":"GK","num":0,"birthDate":"1907-11-22"},{"name":"Giuseppe Meazza","pos":"MF","num":0,"birthDate":"1910-08-23"},{"name":"Eraldo Monzeglio","pos":"DF","num":0,"birthDate":"1906-06-05"},{"name":"Aldo Olivieri","pos":"GK","num":0,"birthDate":"1910-10-02"},{"name":"Renato Olmi","pos":"MF","num":0,"birthDate":"1914-07-12"},{"name":"Piero Pasinati","pos":"FW","num":0,"birthDate":"1910-07-21"},{"name":"Mario Perazzolo","pos":"MF","num":0,"birthDate":"1911-06-07"},{"name":"Silvio Piola","pos":"FW","num":0,"birthDate":"1913-09-29"},{"name":"Pietro Rava","pos":"DF","num":0,"birthDate":"1916-01-21"},{"name":"Pietro Serantoni","pos":"MF","num":0,"birthDate":"1906-12-11"}]},{"year":1934,"stage":"冠军","manager":"Vittorio Pozzo","cards":{"yellow":0,"red":0},"matches":[{"stage":"round of 16","home":"意大利","away":"美国","homeScore":7,"awayScore":1,"extra":false,"pens":false,"penScore":"","goals":[{"player":"Angelo Schiavio","team":"意大利","minute":"18'","penalty":false,"ownGoal":false},{"player":"Raimundo Orsi","team":"意大利","minute":"20'","penalty":false,"ownGoal":false},{"player":"Angelo Schiavio","team":"意大利","minute":"29'","penalty":false,"ownGoal":false},{"player":"Aldo Donelli","team":"美国","minute":"57'","penalty":false,"ownGoal":false},{"player":"Giovanni Ferrari","team":"意大利","minute":"63'","penalty":false,"ownGoal":false},{"player":"Angelo Schiavio","team":"意大利","minute":"64'","penalty":false,"ownGoal":false},{"player":"Raimundo Orsi","team":"意大利","minute":"69'","penalty":false,"ownGoal":false},{"player":"Giuseppe Meazza","team":"意大利","minute":"90'","penalty":false,"ownGoal":false}],"venue":{"stadium":"Stadio Nazionale PNF","city":"Rome","capacity":47000}},{"stage":"quarter-finals","home":"意大利","away":"西班牙","homeScore":1,"awayScore":1,"extra":true,"pens":false,"penScore":"","goals":[{"player":"Luis Regueiro","team":"西班牙","minute":"30'","penalty":false,"ownGoal":false},{"player":"Giovanni Ferrari","team":"意大利","minute":"44'","penalty":false,"ownGoal":false}],"venue":{"stadium":"Stadio Giovanni Berta","city":"Florence","capacity":47000}},{"stage":"quarter-finals","home":"意大利","away":"西班牙","homeScore":1,"awayScore":0,"extra":false,"pens":false,"penScore":"","goals":[{"player":"Giuseppe Meazza","team":"意大利","minute":"11'","penalty":false,"ownGoal":false}],"venue":{"stadium":"Stadio Giovanni Berta","city":"Florence","capacity":47000}},{"stage":"semi-finals","home":"意大利","away":"奥地利","homeScore":1,"awayScore":0,"extra":false,"pens":false,"penScore":"","goals":[{"player":"Enrique Guaita","team":"意大利","minute":"19'","penalty":false,"ownGoal":false}],"venue":{"stadium":"San Siro","city":"Milan","capacity":75000}},{"stage":"final","home":"意大利","away":"捷克斯洛伐克","homeScore":2,"awayScore":1,"extra":true,"pens":false,"penScore":"","goals":[{"player":"Antonín Puč","team":"捷克斯洛伐克","minute":"71'","penalty":false,"ownGoal":false},{"player":"Raimundo Orsi","team":"意大利","minute":"81'","penalty":false,"ownGoal":false},{"player":"Angelo Schiavio","team":"意大利","minute":"95'","penalty":false,"ownGoal":false}],"venue":{"stadium":"Stadio Nazionale PNF","city":"Rome","capacity":47000}}],"squad":[{"name":"Luigi Allemandi","pos":"DF","num":0,"birthDate":"1903-11-18"},{"name":"Pietro Arcari","pos":"FW","num":0,"birthDate":"1909-12-02"},{"name":"Luigi Bertolini","pos":"MF","num":0,"birthDate":"1904-09-13"},{"name":"Felice Borel","pos":"FW","num":0,"birthDate":"1914-04-05"},{"name":"Umberto Caligaris","pos":"DF","num":0,"birthDate":"1901-07-26"},{"name":"Armando Castellazzi","pos":"MF","num":0,"birthDate":"1904-10-07"},{"name":"Giuseppe Cavanna","pos":"GK","num":0,"birthDate":"1905-09-18"},{"name":"Gianpiero Combi","pos":"GK","num":0,"birthDate":"1902-11-20"},{"name":"Attilio Demaría","pos":"FW","num":0,"birthDate":"1909-03-19"},{"name":"Giovanni Ferrari","pos":"FW","num":0,"birthDate":"1907-12-06"},{"name":"Attilio Ferraris","pos":"MF","num":0,"birthDate":"1904-03-26"},{"name":"Enrique Guaita","pos":"FW","num":0,"birthDate":"1910-07-11"},{"name":"Anfilogino Guarisi","pos":"FW","num":0,"birthDate":"1905-12-26"},{"name":"Guido Masetti","pos":"GK","num":0,"birthDate":"1907-11-22"},{"name":"Giuseppe Meazza","pos":"MF","num":0,"birthDate":"1910-08-23"},{"name":"Luis Monti","pos":"MF","num":0,"birthDate":"1901-05-15"},{"name":"Eraldo Monzeglio","pos":"DF","num":0,"birthDate":"1906-06-05"},{"name":"Raimundo Orsi","pos":"FW","num":0,"birthDate":"1901-12-02"},{"name":"Mario Pizziolo","pos":"MF","num":0,"birthDate":"1909-12-07"},{"name":"Virginio Rosetta","pos":"DF","num":0,"birthDate":"1902-02-25"},{"name":"Angelo Schiavio","pos":"FW","num":0,"birthDate":"1905-10-15"},{"name":"Mario Varglien","pos":"MF","num":0,"birthDate":"1905-12-26"}]}]}