{"name":"Sweden","nameZh":"瑞典","iso":"SE","confederation":"UEFA","confederationZh":"欧足联","totalStats":{"p":51,"w":20,"d":12,"l":19,"gf":80,"ga":73,"yellow":49,"red":3,"gd":7,"winRate":39.2},"topPlayers":[{"name":"Henrik Larsson","apps":13,"goals":5,"starts":10,"birthDate":"1971-09-20","age":54},{"name":"Kennet Andersson","apps":7,"goals":5,"starts":6,"birthDate":"1967-10-06","age":58},{"name":"Tomas Brolin","apps":10,"goals":4,"starts":10,"birthDate":"1969-11-29","age":56},{"name":"Ralf Edström","apps":9,"goals":4,"starts":7,"birthDate":"1952-10-07","age":73},{"name":"Martin Dahlin","apps":5,"goals":4,"starts":5,"birthDate":"1968-04-16","age":58},{"name":"Agne Simonsson","apps":0,"goals":4,"starts":0,"birthDate":"1935-10-19","age":90},{"name":"Kurt Hamrin","apps":0,"goals":4,"starts":0,"birthDate":"1934-11-19"},{"name":"Sven Jonasson","apps":0,"goals":3,"starts":0,"birthDate":"1909-07-09"},{"name":"Harry Andersson","apps":0,"goals":3,"starts":0,"birthDate":"1913-03-07"},{"name":"Gustav Wetterström","apps":0,"goals":3,"starts":0,"birthDate":"1911-10-15"},{"name":"Arne Nyberg","apps":0,"goals":3,"starts":0,"birthDate":"1913-06-20"},{"name":"Stig Sundqvist","apps":0,"goals":3,"starts":0,"birthDate":"1922-07-19"},{"name":"Karl-Erik Palmér","apps":0,"goals":3,"starts":0,"birthDate":"1929-04-17"},{"name":"Roland Sandberg","apps":6,"goals":2,"starts":6,"birthDate":"1946-12-16","age":79},{"name":"Andreas Granqvist","apps":5,"goals":2,"starts":5,"birthDate":"1985-04-16","age":41}],"tournaments":[{"year":2018,"stage":"八强","manager":"Janne Andersson","cards":{"yellow":8,"red":0},"group":{"name":"Group F","standings":[{"pos":1,"team":"瑞典","p":3,"w":2,"d":0,"l":1,"gf":5,"ga":2,"pts":6},{"pos":2,"team":"墨西哥","p":3,"w":2,"d":0,"l":1,"gf":3,"ga":4,"pts":6},{"pos":3,"team":"韩国","p":3,"w":1,"d":0,"l":2,"gf":3,"ga":3,"pts":3},{"pos":4,"team":"德国","p":3,"w":1,"d":0,"l":2,"gf":2,"ga":4,"pts":3}]},"matches":[{"stage":"group stage","home":"瑞典","away":"韩国","homeScore":1,"awayScore":0,"extra":false,"pens":false,"penScore":"","goals":[{"player":"Andreas Granqvist","team":"瑞典","minute":"65'","penalty":true,"ownGoal":false}],"venue":{"stadium":"Nizhny Novgorod Stadium","city":"Nizhny Novgorod","capacity":43000},"subs":[{"playerOff":"Albin Ekdal","playerOn":"Oscar Hiljemark","minute":"71'"},{"playerOff":"Ola Toivonen","playerOn":"Isaac Kiese Thelin","minute":"77'"},{"playerOff":"Sebastian Larsson","playerOn":"Gustav Svensson","minute":"81'"},{"playerOff":"Joo-ho Park","playerOn":"Min-woo Kim","minute":"28'"},{"playerOff":"Shin-wook Kim","playerOn":"Woo-young Jung","minute":"66'"},{"playerOff":"Ja-cheol Koo","playerOn":"Seung-woo Lee","minute":"73'"}]},{"stage":"group stage","home":"德国","away":"瑞典","homeScore":2,"awayScore":1,"extra":false,"pens":false,"penScore":"","goals":[{"player":"Ola Toivonen","team":"瑞典","minute":"32'","penalty":false,"ownGoal":false},{"player":"Marco Reus","team":"德国","minute":"48'","penalty":false,"ownGoal":false},{"player":"Toni Kroos","team":"德国","minute":"90'+5'","penalty":false,"ownGoal":false}],"venue":{"stadium":"Fisht Olympic Stadium","city":"Sochi","capacity":44000},"subs":[{"playerOff":"Sebastian Rudy","playerOn":"İlkay Gündoğan","minute":"31'"},{"playerOff":"Julian Draxler","playerOn":"Mario Gómez","minute":"46'"},{"playerOff":"Jonas Hector","playerOn":"Julian Brandt","minute":"87'"},{"playerOff":"Viktor Claesson","playerOn":"Jimmy Durmaz","minute":"74'"},{"playerOff":"Ola Toivonen","playerOn":"John Guidetti","minute":"78'"},{"playerOff":"Marcus Berg","playerOn":"Isaac Kiese Thelin","minute":"90'"}]},{"stage":"group stage","home":"墨西哥","away":"瑞典","homeScore":0,"awayScore":3,"extra":false,"pens":false,"penScore":"","goals":[{"player":"Ludwig Augustinsson","team":"瑞典","minute":"50'","penalty":false,"ownGoal":false},{"player":"Andreas Granqvist","team":"瑞典","minute":"62'","penalty":true,"ownGoal":false},{"player":"Edson Álvarez","team":"瑞典","minute":"74'","penalty":false,"ownGoal":true}],"venue":{"stadium":"Central Stadium","city":"Yekaterinburg","capacity":33000},"subs":[{"playerOff":"Jesús Gallardo","playerOn":"Marco Fabián","minute":"65'"},{"playerOff":"Andrés Guardado","playerOn":"Jesús Manuel Corona","minute":"75'"},{"playerOff":"Miguel Layún","playerOn":"Oribe Peralta","minute":"89'"},{"playerOff":"Sebastian Larsson","playerOn":"Gustav Svensson","minute":"57'"},{"playerOff":"Marcus Berg","playerOn":"Isaac Kiese Thelin","minute":"68'"},{"playerOff":"Albin Ekdal","playerOn":"Oscar Hiljemark","minute":"80'"}]},{"stage":"round of 16","home":"瑞典","away":"瑞士","homeScore":1,"awayScore":0,"extra":false,"pens":false,"penScore":"","goals":[{"player":"Emil Forsberg","team":"瑞典","minute":"66'","penalty":false,"ownGoal":false}],"venue":{"stadium":"Krestovsky Stadium","city":"Saint Petersburg","capacity":64000},"subs":[{"playerOff":"Mikael Lustig","playerOn":"Martin Olsson","minute":"82'"},{"playerOff":"Emil Forsberg","playerOn":"Emil Krafth","minute":"82'"},{"playerOff":"Marcus Berg","playerOn":"Isaac Kiese Thelin","minute":"90'+1'"},{"playerOff":"Blerim Džemaili","playerOn":"Breel Embolo","minute":"73'"},{"playerOff":"Steven Zuber","playerOn":"Haris Seferovic","minute":"73'"}]},{"stage":"quarter-finals","home":"瑞典","away":"英格兰","homeScore":0,"awayScore":2,"extra":false,"pens":false,"penScore":"","goals":[{"player":"Harry Maguire","team":"英格兰","minute":"30'","penalty":false,"ownGoal":false},{"player":"Dele Alli","team":"英格兰","minute":"59'","penalty":false,"ownGoal":false}],"venue":{"stadium":"Samara Arena","city":"Samara","capacity":42000},"subs":[{"playerOff":"Emil Forsberg","playerOn":"John Guidetti","minute":"65'"},{"playerOff":"Ola Toivonen","playerOn":"Martin Olsson","minute":"65'"},{"playerOff":"Emil Krafth","playerOn":"Pontus Jansson","minute":"85'"},{"playerOff":"Dele Alli","playerOn":"Fabian Delph","minute":"77'"},{"playerOff":"Jordan Henderson","playerOn":"Eric Dier","minute":"85'"},{"playerOff":"Raheem Sterling","playerOn":"Marcus Rashford","minute":"90'+1'"}]}],"squad":[{"name":"Robin Olsen","pos":"GK","num":1,"birthDate":"1990-01-08","age":36},{"name":"Mikael Lustig","pos":"DF","num":2,"birthDate":"1986-12-13","age":39},{"name":"Victor Lindelöf","pos":"DF","num":3,"birthDate":"1994-07-17","age":31},{"name":"Andreas Granqvist","pos":"DF","num":4,"birthDate":"1985-04-16","age":41},{"name":"Martin Olsson","pos":"DF","num":5,"birthDate":"1988-05-17","age":38},{"name":"Ludwig Augustinsson","pos":"DF","num":6,"birthDate":"1994-04-21","age":32},{"name":"Sebastian Larsson","pos":"MF","num":7,"birthDate":"1985-06-06","age":41},{"name":"Albin Ekdal","pos":"MF","num":8,"birthDate":"1989-07-28","age":36},{"name":"Marcus Berg","pos":"FW","num":9,"birthDate":"1986-08-17","age":39},{"name":"Emil Forsberg","pos":"MF","num":10,"birthDate":"1991-10-23","age":34},{"name":"John Guidetti","pos":"FW","num":11,"birthDate":"1992-04-15","age":34},{"name":"Karl-Johan Johnsson","pos":"GK","num":12,"birthDate":"1990-01-28","age":36},{"name":"Gustav Svensson","pos":"MF","num":13,"birthDate":"1987-02-07","age":39},{"name":"Filip Helander","pos":"DF","num":14,"birthDate":"1993-04-22","age":33},{"name":"Oscar Hiljemark","pos":"MF","num":15,"birthDate":"1992-06-28","age":33},{"name":"Emil Krafth","pos":"DF","num":16,"birthDate":"1994-08-02","age":31},{"name":"Viktor Claesson","pos":"MF","num":17,"birthDate":"1992-01-02","age":34},{"name":"Pontus Jansson","pos":"DF","num":18,"birthDate":"1991-02-13","age":35},{"name":"Marcus Rohdén","pos":"MF","num":19,"birthDate":"1991-05-11","age":35},{"name":"Ola Toivonen","pos":"FW","num":20,"birthDate":"1986-07-03","age":39},{"name":"Jimmy Durmaz","pos":"MF","num":21,"birthDate":"1989-03-22","age":37},{"name":"Isaac Kiese Thelin","pos":"FW","num":22,"birthDate":"1992-06-24","age":33},{"name":"Kristoffer Nordfeldt","pos":"GK","num":23,"birthDate":"1989-06-23","age":36}]},{"year":2006,"stage":"十六强","manager":"Lars Lagerbäck","cards":{"yellow":9,"red":1},"group":{"name":"Group B","standings":[{"pos":1,"team":"英格兰","p":3,"w":2,"d":1,"l":0,"gf":5,"ga":2,"pts":7},{"pos":2,"team":"瑞典","p":3,"w":1,"d":2,"l":0,"gf":3,"ga":2,"pts":5},{"pos":3,"team":"巴拉圭","p":3,"w":1,"d":0,"l":2,"gf":2,"ga":2,"pts":3},{"pos":4,"team":"特多","p":3,"w":0,"d":1,"l":2,"gf":0,"ga":4,"pts":1}]},"matches":[{"stage":"group stage","home":"特多","away":"瑞典","homeScore":0,"awayScore":0,"extra":false,"pens":false,"penScore":"","goals":[],"venue":{"stadium":"Westfalenstadion","city":"Dortmund","capacity":65000},"subs":[{"playerOff":"Collin Samuel","playerOn":"Cornell Glen","minute":"52'"},{"playerOff":"Densill Theobald","playerOn":"Aurtis Whitley","minute":"66'"},{"playerOff":"Anders Svensson","playerOn":"Marcus Allbäck","minute":"62'"},{"playerOff":"Christian Wilhelmsson","playerOn":"Mattias Jonson","minute":"78'"},{"playerOff":"Tobias Linderoth","playerOn":"Kim Källström","minute":"78'"}]},{"stage":"group stage","home":"瑞典","away":"巴拉圭","homeScore":1,"awayScore":0,"extra":false,"pens":false,"penScore":"","goals":[{"player":"Freddie Ljungberg","team":"瑞典","minute":"89'","penalty":false,"ownGoal":false}],"venue":{"stadium":"Olympiastadion","city":"Berlin","capacity":86000},"subs":[{"playerOff":"Zlatan Ibrahimović","playerOn":"Marcus Allbäck","minute":"46'"},{"playerOff":"Christian Wilhelmsson","playerOn":"Mattias Jonson","minute":"68'"},{"playerOff":"Kim Källström","playerOn":"Johan Elmander","minute":"86'"},{"playerOff":"Cristian Riveros","playerOn":"Julio dos Santos","minute":"62'"},{"playerOff":"Roque Santa Cruz","playerOn":"Dante López","minute":"63'"},{"playerOff":"Carlos Bonet","playerOn":"Édgar Barreto","minute":"81'"}]},{"stage":"group stage","home":"瑞典","away":"英格兰","homeScore":2,"awayScore":2,"extra":false,"pens":false,"penScore":"","goals":[{"player":"Joe Cole","team":"英格兰","minute":"34'","penalty":false,"ownGoal":false},{"player":"Marcus Allbäck","team":"瑞典","minute":"51'","penalty":false,"ownGoal":false},{"player":"Steven Gerrard","team":"英格兰","minute":"85'","penalty":false,"ownGoal":false},{"player":"Henrik Larsson","team":"瑞典","minute":"90'","penalty":false,"ownGoal":false}],"venue":{"stadium":"RheinEnergieStadion","city":"Cologne","capacity":45000},"subs":[{"playerOff":"Mattias Jonson","playerOn":"Christian Wilhelmsson","minute":"54'"},{"playerOff":"Marcus Allbäck","playerOn":"Johan Elmander","minute":"75'"},{"playerOff":"Tobias Linderoth","playerOn":"Daniel Andersson","minute":"90'+1'"},{"playerOff":"Michael Owen","playerOn":"Peter Crouch","minute":"4'"},{"playerOff":"Rio Ferdinand","playerOn":"Sol Campbell","minute":"56'"},{"playerOff":"Wayne Rooney","playerOn":"Steven Gerrard","minute":"69'"}]},{"stage":"round of 16","home":"德国","away":"瑞典","homeScore":2,"awayScore":0,"extra":false,"pens":false,"penScore":"","goals":[{"player":"Lukas Podolski","team":"德国","minute":"4'","penalty":false,"ownGoal":false},{"player":"Lukas Podolski","team":"德国","minute":"12'","penalty":false,"ownGoal":false}],"venue":{"stadium":"Allianz Arena","city":"Munich","capacity":66000},"subs":[{"playerOff":"Bastian Schweinsteiger","playerOn":"Tim Borowski","minute":"72'"},{"playerOff":"Lukas Podolski","playerOn":"Oliver Neuville","minute":"74'"},{"playerOff":"Torsten Frings","playerOn":"Sebastian Kehl","minute":"85'"},{"playerOff":"Kim Källström","playerOn":"Petter Hansson","minute":"39'"},{"playerOff":"Mattias Jonson","playerOn":"Christian Wilhelmsson","minute":"52'"},{"playerOff":"Zlatan Ibrahimović","playerOn":"Marcus Allbäck","minute":"72'"}]}],"squad":[{"name":"Andreas Isaksson","pos":"GK","num":1,"birthDate":"1981-10-03","age":44},{"name":"Mikael Nilsson","pos":"DF","num":2,"birthDate":"1978-06-24","age":47},{"name":"Olof Mellberg","pos":"DF","num":3,"birthDate":"1977-09-03","age":48},{"name":"Teddy Lučić","pos":"DF","num":4,"birthDate":"1973-04-15","age":53},{"name":"Erik Edman","pos":"DF","num":5,"birthDate":"1978-11-11","age":47},{"name":"Tobias Linderoth","pos":"MF","num":6,"birthDate":"1979-04-21","age":47},{"name":"Niclas Alexandersson","pos":"MF","num":7,"birthDate":"1971-12-29","age":54},{"name":"Anders Svensson","pos":"MF","num":8,"birthDate":"1976-07-17","age":49},{"name":"Freddie Ljungberg","pos":"MF","num":9,"birthDate":"1977-04-16","age":49},{"name":"Zlatan Ibrahimović","pos":"FW","num":10,"birthDate":"1981-10-03","age":44},{"name":"Henrik Larsson","pos":"FW","num":11,"birthDate":"1971-09-20","age":54},{"name":"John Alvbåge","pos":"GK","num":12,"birthDate":"1982-08-10","age":43},{"name":"Petter Hansson","pos":"DF","num":13,"birthDate":"1976-12-14","age":49},{"name":"Fredrik Stenman","pos":"DF","num":14,"birthDate":"1983-06-02","age":43},{"name":"Karl Svensson","pos":"DF","num":15,"birthDate":"1984-03-21","age":42},{"name":"Kim Källström","pos":"MF","num":16,"birthDate":"1982-08-24","age":43},{"name":"Johan Elmander","pos":"FW","num":17,"birthDate":"1981-05-27","age":45},{"name":"Mattias Jonson","pos":"MF","num":18,"birthDate":"1974-01-16","age":52},{"name":"Daniel Andersson","pos":"MF","num":19,"birthDate":"1977-08-28","age":48},{"name":"Marcus Allbäck","pos":"FW","num":20,"birthDate":"1973-07-05","age":52},{"name":"Christian Wilhelmsson","pos":"MF","num":21,"birthDate":"1979-12-08","age":46},{"name":"Markus Rosenberg","pos":"FW","num":22,"birthDate":"1982-09-27","age":43},{"name":"Rami Shaaban","pos":"GK","num":23,"birthDate":"1975-06-30","age":50}]},{"year":2002,"stage":"十六强","manager":"Tommy Söderberg","cards":{"yellow":6,"red":0},"group":{"name":"Group F","standings":[{"pos":1,"team":"瑞典","p":3,"w":1,"d":2,"l":0,"gf":4,"ga":3,"pts":5},{"pos":2,"team":"英格兰","p":3,"w":1,"d":2,"l":0,"gf":2,"ga":1,"pts":5},{"pos":3,"team":"阿根廷","p":3,"w":1,"d":1,"l":1,"gf":2,"ga":2,"pts":4},{"pos":4,"team":"尼日利亚","p":3,"w":0,"d":1,"l":2,"gf":1,"ga":3,"pts":1}]},"matches":[{"stage":"group stage","home":"英格兰","away":"瑞典","homeScore":1,"awayScore":1,"extra":false,"pens":false,"penScore":"","goals":[{"player":"Sol Campbell","team":"英格兰","minute":"24'","penalty":false,"ownGoal":false},{"player":"Niclas Alexandersson","team":"瑞典","minute":"59'","penalty":false,"ownGoal":false}],"venue":{"stadium":"Saitama Stadium","city":"Saitama","capacity":63000},"subs":[{"playerOff":"David Beckham","playerOn":"Kieron Dyer","minute":"63'"},{"playerOff":"Darius Vassell","playerOn":"Joe Cole","minute":"74'"},{"playerOff":"Magnus Svensson","playerOn":"Anders Svensson","minute":"56'"},{"playerOff":"Marcus Allbäck","playerOn":"Andreas Andersson","minute":"80'"}]},{"stage":"group stage","home":"瑞典","away":"尼日利亚","homeScore":2,"awayScore":1,"extra":false,"pens":false,"penScore":"","goals":[{"player":"Julius Aghahowa","team":"尼日利亚","minute":"27'","penalty":false,"ownGoal":false},{"player":"Henrik Larsson","team":"瑞典","minute":"35'","penalty":false,"ownGoal":false},{"player":"Henrik Larsson","team":"瑞典","minute":"63'","penalty":true,"ownGoal":false}],"venue":{"stadium":"Kobe Wing Stadium","city":"Kobe","capacity":42000},"subs":[{"playerOff":"Marcus Allbäck","playerOn":"Andreas Andersson","minute":"64'"},{"playerOff":"Anders Svensson","playerOn":"Magnus Svensson","minute":"83'"},{"playerOff":"Celestine Babayaro","playerOn":"Nwankwo Kanu","minute":"65'"},{"playerOff":"Bartholomew Ogbeche","playerOn":"Pius Ikedia","minute":"70'"}]},{"stage":"group stage","home":"瑞典","away":"阿根廷","homeScore":1,"awayScore":1,"extra":false,"pens":false,"penScore":"","goals":[{"player":"Anders Svensson","team":"瑞典","minute":"59'","penalty":false,"ownGoal":false},{"player":"Hernán Crespo","team":"阿根廷","minute":"88'","penalty":false,"ownGoal":false}],"venue":{"stadium":"Miyagi Stadium","city":"Miyagi","capacity":49000},"subs":[{"playerOff":"Marcus Allbäck","playerOn":"Andreas Andersson","minute":"46'"},{"playerOff":"Anders Svensson","playerOn":"Mattias Jonson","minute":"68'"},{"playerOff":"Henrik Larsson","playerOn":"Zlatan Ibrahimović","minute":"88'"},{"playerOff":"Gabriel Batistuta","playerOn":"Hernán Crespo","minute":"58'"},{"playerOff":"Matías Almeyda","playerOn":"Juan Sebastián Verón","minute":"63'"},{"playerOff":"Juan Pablo Sorín","playerOn":"Kily González","minute":"63'"}]},{"stage":"round of 16","home":"瑞典","away":"塞内加尔","homeScore":1,"awayScore":2,"extra":true,"pens":false,"penScore":"","goals":[{"player":"Henrik Larsson","team":"瑞典","minute":"11'","penalty":false,"ownGoal":false},{"player":"Henri Camara","team":"塞内加尔","minute":"37'","penalty":false,"ownGoal":false},{"player":"Henri Camara","team":"塞内加尔","minute":"104'","penalty":false,"ownGoal":false}],"venue":{"stadium":"Ōita Stadium","city":"Ōita","capacity":43000},"subs":[{"playerOff":"Marcus Allbäck","playerOn":"Andreas Andersson","minute":"65'"},{"playerOff":"Niclas Alexandersson","playerOn":"Zlatan Ibrahimović","minute":"76'"},{"playerOff":"Magnus Svensson","playerOn":"Mattias Jonson","minute":"99'"},{"playerOff":"Pape Malick Diop","playerOn":"Habib Beye","minute":"66'"}]}],"squad":[{"name":"Magnus Hedman","pos":"GK","num":1,"birthDate":"1973-03-19","age":53},{"name":"Olof Mellberg","pos":"DF","num":2,"birthDate":"1977-09-03","age":48},{"name":"Patrik Andersson","pos":"DF","num":3,"birthDate":"1971-08-18","age":54},{"name":"Johan Mjällby","pos":"DF","num":4,"birthDate":"1971-02-09","age":55},{"name":"Michael Svensson","pos":"DF","num":5,"birthDate":"1975-11-25","age":50},{"name":"Tobias Linderoth","pos":"MF","num":6,"birthDate":"1979-04-21","age":47},{"name":"Niclas Alexandersson","pos":"MF","num":7,"birthDate":"1971-12-29","age":54},{"name":"Anders Svensson","pos":"MF","num":8,"birthDate":"1976-07-17","age":49},{"name":"Freddie Ljungberg","pos":"MF","num":9,"birthDate":"1977-04-16","age":49},{"name":"Marcus Allbäck","pos":"FW","num":10,"birthDate":"1973-07-05","age":52},{"name":"Henrik Larsson","pos":"FW","num":11,"birthDate":"1971-09-20","age":54},{"name":"Magnus Kihlstedt","pos":"GK","num":12,"birthDate":"1972-02-29","age":54},{"name":"Tomas Antonelius","pos":"DF","num":13,"birthDate":"1973-05-07","age":53},{"name":"Erik Edman","pos":"DF","num":14,"birthDate":"1978-11-11","age":47},{"name":"Andreas Jakobsson","pos":"DF","num":15,"birthDate":"1972-10-06","age":53},{"name":"Teddy Lučić","pos":"DF","num":16,"birthDate":"1973-04-15","age":53},{"name":"Magnus Svensson","pos":"MF","num":17,"birthDate":"1969-03-10","age":57},{"name":"Mattias Jonson","pos":"MF","num":18,"birthDate":"1974-01-16","age":52},{"name":"Pontus Farnerud","pos":"MF","num":19,"birthDate":"1980-06-04","age":46},{"name":"Daniel Andersson","pos":"MF","num":20,"birthDate":"1977-08-28","age":48},{"name":"Zlatan Ibrahimović","pos":"FW","num":21,"birthDate":"1981-10-03","age":44},{"name":"Andreas Andersson","pos":"FW","num":22,"birthDate":"1974-04-10","age":52},{"name":"Andreas Isaksson","pos":"GK","num":23,"birthDate":"1981-10-03","age":44}]},{"year":1994,"stage":"季军赛","manager":"Tommy Svensson","cards":{"yellow":13,"red":2},"group":{"name":"Group B","standings":[{"pos":1,"team":"巴西","p":3,"w":2,"d":1,"l":0,"gf":6,"ga":1,"pts":7},{"pos":2,"team":"瑞典","p":3,"w":1,"d":2,"l":0,"gf":6,"ga":4,"pts":5},{"pos":3,"team":"俄罗斯","p":3,"w":1,"d":0,"l":2,"gf":7,"ga":6,"pts":3},{"pos":4,"team":"喀麦隆","p":3,"w":0,"d":1,"l":2,"gf":3,"ga":11,"pts":1}]},"matches":[{"stage":"group stage","home":"喀麦隆","away":"瑞典","homeScore":2,"awayScore":2,"extra":false,"pens":false,"penScore":"","goals":[{"player":"Roger Ljung","team":"瑞典","minute":"8'","penalty":false,"ownGoal":false},{"player":"David Embé","team":"喀麦隆","minute":"31'","penalty":false,"ownGoal":false},{"player":"François Omam-Biyik","team":"喀麦隆","minute":"47'","penalty":false,"ownGoal":false},{"player":"Martin Dahlin","team":"瑞典","minute":"75'","penalty":false,"ownGoal":false}],"venue":{"stadium":"Rose Bowl","city":"Pasadena","capacity":94000},"subs":[{"playerOff":"David Embé","playerOn":"Georges Mouyémé","minute":"81'"},{"playerOff":"Louis-Paul M'Fédé","playerOn":"Emmanuel Maboang","minute":"88'"},{"playerOff":"Jesper Blomqvist","playerOn":"Henrik Larsson","minute":"61'"},{"playerOff":"Klas Ingesson","playerOn":"Kennet Andersson","minute":"76'"}]},{"stage":"group stage","home":"瑞典","away":"俄罗斯","homeScore":3,"awayScore":1,"extra":false,"pens":false,"penScore":"","goals":[{"player":"Oleg Salenko","team":"俄罗斯","minute":"4'","penalty":true,"ownGoal":false},{"player":"Tomas Brolin","team":"瑞典","minute":"39'","penalty":true,"ownGoal":false},{"player":"Martin Dahlin","team":"瑞典","minute":"60'","penalty":false,"ownGoal":false},{"player":"Martin Dahlin","team":"瑞典","minute":"82'","penalty":false,"ownGoal":false}],"venue":{"stadium":"Pontiac Silverdome","city":"Pontiac","capacity":78000},"subs":[{"playerOff":"Kennet Andersson","playerOn":"Henrik Larsson","minute":"84'"},{"playerOff":"Joachim Björklund","playerOn":"Magnus Erlingmark","minute":"89'"},{"playerOff":"Dmitri Popov","playerOn":"Valeri Karpin","minute":"41'"},{"playerOff":"Aleksandr Borodyuk","playerOn":"Dmitri Galiamin","minute":"51'"}]},{"stage":"group stage","home":"巴西","away":"瑞典","homeScore":1,"awayScore":1,"extra":false,"pens":false,"penScore":"","goals":[{"player":"Kennet Andersson","team":"瑞典","minute":"23'","penalty":false,"ownGoal":false},{"player":"Romário","team":"巴西","minute":"47'","penalty":false,"ownGoal":false}],"venue":{"stadium":"Pontiac Silverdome","city":"Pontiac","capacity":78000},"subs":[{"playerOff":"Mauro Silva","playerOn":"Mazinho","minute":"45'"},{"playerOff":"Raí","playerOn":"Paulo Sérgio","minute":"83'"},{"playerOff":"Henrik Larsson","playerOn":"Jesper Blomqvist","minute":"65'"},{"playerOff":"Stefan Schwarz","playerOn":"Håkan Mild","minute":"75'"}]},{"stage":"round of 16","home":"沙特","away":"瑞典","homeScore":1,"awayScore":3,"extra":false,"pens":false,"penScore":"","goals":[{"player":"Martin Dahlin","team":"瑞典","minute":"6'","penalty":false,"ownGoal":false},{"player":"Kennet Andersson","team":"瑞典","minute":"51'","penalty":false,"ownGoal":false},{"player":"Fahad Al-Ghesheyan","team":"沙特","minute":"85'","penalty":false,"ownGoal":false},{"player":"Kennet Andersson","team":"瑞典","minute":"88'","penalty":false,"ownGoal":false}],"venue":{"stadium":"Cotton Bowl","city":"Dallas","capacity":64000},"subs":[{"playerOff":"Mohamed Abd Al-Jawad","playerOn":"Fahad Al-Ghesheyan","minute":"55'"},{"playerOff":"Fahad Al-Bishi","playerOn":"Khalid Al-Muwallid","minute":"63'"},{"playerOff":"Joachim Björklund","playerOn":"Pontus Kåmark","minute":"55'"},{"playerOff":"Jonas Thern","playerOn":"Håkan Mild","minute":"70'"}]},{"stage":"quarter-finals","home":"罗马尼亚","away":"瑞典","homeScore":2,"awayScore":2,"extra":true,"pens":true,"penScore":"4-5","goals":[{"player":"Tomas Brolin","team":"瑞典","minute":"78'","penalty":false,"ownGoal":false},{"player":"Florin Răducioiu","team":"罗马尼亚","minute":"88'","penalty":false,"ownGoal":false},{"player":"Florin Răducioiu","team":"罗马尼亚","minute":"101'","penalty":false,"ownGoal":false},{"player":"Kennet Andersson","team":"瑞典","minute":"115'","penalty":false,"ownGoal":false}],"venue":{"stadium":"Stanford Stadium","city":"Stanford","capacity":84000},"subs":[{"playerOff":"Dorinel Munteanu","playerOn":"Basarab Panduru","minute":"84'"},{"playerOff":"Joachim Björklund","playerOn":"Pontus Kåmark","minute":"84'"},{"playerOff":"Martin Dahlin","playerOn":"Henrik Larsson","minute":"107'"}]},{"stage":"semi-finals","home":"瑞典","away":"巴西","homeScore":0,"awayScore":1,"extra":false,"pens":false,"penScore":"","goals":[{"player":"Romário","team":"巴西","minute":"80'","penalty":false,"ownGoal":false}],"venue":{"stadium":"Rose Bowl","city":"Pasadena","capacity":94000},"subs":[{"playerOff":"Martin Dahlin","playerOn":"Stefan Rehn","minute":"68'"},{"playerOff":"Mazinho","playerOn":"Raí","minute":"45'"}]},{"stage":"third-place match","home":"瑞典","away":"保加利亚","homeScore":4,"awayScore":0,"extra":false,"pens":false,"penScore":"","goals":[{"player":"Tomas Brolin","team":"瑞典","minute":"8'","penalty":false,"ownGoal":false},{"player":"Håkan Mild","team":"瑞典","minute":"30'","penalty":false,"ownGoal":false},{"player":"Henrik Larsson","team":"瑞典","minute":"37'","penalty":false,"ownGoal":false},{"player":"Kennet Andersson","team":"瑞典","minute":"39'","penalty":false,"ownGoal":false}],"venue":{"stadium":"Rose Bowl","city":"Pasadena","capacity":94000},"subs":[{"playerOff":"Henrik Larsson","playerOn":"Anders Limpar","minute":"79'"},{"playerOff":"Trifon Ivanov","playerOn":"Emil Kremenliev","minute":"42'"},{"playerOff":"Borislav Mihaylov","playerOn":"Plamen Nikolov","minute":"46'"},{"playerOff":"Nasko Sirakov","playerOn":"Ivaylo Yordanov","minute":"46'"}]}],"squad":[{"name":"Thomas Ravelli","pos":"GK","num":1,"birthDate":"1959-08-13","age":66},{"name":"Roland Nilsson","pos":"DF","num":2,"birthDate":"1963-11-27","age":62},{"name":"Patrik Andersson","pos":"DF","num":3,"birthDate":"1971-08-18","age":54},{"name":"Joachim Björklund","pos":"DF","num":4,"birthDate":"1971-03-15","age":55},{"name":"Roger Ljung","pos":"DF","num":5,"birthDate":"1966-01-08","age":60},{"name":"Stefan Schwarz","pos":"MF","num":6,"birthDate":"1969-04-18","age":57},{"name":"Henrik Larsson","pos":"FW","num":7,"birthDate":"1971-09-20","age":54},{"name":"Klas Ingesson","pos":"MF","num":8,"birthDate":"1968-08-20","age":57},{"name":"Jonas Thern","pos":"MF","num":9,"birthDate":"1967-03-20","age":59},{"name":"Martin Dahlin","pos":"FW","num":10,"birthDate":"1968-04-16","age":58},{"name":"Tomas Brolin","pos":"FW","num":11,"birthDate":"1969-11-29","age":56},{"name":"Lars Eriksson","pos":"GK","num":12,"birthDate":"1965-09-21","age":60},{"name":"Mikael Nilsson","pos":"DF","num":13,"birthDate":"1968-09-28","age":57},{"name":"Pontus Kåmark","pos":"DF","num":14,"birthDate":"1969-04-05","age":57},{"name":"Teddy Lučić","pos":"DF","num":15,"birthDate":"1973-04-15","age":53},{"name":"Anders Limpar","pos":"MF","num":16,"birthDate":"1965-09-24","age":60},{"name":"Stefan Rehn","pos":"MF","num":17,"birthDate":"1966-09-22","age":59},{"name":"Håkan Mild","pos":"MF","num":18,"birthDate":"1971-06-14","age":54},{"name":"Kennet Andersson","pos":"FW","num":19,"birthDate":"1967-10-06","age":58},{"name":"Magnus Erlingmark","pos":"DF","num":20,"birthDate":"1968-07-08","age":57},{"name":"Jesper Blomqvist","pos":"MF","num":21,"birthDate":"1974-02-05","age":52},{"name":"Magnus Hedman","pos":"GK","num":22,"birthDate":"1973-03-19","age":53}]},{"year":1990,"stage":"小组赛","manager":"Olle Nordin","cards":{"yellow":4,"red":0},"group":{"name":"Group C","standings":[{"pos":1,"team":"巴西","p":3,"w":3,"d":0,"l":0,"gf":4,"ga":1,"pts":6},{"pos":2,"team":"哥斯达黎加","p":3,"w":2,"d":0,"l":1,"gf":3,"ga":2,"pts":4},{"pos":3,"team":"苏格兰","p":3,"w":1,"d":0,"l":2,"gf":2,"ga":3,"pts":2},{"pos":4,"team":"瑞典","p":3,"w":0,"d":0,"l":3,"gf":3,"ga":6,"pts":0}]},"matches":[{"stage":"group stage","home":"巴西","away":"瑞典","homeScore":2,"awayScore":1,"extra":false,"pens":false,"penScore":"","goals":[{"player":"Careca","team":"巴西","minute":"40'","penalty":false,"ownGoal":false},{"player":"Careca","team":"巴西","minute":"63'","penalty":false,"ownGoal":false},{"player":"Tomas Brolin","team":"瑞典","minute":"79'","penalty":false,"ownGoal":false}],"venue":{"stadium":"Stadio delle Alpi","city":"Turin","capacity":63000},"subs":[{"playerOff":"Valdo","playerOn":"Paulo Silas","minute":"82'"},{"playerOff":"Mats Magnusson","playerOn":"Stefan Pettersson","minute":"46'"},{"playerOff":"Roger Ljung","playerOn":"Glenn Strömberg","minute":"70'"}]},{"stage":"group stage","home":"瑞典","away":"苏格兰","homeScore":1,"awayScore":2,"extra":false,"pens":false,"penScore":"","goals":[{"player":"Stuart McCall","team":"苏格兰","minute":"11'","penalty":false,"ownGoal":false},{"player":"Mo Johnston","team":"苏格兰","minute":"81'","penalty":true,"ownGoal":false},{"player":"Glenn Strömberg","team":"瑞典","minute":"86'","penalty":false,"ownGoal":false}],"venue":{"stadium":"Stadio Luigi Ferraris","city":"Genoa","capacity":37000},"subs":[{"playerOff":"Stefan Pettersson","playerOn":"Johnny Ekström","minute":"62'"},{"playerOff":"Peter Larsson","playerOn":"Glenn Strömberg","minute":"75'"},{"playerOff":"Gordon Durie","playerOn":"Paul McStay","minute":"75'"},{"playerOff":"Robert Fleck","playerOn":"Ally McCoist","minute":"84'"}]},{"stage":"group stage","home":"瑞典","away":"哥斯达黎加","homeScore":1,"awayScore":2,"extra":false,"pens":false,"penScore":"","goals":[{"player":"Johnny Ekström","team":"瑞典","minute":"32'","penalty":false,"ownGoal":false},{"player":"Róger Flores","team":"哥斯达黎加","minute":"75'","penalty":false,"ownGoal":false},{"player":"Hernán Medford","team":"哥斯达黎加","minute":"87'","penalty":false,"ownGoal":false}],"venue":{"stadium":"Stadio Luigi Ferraris","city":"Genoa","capacity":37000},"subs":[{"playerOff":"Tomas Brolin","playerOn":"Mats Gren","minute":"34'"},{"playerOff":"Glenn Strömberg","playerOn":"Leif Engqvist","minute":"81'"},{"playerOff":"Róger Gómez","playerOn":"Hernán Medford","minute":"60'"},{"playerOff":"Germán Chavarría","playerOn":"Alexandre Guimarães","minute":"73'"}]}],"squad":[{"name":"Sven Andersson","pos":"GK","num":1,"birthDate":"1963-10-06","age":62},{"name":"Jan Eriksson","pos":"DF","num":2,"birthDate":"1967-08-24","age":58},{"name":"Glenn Hysén","pos":"DF","num":3,"birthDate":"1959-10-30","age":66},{"name":"Peter Larsson","pos":"DF","num":4,"birthDate":"1961-03-08","age":65},{"name":"Roger Ljung","pos":"DF","num":5,"birthDate":"1966-01-08","age":60},{"name":"Roland Nilsson","pos":"DF","num":6,"birthDate":"1963-11-27","age":62},{"name":"Niklas Nyhlén","pos":"MF","num":7,"birthDate":"1966-03-21","age":60},{"name":"Stefan Schwarz","pos":"MF","num":8,"birthDate":"1969-04-18","age":57},{"name":"Leif Engqvist","pos":"MF","num":9,"birthDate":"1962-07-30","age":63},{"name":"Klas Ingesson","pos":"MF","num":10,"birthDate":"1968-08-20","age":57},{"name":"Ulrik Jansson","pos":"MF","num":11,"birthDate":"1968-02-02","age":58},{"name":"Lars Eriksson","pos":"GK","num":12,"birthDate":"1965-09-21","age":60},{"name":"Anders Limpar","pos":"MF","num":13,"birthDate":"1965-09-24","age":60},{"name":"Joakim Nilsson","pos":"MF","num":14,"birthDate":"1966-03-31","age":60},{"name":"Glenn Strömberg","pos":"MF","num":15,"birthDate":"1960-01-05","age":66},{"name":"Jonas Thern","pos":"MF","num":16,"birthDate":"1967-03-20","age":59},{"name":"Tomas Brolin","pos":"FW","num":17,"birthDate":"1969-11-29","age":56},{"name":"Johnny Ekström","pos":"FW","num":18,"birthDate":"1965-03-05","age":61},{"name":"Mats Gren","pos":"DF","num":19,"birthDate":"1963-12-20","age":62},{"name":"Mats Magnusson","pos":"FW","num":20,"birthDate":"1963-07-10","age":62},{"name":"Stefan Pettersson","pos":"FW","num":21,"birthDate":"1963-03-22","age":63},{"name":"Thomas Ravelli","pos":"GK","num":22,"birthDate":"1959-08-13","age":66}]},{"year":1978,"stage":"小组赛","manager":"Georg Ericson","cards":{"yellow":2,"red":0},"group":{"name":"Group 3","standings":[{"pos":1,"team":"奥地利","p":3,"w":2,"d":0,"l":1,"gf":3,"ga":2,"pts":4},{"pos":2,"team":"巴西","p":3,"w":1,"d":2,"l":0,"gf":2,"ga":1,"pts":4},{"pos":3,"team":"西班牙","p":3,"w":1,"d":1,"l":1,"gf":2,"ga":2,"pts":3},{"pos":4,"team":"瑞典","p":3,"w":0,"d":1,"l":2,"gf":1,"ga":3,"pts":1}]},"matches":[{"stage":"group stage","home":"巴西","away":"瑞典","homeScore":1,"awayScore":1,"extra":false,"pens":false,"penScore":"","goals":[{"player":"Thomas Sjöberg","team":"瑞典","minute":"37'","penalty":false,"ownGoal":false},{"player":"Reinaldo","team":"巴西","minute":"45'","penalty":false,"ownGoal":false}],"venue":{"stadium":"Estadio José María Minella","city":"Mar del Plata","capacity":44000},"subs":[{"playerOff":"Gil","playerOn":"Nelinho","minute":"68'"},{"playerOff":"Toninho Cerezo","playerOn":"Dirceu","minute":"80'"},{"playerOff":"Lennart Larsson","playerOn":"Ralf Edström","minute":"79'"}]},{"stage":"group stage","home":"奥地利","away":"瑞典","homeScore":1,"awayScore":0,"extra":false,"pens":false,"penScore":"","goals":[{"player":"Hans Krankl","team":"奥地利","minute":"42'","penalty":true,"ownGoal":false}],"venue":{"stadium":"Estadio José Amalfitani","city":"Buenos Aires","capacity":49000},"subs":[{"playerOff":"Eduard Krieger","playerOn":"Heribert Weber","minute":"71'"},{"playerOff":"Staffan Tapper","playerOn":"Conny Torstensson","minute":"36'"},{"playerOff":"Anders Linderoth","playerOn":"Ralf Edström","minute":"60'"}]},{"stage":"group stage","home":"西班牙","away":"瑞典","homeScore":1,"awayScore":0,"extra":false,"pens":false,"penScore":"","goals":[{"player":"Juan Manuel Asensi","team":"西班牙","minute":"75'","penalty":false,"ownGoal":false}],"venue":{"stadium":"Estadio José Amalfitani","city":"Buenos Aires","capacity":49000},"subs":[{"playerOff":"Antonio Olmo","playerOn":"Pirri","minute":"45'"},{"playerOff":"Ralf Edström","playerOn":"Benny Wendt","minute":"60'"},{"playerOff":"Thomas Sjöberg","playerOn":"Anders Linderoth","minute":"67'"}]}],"squad":[{"name":"Ronnie Hellström","pos":"GK","num":1,"birthDate":"1949-02-21","age":77},{"name":"Hasse Borg","pos":"DF","num":2,"birthDate":"1953-08-04","age":72},{"name":"Roy Andersson","pos":"DF","num":3,"birthDate":"1949-08-02","age":76},{"name":"Björn Nordqvist","pos":"MF","num":4,"birthDate":"1942-10-06","age":83},{"name":"Ingemar Erlandsson","pos":"DF","num":5,"birthDate":"1957-11-16","age":68},{"name":"Staffan Tapper","pos":"MF","num":6,"birthDate":"1948-07-10","age":77},{"name":"Anders Linderoth","pos":"MF","num":7,"birthDate":"1950-03-21","age":76},{"name":"Bo Larsson","pos":"FW","num":8,"birthDate":"1944-05-05","age":82},{"name":"Lennart Larsson","pos":"MF","num":9,"birthDate":"1953-07-09","age":72},{"name":"Thomas Sjöberg","pos":"FW","num":10,"birthDate":"1952-07-06","age":73},{"name":"Benny Wendt","pos":"FW","num":11,"birthDate":"1950-11-04","age":75},{"name":"Göran Hagberg","pos":"GK","num":12,"birthDate":"1947-11-08","age":78},{"name":"Magnus Andersson","pos":"DF","num":13,"birthDate":"1958-04-23","age":68},{"name":"Ronald Åhman","pos":"MF","num":14,"birthDate":"1957-01-31","age":69},{"name":"Torbjörn Nilsson","pos":"FW","num":15,"birthDate":"1954-07-09","age":71},{"name":"Conny Torstensson","pos":"FW","num":16,"birthDate":"1949-08-28","age":76},{"name":"Jan Möller","pos":"GK","num":17,"birthDate":"1953-09-17","age":72},{"name":"Olle Nordin","pos":"MF","num":18,"birthDate":"1949-11-23","age":76},{"name":"Kent Karlsson","pos":"DF","num":19,"birthDate":"1945-11-25","age":80},{"name":"Roland Andersson","pos":"DF","num":20,"birthDate":"1950-03-28","age":76},{"name":"Sanny Åslund","pos":"FW","num":21,"birthDate":"1952-08-29","age":73},{"name":"Ralf Edström","pos":"FW","num":22,"birthDate":"1952-10-07","age":73}]},{"year":1974,"stage":"第二轮小组赛","manager":"Georg Ericson","cards":{"yellow":5,"red":0},"group":{"name":"Group B","standings":[{"pos":1,"team":"西德","p":3,"w":3,"d":0,"l":0,"gf":7,"ga":2,"pts":6},{"pos":2,"team":"波兰","p":3,"w":2,"d":0,"l":1,"gf":3,"ga":2,"pts":4},{"pos":3,"team":"瑞典","p":3,"w":1,"d":0,"l":2,"gf":4,"ga":6,"pts":2},{"pos":4,"team":"南斯拉夫","p":3,"w":0,"d":0,"l":3,"gf":2,"ga":6,"pts":0}]},"matches":[{"stage":"group stage","home":"瑞典","away":"保加利亚","homeScore":0,"awayScore":0,"extra":false,"pens":false,"penScore":"","goals":[],"venue":{"stadium":"Rheinstadion","city":"Düsseldorf","capacity":70000},"subs":[{"playerOff":"Ove Kindvall","playerOn":"Benno Magnusson","minute":"73'"},{"playerOff":"Pavel Panov","playerOn":"Mladen Vasilev","minute":"73'"},{"playerOff":"Voyn Voynov","playerOn":"Atanas Mihailov","minute":"75'"}]},{"stage":"group stage","home":"荷兰","away":"瑞典","homeScore":0,"awayScore":0,"extra":false,"pens":false,"penScore":"","goals":[],"venue":{"stadium":"Westfalenstadion","city":"Dortmund","capacity":65000},"subs":[{"playerOff":"Willem van Hanegem","playerOn":"Theo de Jong","minute":"73'"},{"playerOff":"Staffan Tapper","playerOn":"Örjan Persson","minute":"61'"},{"playerOff":"Jan Olsson","playerOn":"Roland Grip","minute":"75'"}]},{"stage":"group stage","home":"瑞典","away":"乌拉圭","homeScore":3,"awayScore":0,"extra":false,"pens":false,"penScore":"","goals":[{"player":"Ralf Edström","team":"瑞典","minute":"46'","penalty":false,"ownGoal":false},{"player":"Roland Sandberg","team":"瑞典","minute":"74'","penalty":false,"ownGoal":false},{"player":"Ralf Edström","team":"瑞典","minute":"77'","penalty":false,"ownGoal":false}],"venue":{"stadium":"Rheinstadion","city":"Düsseldorf","capacity":70000},"subs":[{"playerOff":"Benno Magnusson","playerOn":"Thomas Ahlström","minute":"60'"},{"playerOff":"Ove Kindvall","playerOn":"Conny Torstensson","minute":"76'"},{"playerOff":"Rubén Corbo","playerOn":"Luis Cubilla","minute":"43'"},{"playerOff":"Luis Garisto","playerOn":"Juan Carlos Masnik","minute":"46'"}]},{"stage":"second group stage","home":"瑞典","away":"波兰","homeScore":0,"awayScore":1,"extra":false,"pens":false,"penScore":"","goals":[{"player":"Grzegorz Lato","team":"波兰","minute":"43'","penalty":false,"ownGoal":false}],"venue":{"stadium":"Neckarstadion","city":"Stuttgart","capacity":72000},"subs":[{"playerOff":"Björn Andersson","playerOn":"Jörgen Augustsson","minute":"60'"},{"playerOff":"Staffan Tapper","playerOn":"Thomas Ahlström","minute":"80'"},{"playerOff":"Andrzej Szarmach","playerOn":"Kazimierz Kmiecik","minute":"62'"}]},{"stage":"second group stage","home":"西德","away":"瑞典","homeScore":4,"awayScore":2,"extra":false,"pens":false,"penScore":"","goals":[{"player":"Ralf Edström","team":"瑞典","minute":"24'","penalty":false,"ownGoal":false},{"player":"Wolfgang Overath","team":"西德","minute":"51'","penalty":false,"ownGoal":false},{"player":"Rainer Bonhof","team":"西德","minute":"52'","penalty":false,"ownGoal":false},{"player":"Roland Sandberg","team":"瑞典","minute":"53'","penalty":false,"ownGoal":false},{"player":"Jürgen Grabowski","team":"西德","minute":"76'","penalty":false,"ownGoal":false},{"player":"Uli Hoeneß","team":"西德","minute":"89'","penalty":true,"ownGoal":false}],"venue":{"stadium":"Rheinstadion","city":"Düsseldorf","capacity":70000},"subs":[{"playerOff":"Dieter Herzog","playerOn":"Jürgen Grabowski","minute":"64'"},{"playerOff":"Bernd Hölzenbein","playerOn":"Heinz Flohe","minute":"83'"},{"playerOff":"Bo Larsson","playerOn":"Inge Ejderstedt","minute":"32'"}]},{"stage":"second group stage","home":"瑞典","away":"南斯拉夫","homeScore":2,"awayScore":1,"extra":false,"pens":false,"penScore":"","goals":[{"player":"Ivica Šurjak","team":"南斯拉夫","minute":"27'","penalty":false,"ownGoal":false},{"player":"Ralf Edström","team":"瑞典","minute":"29'","penalty":false,"ownGoal":false},{"player":"Conny Torstensson","team":"瑞典","minute":"85'","penalty":false,"ownGoal":false}],"venue":{"stadium":"Rheinstadion","city":"Düsseldorf","capacity":70000},"subs":[{"playerOff":"Vladimir Petrović","playerOn":"Stanislav Karasi","minute":"70'"},{"playerOff":"Miroslav Pavlović","playerOn":"Luka Peruzović","minute":"78'"}]}],"squad":[{"name":"Ronnie Hellström","pos":"GK","num":1,"birthDate":"1949-02-21","age":77},{"name":"Jan Olsson","pos":"DF","num":2,"birthDate":"1942-03-30","age":84},{"name":"Kent Karlsson","pos":"DF","num":3,"birthDate":"1945-11-25","age":80},{"name":"Björn Nordqvist","pos":"DF","num":4,"birthDate":"1942-10-06","age":83},{"name":"Björn Andersson","pos":"DF","num":5,"birthDate":"1951-07-20","age":74},{"name":"Ove Grahn","pos":"MF","num":6,"birthDate":"1943-05-09","age":83},{"name":"Bo Larsson","pos":"MF","num":7,"birthDate":"1944-05-05","age":82},{"name":"Conny Torstensson","pos":"MF","num":8,"birthDate":"1949-08-28","age":76},{"name":"Ove Kindvall","pos":"FW","num":9,"birthDate":"1943-05-16","age":83},{"name":"Ralf Edström","pos":"FW","num":10,"birthDate":"1952-10-07","age":73},{"name":"Roland Sandberg","pos":"FW","num":11,"birthDate":"1946-12-16","age":79},{"name":"Sven-Gunnar Larsson","pos":"GK","num":12,"birthDate":"1940-05-10","age":86},{"name":"Roland Grip","pos":"DF","num":13,"birthDate":"1941-01-01","age":85},{"name":"Staffan Tapper","pos":"MF","num":14,"birthDate":"1948-07-10","age":77},{"name":"Benno Magnusson","pos":"MF","num":15,"birthDate":"1953-02-04","age":73},{"name":"Inge Ejderstedt","pos":"MF","num":16,"birthDate":"1946-12-24","age":79},{"name":"Göran Hagberg","pos":"GK","num":17,"birthDate":"1947-11-08","age":78},{"name":"Jörgen Augustsson","pos":"DF","num":18,"birthDate":"1952-10-28","age":73},{"name":"Claes Cronqvist","pos":"MF","num":19,"birthDate":"1944-10-15","age":81},{"name":"Sven Lindman","pos":"MF","num":20,"birthDate":"1942-04-19","age":84},{"name":"Örjan Persson","pos":"MF","num":21,"birthDate":"1942-08-27","age":83},{"name":"Thomas Ahlström","pos":"MF","num":22,"birthDate":"1952-07-17","age":73}]},{"year":1970,"stage":"小组赛","manager":"Orvar Bergmark","cards":{"yellow":2,"red":0},"group":{"name":"Group 2","standings":[{"pos":1,"team":"意大利","p":3,"w":1,"d":2,"l":0,"gf":1,"ga":0,"pts":4},{"pos":2,"team":"乌拉圭","p":3,"w":1,"d":1,"l":1,"gf":2,"ga":1,"pts":3},{"pos":3,"team":"瑞典","p":3,"w":1,"d":1,"l":1,"gf":2,"ga":2,"pts":3},{"pos":4,"team":"以色列","p":3,"w":0,"d":2,"l":1,"gf":1,"ga":3,"pts":2}]},"matches":[{"stage":"group stage","home":"意大利","away":"瑞典","homeScore":1,"awayScore":0,"extra":false,"pens":false,"penScore":"","goals":[{"player":"Angelo Domenghini","team":"意大利","minute":"10'","penalty":false,"ownGoal":false}],"venue":{"stadium":"La Bombonera","city":"Toluca","capacity":33000},"subs":[{"playerOff":"Comunardo Niccolai","playerOn":"Roberto Rosato","minute":"37'"},{"playerOff":"Leif Eriksson","playerOn":"Inge Ejderstedt","minute":"68'"},{"playerOff":"Bo Larsson","playerOn":"Göran Nicklasson","minute":"80'"}]},{"stage":"group stage","home":"瑞典","away":"以色列","homeScore":1,"awayScore":1,"extra":false,"pens":false,"penScore":"","goals":[{"player":"Tom Turesson","team":"瑞典","minute":"53'","penalty":false,"ownGoal":false},{"player":"Mordechai Spiegler","team":"以色列","minute":"56'","penalty":false,"ownGoal":false}],"venue":{"stadium":"La Bombonera","city":"Toluca","capacity":33000},"subs":[{"playerOff":"Örjan Persson","playerOn":"Sten Pålsson","minute":"75'"},{"playerOff":"Yochanan Vollach","playerOn":"Roni Shuruk","minute":"51'"}]},{"stage":"group stage","home":"瑞典","away":"乌拉圭","homeScore":1,"awayScore":0,"extra":false,"pens":false,"penScore":"","goals":[{"player":"Ove Grahn","team":"瑞典","minute":"90'","penalty":false,"ownGoal":false}],"venue":{"stadium":"Estadio Cuauhtémoc","city":"Puebla","capacity":46000},"subs":[{"playerOff":"Ove Kindvall","playerOn":"Tom Turesson","minute":"58'"},{"playerOff":"Göran Nicklasson","playerOn":"Ove Grahn","minute":"84'"},{"playerOff":"Víctor Espárrago","playerOn":"Dagoberto Fontes","minute":"61'"}]}],"squad":[{"name":"Ronnie Hellström","pos":"GK","num":1,"birthDate":"1949-02-21","age":77},{"name":"Hans Selander","pos":"DF","num":2,"birthDate":"1945-03-15","age":81},{"name":"Kurt Axelsson","pos":"DF","num":3,"birthDate":"1941-11-10","age":84},{"name":"Björn Nordqvist","pos":"DF","num":4,"birthDate":"1942-10-06","age":83},{"name":"Roland Grip","pos":"DF","num":5,"birthDate":"1941-01-01","age":85},{"name":"Tommy Svensson","pos":"MF","num":6,"birthDate":"1945-03-04","age":81},{"name":"Bo Larsson","pos":"MF","num":7,"birthDate":"1944-05-05","age":82},{"name":"Leif Eriksson","pos":"MF","num":8,"birthDate":"1942-03-20","age":84},{"name":"Ove Kindvall","pos":"MF","num":9,"birthDate":"1943-05-16","age":83},{"name":"Ove Grahn","pos":"MF","num":10,"birthDate":"1943-05-09","age":83},{"name":"Örjan Persson","pos":"MF","num":11,"birthDate":"1942-08-27","age":83},{"name":"Sven-Gunnar Larsson","pos":"GK","num":12,"birthDate":"1940-05-10","age":86},{"name":"Claes Cronqvist","pos":"MF","num":13,"birthDate":"1944-10-15","age":81},{"name":"Krister Kristensson","pos":"DF","num":14,"birthDate":"1942-07-25","age":83},{"name":"Leif Målberg","pos":"DF","num":15,"birthDate":"1945-09-01","age":80},{"name":"Tomas Nordahl","pos":"FW","num":16,"birthDate":"1946-05-24","age":80},{"name":"Ronney Pettersson","pos":"GK","num":17,"birthDate":"1940-04-26","age":86},{"name":"Tom Turesson","pos":"FW","num":18,"birthDate":"1942-05-17","age":84},{"name":"Göran Nicklasson","pos":"MF","num":19,"birthDate":"1942-08-20","age":83},{"name":"Jan Olsson","pos":"DF","num":20,"birthDate":"1944-03-18","age":82},{"name":"Inge Ejderstedt","pos":"FW","num":21,"birthDate":"1946-12-24","age":79},{"name":"Sten Pålsson","pos":"MF","num":22,"birthDate":"1945-12-04","age":80}]},{"year":1958,"stage":"亚军","manager":"George Raynor","cards":{"yellow":0,"red":0},"group":{"name":"Group 3","standings":[{"pos":1,"team":"瑞典","p":3,"w":2,"d":1,"l":0,"gf":5,"ga":1,"pts":5},{"pos":2,"team":"威尔士","p":3,"w":0,"d":3,"l":0,"gf":2,"ga":2,"pts":3},{"pos":3,"team":"匈牙利","p":3,"w":1,"d":1,"l":1,"gf":6,"ga":3,"pts":3},{"pos":4,"team":"墨西哥","p":3,"w":0,"d":1,"l":2,"gf":1,"ga":8,"pts":1}]},"matches":[{"stage":"group stage","home":"瑞典","away":"墨西哥","homeScore":3,"awayScore":0,"extra":false,"pens":false,"penScore":"","goals":[{"player":"Agne Simonsson","team":"瑞典","minute":"17'","penalty":false,"ownGoal":false},{"player":"Nils Liedholm","team":"瑞典","minute":"57'","penalty":true,"ownGoal":false},{"player":"Agne Simonsson","team":"瑞典","minute":"64'","penalty":false,"ownGoal":false}],"venue":{"stadium":"Råsunda Stadium","city":"Solna","capacity":52000}},{"stage":"group stage","home":"瑞典","away":"匈牙利","homeScore":2,"awayScore":1,"extra":false,"pens":false,"penScore":"","goals":[{"player":"Kurt Hamrin","team":"瑞典","minute":"34'","penalty":false,"ownGoal":false},{"player":"Kurt Hamrin","team":"瑞典","minute":"55'","penalty":false,"ownGoal":false},{"player":"Lajos Tichy","team":"匈牙利","minute":"77'","penalty":false,"ownGoal":false}],"venue":{"stadium":"Råsunda Stadium","city":"Solna","capacity":52000}},{"stage":"group stage","home":"瑞典","away":"威尔士","homeScore":0,"awayScore":0,"extra":false,"pens":false,"penScore":"","goals":[],"venue":{"stadium":"Råsunda Stadium","city":"Solna","capacity":52000}},{"stage":"quarter-finals","home":"瑞典","away":"苏联","homeScore":2,"awayScore":0,"extra":false,"pens":false,"penScore":"","goals":[{"player":"Kurt Hamrin","team":"瑞典","minute":"49'","penalty":false,"ownGoal":false},{"player":"Agne Simonsson","team":"瑞典","minute":"88'","penalty":false,"ownGoal":false}],"venue":{"stadium":"Råsunda Stadium","city":"Solna","capacity":52000}},{"stage":"semi-finals","home":"瑞典","away":"西德","homeScore":3,"awayScore":1,"extra":false,"pens":false,"penScore":"","goals":[{"player":"Hans Schäfer","team":"西德","minute":"24'","penalty":false,"ownGoal":false},{"player":"Lennart Skoglund","team":"瑞典","minute":"32'","penalty":false,"ownGoal":false},{"player":"Gunnar Gren","team":"瑞典","minute":"81'","penalty":false,"ownGoal":false},{"player":"Kurt Hamrin","team":"瑞典","minute":"88'","penalty":false,"ownGoal":false}],"venue":{"stadium":"Ullevi","city":"Gothenburg","capacity":54000}},{"stage":"final","home":"巴西","away":"瑞典","homeScore":5,"awayScore":2,"extra":false,"pens":false,"penScore":"","goals":[{"player":"Nils Liedholm","team":"瑞典","minute":"4'","penalty":false,"ownGoal":false},{"player":"Vavá","team":"巴西","minute":"9'","penalty":false,"ownGoal":false},{"player":"Vavá","team":"巴西","minute":"32'","penalty":false,"ownGoal":false},{"player":"Pelé","team":"巴西","minute":"55'","penalty":false,"ownGoal":false},{"player":"Mário Zagallo","team":"巴西","minute":"68'","penalty":false,"ownGoal":false},{"player":"Agne Simonsson","team":"瑞典","minute":"80'","penalty":false,"ownGoal":false},{"player":"Pelé","team":"巴西","minute":"90'","penalty":false,"ownGoal":false}],"venue":{"stadium":"Råsunda Stadium","city":"Solna","capacity":52000}}],"squad":[{"name":"Kalle Svensson","pos":"GK","num":1,"birthDate":"1925-11-11"},{"name":"Orvar Bergmark","pos":"DF","num":2,"birthDate":"1930-11-16"},{"name":"Sven Axbom","pos":"DF","num":3,"birthDate":"1926-10-15"},{"name":"Nils Liedholm","pos":"MF","num":4,"birthDate":"1922-10-08"},{"name":"Åke Johansson","pos":"DF","num":5,"birthDate":"1928-03-19"},{"name":"Sigge Parling","pos":"MF","num":6,"birthDate":"1930-03-26"},{"name":"Kurt Hamrin","pos":"MF","num":7,"birthDate":"1934-11-19"},{"name":"Gunnar Gren","pos":"FW","num":8,"birthDate":"1920-10-31"},{"name":"Agne Simonsson","pos":"FW","num":9,"birthDate":"1935-10-19","age":90},{"name":"Arne Selmosson","pos":"FW","num":10,"birthDate":"1931-03-29"},{"name":"Lennart Skoglund","pos":"MF","num":11,"birthDate":"1929-12-24"},{"name":"Tore Svensson","pos":"GK","num":12,"birthDate":"1927-12-06"},{"name":"Prawitz Öberg","pos":"DF","num":13,"birthDate":"1930-11-16"},{"name":"Bengt Gustavsson","pos":"DF","num":14,"birthDate":"1928-01-15"},{"name":"Reino Börjesson","pos":"MF","num":15,"birthDate":"1929-02-04"},{"name":"Ingemar Haraldsson","pos":"GK","num":16,"birthDate":"1928-02-03"},{"name":"Olle Håkansson","pos":"MF","num":17,"birthDate":"1927-02-22"},{"name":"Gösta Löfgren","pos":"FW","num":18,"birthDate":"1923-08-29"},{"name":"Henry Källgren","pos":"FW","num":19,"birthDate":"1931-03-13"},{"name":"Bror Mellberg","pos":"FW","num":20,"birthDate":"1923-12-09"},{"name":"Bengt Berndtsson","pos":"MF","num":21,"birthDate":"1933-01-26"},{"name":"Owe Ohlsson","pos":"FW","num":22,"birthDate":"1938-08-19","age":87}]},{"year":1950,"stage":"亚军","manager":"George Raynor","cards":{"yellow":0,"red":0},"group":{"name":"Group 1","standings":[{"pos":1,"team":"巴西","p":3,"w":2,"d":1,"l":0,"gf":8,"ga":2,"pts":5},{"pos":1,"team":"乌拉圭","p":3,"w":2,"d":1,"l":0,"gf":7,"ga":5,"pts":5},{"pos":2,"team":"南斯拉夫","p":3,"w":2,"d":0,"l":1,"gf":7,"ga":3,"pts":4},{"pos":2,"team":"巴西","p":3,"w":2,"d":0,"l":1,"gf":14,"ga":4,"pts":4},{"pos":3,"team":"瑞士","p":3,"w":1,"d":1,"l":1,"gf":4,"ga":6,"pts":3},{"pos":3,"team":"瑞典","p":3,"w":1,"d":0,"l":2,"gf":6,"ga":11,"pts":2},{"pos":4,"team":"墨西哥","p":3,"w":0,"d":0,"l":3,"gf":2,"ga":10,"pts":0},{"pos":4,"team":"西班牙","p":3,"w":0,"d":1,"l":2,"gf":4,"ga":11,"pts":1}]},"matches":[{"stage":"group stage","home":"瑞典","away":"意大利","homeScore":3,"awayScore":2,"extra":false,"pens":false,"penScore":"","goals":[{"player":"Riccardo Carapellese","team":"意大利","minute":"7'","penalty":false,"ownGoal":false},{"player":"Hasse Jeppson","team":"瑞典","minute":"25'","penalty":false,"ownGoal":false},{"player":"Sune Andersson","team":"瑞典","minute":"33'","penalty":false,"ownGoal":false},{"player":"Hasse Jeppson","team":"瑞典","minute":"68'","penalty":false,"ownGoal":false},{"player":"Ermes Muccinelli","team":"意大利","minute":"75'","penalty":false,"ownGoal":false}],"venue":{"stadium":"Estádio do Pacaembu","city":"São Paulo","capacity":60000}},{"stage":"group stage","home":"瑞典","away":"巴拉圭","homeScore":2,"awayScore":2,"extra":false,"pens":false,"penScore":"","goals":[{"player":"Stig Sundqvist","team":"瑞典","minute":"17'","penalty":false,"ownGoal":false},{"player":"Karl-Erik Palmér","team":"瑞典","minute":"26'","penalty":false,"ownGoal":false},{"player":"Atilio López","team":"巴拉圭","minute":"35'","penalty":false,"ownGoal":false},{"player":"César López Fretes","team":"巴拉圭","minute":"74'","penalty":false,"ownGoal":false}],"venue":{"stadium":"Estádio Vila Capanema","city":"Curitiba","capacity":10000}},{"stage":"final round","home":"巴西","away":"瑞典","homeScore":7,"awayScore":1,"extra":false,"pens":false,"penScore":"","goals":[{"player":"Ademir","team":"巴西","minute":"17'","penalty":false,"ownGoal":false},{"player":"Ademir","team":"巴西","minute":"36'","penalty":false,"ownGoal":false},{"player":"Chico","team":"巴西","minute":"39'","penalty":false,"ownGoal":false},{"player":"Ademir","team":"巴西","minute":"52'","penalty":false,"ownGoal":false},{"player":"Ademir","team":"巴西","minute":"58'","penalty":false,"ownGoal":false},{"player":"Sune Andersson","team":"瑞典","minute":"67'","penalty":true,"ownGoal":false},{"player":"Maneca","team":"巴西","minute":"85'","penalty":false,"ownGoal":false},{"player":"Chico","team":"巴西","minute":"88'","penalty":false,"ownGoal":false}],"venue":{"stadium":"Estádio do Maracanã","city":"Rio de Janeiro","capacity":200000}},{"stage":"final round","home":"乌拉圭","away":"瑞典","homeScore":3,"awayScore":2,"extra":false,"pens":false,"penScore":"","goals":[{"player":"Karl-Erik Palmér","team":"瑞典","minute":"5'","penalty":false,"ownGoal":false},{"player":"Alcides Ghiggia","team":"乌拉圭","minute":"39'","penalty":false,"ownGoal":false},{"player":"Stig Sundqvist","team":"瑞典","minute":"40'","penalty":false,"ownGoal":false},{"player":"Oscar Míguez","team":"乌拉圭","minute":"77'","penalty":false,"ownGoal":false},{"player":"Oscar Míguez","team":"乌拉圭","minute":"85'","penalty":false,"ownGoal":false}],"venue":{"stadium":"Estádio do Pacaembu","city":"São Paulo","capacity":60000}},{"stage":"final round","home":"瑞典","away":"西班牙","homeScore":3,"awayScore":1,"extra":false,"pens":false,"penScore":"","goals":[{"player":"Stig Sundqvist","team":"瑞典","minute":"15'","penalty":false,"ownGoal":false},{"player":"Bror Mellberg","team":"瑞典","minute":"33'","penalty":false,"ownGoal":false},{"player":"Karl-Erik Palmér","team":"瑞典","minute":"80'","penalty":false,"ownGoal":false},{"player":"Telmo Zarra","team":"西班牙","minute":"82'","penalty":false,"ownGoal":false}],"venue":{"stadium":"Estádio do Pacaembu","city":"São Paulo","capacity":60000}}],"squad":[{"name":"Olle Åhlund","pos":"MF","num":0,"birthDate":"1920-08-22"},{"name":"Sune Andersson","pos":"MF","num":0,"birthDate":"1921-02-22"},{"name":"Ingvar Gärd","pos":"MF","num":0,"birthDate":"1921-10-06"},{"name":"Hasse Jeppson","pos":"FW","num":0,"birthDate":"1925-05-10"},{"name":"Gunnar Johansson","pos":"DF","num":0,"birthDate":"1924-02-29"},{"name":"Egon Jönsson","pos":"FW","num":0,"birthDate":"1921-10-08"},{"name":"Torsten Lindberg","pos":"GK","num":0,"birthDate":"1917-04-14"},{"name":"Arne Månsson","pos":"DF","num":0,"birthDate":"1925-11-11"},{"name":"Bror Mellberg","pos":"FW","num":0,"birthDate":"1923-12-09"},{"name":"Erik Nilsson","pos":"DF","num":0,"birthDate":"1916-08-06"},{"name":"Stellan Nilsson","pos":"FW","num":0,"birthDate":"1922-05-28"},{"name":"Knut Nordahl","pos":"MF","num":0,"birthDate":"1920-01-13"},{"name":"Karl-Erik Palmér","pos":"FW","num":0,"birthDate":"1929-04-17"},{"name":"Kjell Rosén","pos":"MF","num":0,"birthDate":"1921-04-24"},{"name":"Ingvar Rydell","pos":"FW","num":0,"birthDate":"1922-05-07"},{"name":"Lennart Samuelsson","pos":"DF","num":0,"birthDate":"1924-07-07"},{"name":"Lennart Skoglund","pos":"FW","num":0,"birthDate":"1929-12-24"},{"name":"Stig Sundqvist","pos":"FW","num":0,"birthDate":"1922-07-19"},{"name":"Kalle Svensson","pos":"GK","num":0,"birthDate":"1925-11-11"},{"name":"Kurt Svensson","pos":"FW","num":0,"birthDate":"1927-04-15"},{"name":"Tore Svensson","pos":"GK","num":0,"birthDate":"1927-12-06"},{"name":"Börje Tapper","pos":"FW","num":0,"birthDate":"1922-05-20"}]},{"year":1938,"stage":"季军赛","manager":"József Nagy","cards":{"yellow":0,"red":0},"matches":[{"stage":"quarter-finals","home":"瑞典","away":"古巴","homeScore":8,"awayScore":0,"extra":false,"pens":false,"penScore":"","goals":[{"player":"Harry Andersson","team":"瑞典","minute":"9'","penalty":false,"ownGoal":false},{"player":"Gustav Wetterström","team":"瑞典","minute":"22'","penalty":false,"ownGoal":false},{"player":"Gustav Wetterström","team":"瑞典","minute":"37'","penalty":false,"ownGoal":false},{"player":"Gustav Wetterström","team":"瑞典","minute":"44'","penalty":false,"ownGoal":false},{"player":"Tore Keller","team":"瑞典","minute":"80'","penalty":false,"ownGoal":false},{"player":"Harry Andersson","team":"瑞典","minute":"81'","penalty":false,"ownGoal":false},{"player":"Arne Nyberg","team":"瑞典","minute":"84'","penalty":false,"ownGoal":false},{"player":"Harry Andersson","team":"瑞典","minute":"89'","penalty":false,"ownGoal":false}],"venue":{"stadium":"Stade du Fort Carré","city":"Antibes","capacity":7000}},{"stage":"semi-finals","home":"匈牙利","away":"瑞典","homeScore":5,"awayScore":1,"extra":false,"pens":false,"penScore":"","goals":[{"player":"Arne Nyberg","team":"瑞典","minute":"1'","penalty":false,"ownGoal":false},{"player":"Sven Jacobsson","team":"匈牙利","minute":"19'","penalty":false,"ownGoal":true},{"player":"Pál Titkos","team":"匈牙利","minute":"37'","penalty":false,"ownGoal":false},{"player":"Gyula Zsengellér","team":"匈牙利","minute":"39'","penalty":false,"ownGoal":false},{"player":"György Sárosi","team":"匈牙利","minute":"65'","penalty":false,"ownGoal":false},{"player":"Gyula Zsengellér","team":"匈牙利","minute":"85'","penalty":false,"ownGoal":false}],"venue":{"stadium":"Parc des Princes","city":"Paris","capacity":49000}},{"stage":"third-place match","home":"巴西","away":"瑞典","homeScore":4,"awayScore":2,"extra":false,"pens":false,"penScore":"","goals":[{"player":"Sven Jonasson","team":"瑞典","minute":"28'","penalty":false,"ownGoal":false},{"player":"Arne Nyberg","team":"瑞典","minute":"38'","penalty":false,"ownGoal":false},{"player":"Romeu","team":"巴西","minute":"44'","penalty":false,"ownGoal":false},{"player":"Leônidas","team":"巴西","minute":"63'","penalty":false,"ownGoal":false},{"player":"Leônidas","team":"巴西","minute":"74'","penalty":false,"ownGoal":false},{"player":"Perácio","team":"巴西","minute":"80'","penalty":false,"ownGoal":false}],"venue":{"stadium":"Stade du Parc Lescure","city":"Bordeaux","capacity":35000}}],"squad":[{"name":"Henock Abrahamsson","pos":"GK","num":0,"birthDate":"1909-10-29"},{"name":"Erik Almgren","pos":"MF","num":0,"birthDate":"1908-01-28"},{"name":"Åke Andersson","pos":"FW","num":0,"birthDate":"1917-04-22"},{"name":"Harry Andersson","pos":"FW","num":0,"birthDate":"1913-03-07"},{"name":"Curt Bergsten","pos":"FW","num":0,"birthDate":"1915-08-21"},{"name":"Lennart Bunke","pos":"FW","num":0,"birthDate":"1912-04-03"},{"name":"Ivar Eriksson","pos":"DF","num":0,"birthDate":"1909-12-25"},{"name":"Karl-Erik Grahn","pos":"MF","num":0,"birthDate":"1914-11-05"},{"name":"Knut Hansson","pos":"FW","num":0,"birthDate":"1911-05-09"},{"name":"Sven Jacobsson","pos":"MF","num":0,"birthDate":"1914-04-17"},{"name":"Sven Jonasson","pos":"FW","num":0,"birthDate":"1909-07-09"},{"name":"Olle Källgren","pos":"DF","num":0,"birthDate":"1907-09-07"},{"name":"Tore Keller","pos":"FW","num":0,"birthDate":"1905-01-04"},{"name":"Arne Linderholm","pos":"MF","num":0,"birthDate":"1916-02-22"},{"name":"Erik Nilsson","pos":"DF","num":0,"birthDate":"1916-08-06"},{"name":"Harry Nilsson","pos":"DF","num":0,"birthDate":"not available"},{"name":"Arne Nyberg","pos":"FW","num":0,"birthDate":"1913-06-20"},{"name":"Erik Persson","pos":"FW","num":0,"birthDate":"1909-11-19"},{"name":"Gustav Sjöberg","pos":"GK","num":0,"birthDate":"1913-03-23"},{"name":"Kurt Svanström","pos":"MF","num":0,"birthDate":"1915-03-24"},{"name":"Sven Unger","pos":"FW","num":0,"birthDate":"not available"},{"name":"Gustav Wetterström","pos":"FW","num":0,"birthDate":"1911-10-15"}]},{"year":1934,"stage":"八强","manager":"John Pettersson","cards":{"yellow":0,"red":0},"matches":[{"stage":"round of 16","home":"瑞典","away":"阿根廷","homeScore":3,"awayScore":2,"extra":false,"pens":false,"penScore":"","goals":[{"player":"Ernesto Belis","team":"阿根廷","minute":"4'","penalty":false,"ownGoal":false},{"player":"Sven Jonasson","team":"瑞典","minute":"9'","penalty":false,"ownGoal":false},{"player":"Alberto Galateo","team":"阿根廷","minute":"48'","penalty":false,"ownGoal":false},{"player":"Sven Jonasson","team":"瑞典","minute":"67'","penalty":false,"ownGoal":false},{"player":"Knut Kroon","team":"瑞典","minute":"79'","penalty":false,"ownGoal":false}],"venue":{"stadium":"Stadio Renato Dall'Ara","city":"Bologna","capacity":50000}},{"stage":"quarter-finals","home":"德国","away":"瑞典","homeScore":2,"awayScore":1,"extra":false,"pens":false,"penScore":"","goals":[{"player":"Karl Hohmann","team":"德国","minute":"60'","penalty":false,"ownGoal":false},{"player":"Karl Hohmann","team":"德国","minute":"63'","penalty":false,"ownGoal":false},{"player":"Gösta Dunker","team":"瑞典","minute":"82'","penalty":false,"ownGoal":false}],"venue":{"stadium":"San Siro","city":"Milan","capacity":75000}}],"squad":[{"name":"Ernst Andersson","pos":"MF","num":0,"birthDate":"1909-03-26"},{"name":"Otto Andersson","pos":"DF","num":0,"birthDate":"1910-05-07"},{"name":"Sven Andersson","pos":"DF","num":0,"birthDate":"1907-02-14"},{"name":"Nils Axelsson","pos":"DF","num":0,"birthDate":"1906-01-18"},{"name":"Lennart Bunke","pos":"FW","num":0,"birthDate":"1912-04-03"},{"name":"Rune Carlsson","pos":"MF","num":0,"birthDate":"1909-10-01"},{"name":"Victor Carlund","pos":"MF","num":0,"birthDate":"1906-02-05"},{"name":"Gösta Dunker","pos":"FW","num":0,"birthDate":"1905-09-16"},{"name":"Erik Granath","pos":"MF","num":0,"birthDate":"not available"},{"name":"Ragnar Gustavsson","pos":"FW","num":0,"birthDate":"1907-09-28"},{"name":"Carl-Erik Holmberg","pos":"FW","num":0,"birthDate":"1906-07-17"},{"name":"Sture Hult","pos":"GK","num":0,"birthDate":"1910-10-19"},{"name":"Gunnar Jansson","pos":"FW","num":0,"birthDate":"1907-07-17"},{"name":"Carl Johnsson","pos":"MF","num":0,"birthDate":"not available"},{"name":"Sven Jonasson","pos":"FW","num":0,"birthDate":"1909-07-09"},{"name":"Tore Keller","pos":"FW","num":0,"birthDate":"1905-01-04"},{"name":"Knut Kroon","pos":"FW","num":0,"birthDate":"1906-06-19"},{"name":"Harry Lundahl","pos":"FW","num":0,"birthDate":"1905-10-16"},{"name":"Gunnar Olsson","pos":"FW","num":0,"birthDate":"1908-07-19"},{"name":"Nils Rosén","pos":"MF","num":0,"birthDate":"1902-05-22"},{"name":"Anders Rydberg","pos":"GK","num":0,"birthDate":"1903-03-03"},{"name":"Arvid Thörn","pos":"FW","num":0,"birthDate":"1906-10-29"},{"name":"Eivar Widlund","pos":"GK","num":0,"birthDate":"1905-06-15"}]}]}